Workbook
Name IDX: 'Medicare Enrolments'!$A$3

Sheet Labour - Prices
V1: Year 0 | AE1: Year 1 | AN1: Year 2 | AW1: Year 3 | BF1: Year 4
A2: Jurisdiction | B2: Personnel type | C2: Label | D2: Award | E2: Grade(s) | V2: Base Salary | Y2: Base Salary + Costs | AB2: Base Salary + Costs (hourly) | AE2: Base Salary | AH2: Base Salary + Costs | AK2: Base Salary + Costs (hourly) | AN2: Base Salary | AQ2: Base Salary + Costs | AT2: Base Salary + Costs (hourly) | AW2: Base Salary | AZ2: Base Salary + Costs | BC2: Base Salary + Costs (hourly) | BF2: Base Salary | BI2: Base Salary + Costs | BL2: Base Salary + Costs (hourly)
F3: Distribution desc | G3: References | H3: Rate of Pay (weekly, 38h) desc | I3: Year | J3: Superannuation Rate (%) | K3: Hours per week | L3: Average productive time (%) | M3: Average Penalties % | N3: Public Holiday Penalty % | O3: Private Practice Loading % | P3: Attraction and Retention Allowance % | Q3: Sick Leave % | R3: Professional Development Allowance ($) | S3: Annual Leave Entitlement (Weeks) | T3: Annual Leave Loading (%) | U3: Indexation per annum (%) | V3: LL | W3: Mid-point | X3: UL | Y3: LL | Z3: Mid-point | AA3: UL | AB3: LL | AC3: Mid-point | AD3: UL | AE3: LL | AF3: Mid-point | AG3: UL | AH3: LL | AI3: Mid-point | AJ3: UL | AK3: LL | AL3: Mid-point | AM3: UL | AN3: LL | AO3: Mid-point | AP3: UL | AQ3: LL | AR3: Mid-point | AS3: UL | AT3: LL | AU3: Mid-point | AV3: UL | AW3: LL | AX3: Mid-point | AY3: UL | AZ3: LL | BA3: Mid-point | BB3: UL | BC3: LL | BD3: Mid-point | BE3: UL | BF3: LL | BG3: Mid-point | BH3: UL | BI3: LL | BJ3: Mid-point | BK3: UL | BL3: LL | BM3: Mid-point | BN3: UL
A4: VIC | B4: Lab technician | C4: LT | D4: HPA | E4: 5-7 | F4: normal distro | G4: pp247 HS5-HS7 (July 22) | H4: 1785.7-2257.10 | I4: 2022 | J4: 0.105 | K4: 38 | L4: 1 | M4: 0.1 | N4: 0.035 | O4: 0 | P4: 0 | Q4: 0.046 | R4: 0 | S4: 4 | T4: 0.175 | U4: 0.015 | V4: 79624 | W4: =V4+((X4-V4)/2) -> 94969 | X4: 110314 | Y4: =(V4+(V4*$J4)+(V4*$M4)+(V4*$N4)+(V4*$O4)+(V4*$P4)+(V4*$Q4)+($R4)+(V4*((52+$S4)/52))*(1+$T4))*1/$L4 -> 203151.45 | Z4: =(W4+(W4*$J4)+(W4*$M4)+(W4*$N4)+(W4*$O4)+(W4*$P4)+(W4*$Q4)+($R4)+(W4*((52+$S4)/52))*(1+$T4))*1/$L4 -> 242302.45 | AA4: =(X4+(X4*$J4)+(X4*$M4)+(X4*$N4)+(X4*$O4)+(X4*$P4)+(X4*$Q4)+($R4)+(X4*((52+$S4)/52))*(1+$T4))*1/$L4 -> 281453.44 | AB4: =Y4/52/$K4 -> 102.80944 | AC4: =Z4/52/$K4 -> 122.6227 | AD4: =AA4/52/$K4 -> 142.43595 | AE4: =($V4*(1+(($U4/100)*1))) -> 79635.944 | AF4: =($W4*(1+(($U4/100)*1))) -> 94983.245 | AG4: =($X4*(1+(($U4/100)*1))) -> 110330.55 | AH4: =(AE4+(AE4*$J4)+(AE4*$M4)+(AE4*$N4)+(AE4*$O4)+(AE4*$P4)+(AE4*$Q4)+($R4)+(AE4*((52+$S4)/52))*(1+$T4))*1/$L4 -> 203181.92 | AI4: =(AF4+(AF4*$J4)+(AF4*$M4)+(AF4*$N4)+(AF4*$O4)+(AF4*$P4)+(AF4*$Q4)+($R4)+(AF4*((52+$S4)/52))*(1+$T4))*1/$L4 -> 242338.79 | AJ4: =(AG4+(AG4*$J4)+(AG4*$M4)+(AG4*$N4)+(AG4*$O4)+(AG4*$P4)+(AG4*$Q4)+($R4)+(AG4*((52+$S4)/52))*(1+$T4))*1/$L4 -> 281495.66 | AK4: =AH4/52/$K4 -> 102.82486 | AL4: =AI4/52/$K4 -> 122.64109 | AM4: =AJ4/52/$K4 -> 142.45732 | AN4: =($V4*(1+(($U4/100)*2))) -> 79647.887 | AO4: =($W4*(1+(($U4/100)*2))) -> 94997.491 | AP4: =($X4*(1+(($U4/100)*2))) -> 110347.09 | AQ4: =(AN4+(AN4*$J4)+(AN4*$M4)+(AN4*$N4)+(AN4*$O4)+(AN4*$P4)+(AN4*$Q4)+($R4)+(AN4*((52+$S4)/52))*(1+$T4))*1/$L4 -> 203212.39 | AR4: =(AO4+(AO4*$J4)+(AO4*$M4)+(AO4*$N4)+(AO4*$O4)+(AO4*$P4)+(AO4*$Q4)+($R4)+(AO4*((52+$S4)/52))*(1+$T4))*1/$L4 -> 242375.14 | AS4: =(AP4+(AP4*$J4)+(AP4*$M4)+(AP4*$N4)+(AP4*$O4)+(AP4*$P4)+(AP4*$Q4)+($R4)+(AP4*((52+$S4)/52))*(1+$T4))*1/$L4 -> 281537.88 | AT4: =AQ4/52/$K4 -> 102.84028 | AU4: =AR4/52/$K4 -> 122.65948 | AV4: =AS4/52/$K4 -> 142.47868 | AW4: =($V4*(1+(($U4/100)*3))) -> 79659.831 | AX4: =($W4*(1+(($U4/100)*3))) -> 95011.736 | AY4: =($X4*(1+(($U4/100)*3))) -> 110363.64 | AZ4: =(AW4+(AW4*$J4)+(AW4*$M4)+(AW4*$N4)+(AW4*$O4)+(AW4*$P4)+(AW4*$Q4)+($R4)+(AW4*((52+$S4)/52))*(1+$T4))*1/$L4 -> 203242.87 | BA4: =(AX4+(AX4*$J4)+(AX4*$M4)+(AX4*$N4)+(AX4*$O4)+(AX4*$P4)+(AX4*$Q4)+($R4)+(AX4*((52+$S4)/52))*(1+$T4))*1/$L4 -> 242411.48 | BB4: =(AY4+(AY4*$J4)+(AY4*$M4)+(AY4*$N4)+(AY4*$O4)+(AY4*$P4)+(AY4*$Q4)+($R4)+(AY4*((52+$S4)/52))*(1+$T4))*1/$L4 -> 281580.1 | BC4: =AZ4/52/$K4 -> 102.8557 | BD4: =BA4/52/$K4 -> 122.67788 | BE4: =BB4/52/$K4 -> 142.50005 | BF4: =($V4*(1+(($U4/100)*4))) -> 79671.774 | BG4: =($W4*(1+(($U4/100)*4))) -> 95025.981 | BH4: =($X4*(1+(($U4/100)*4))) -> 110380.19 | BI4: =(BF4+(BF4*$J4)+(BF4*$M4)+(BF4*$N4)+(BF4*$O4)+(BF4*$P4)+(BF4*$Q4)+($R4)+(BF4*((52+$S4)/52))*(1+$T4))*1/$L4 -> 203273.34 | BJ4: =(BG4+(BG4*$J4)+(BG4*$M4)+(BG4*$N4)+(BG4*$O4)+(BG4*$P4)+(BG4*$Q4)+($R4)+(BG4*((52+$S4)/52))*(1+$T4))*1/$L4 -> 242447.83 | BK4: =(BH4+(BH4*$J4)+(BH4*$M4)+(BH4*$N4)+(BH4*$O4)+(BH4*$P4)+(BH4*$Q4)+($R4)+(BH4*((52+$S4)/52))*(1+$T4))*1/$L4 -> 281622.31 | BL4: =BI4/52/$K4 -> 102.87112 | BM4: =BJ4/52/$K4 -> 122.69627 | BN4: =BK4/52/$K4 -> 142.52141
A5: VIC | B5: Medical scientist | C5: MS | D5: MSEBA | E5: MS1-4(RX4)-MS4-5(RZ7) | F5: skewed normal | G5: pp111 VPHS 2017-21 RX1-RZ7 | H5: 1131.30-2622.00 | I5: 2023 | J5: 0.105 | K5: 38 | L5: 1 | M5: 0.1 | N5: 0.035 | O5: 0 | P5: 0 | Q5: 0.046 | R5: 0 | S5: 5 | T5: 0.175 | U5: 0.015 | V5: =1177*52 -> 61204 | W5: =V5+((X5-V5)/2) -> 101878.4 | X5: =2741.4*52 -> 142552.8 | Y5: =(V5+(V5*$J5)+(V5*$M5)+(V5*$N5)+(V5*$O5)+(V5*$P5)+(V5*$Q5)+($R5)+(V5*((52+$S5)/52))*(1+$T5))*1/$L5 -> 157537.92 | Z5: =(W5+(W5*$J5)+(W5*$M5)+(W5*$N5)+(W5*$O5)+(W5*$P5)+(W5*$Q5)+($R5)+(W5*((52+$S5)/52))*(1+$T5))*1/$L5 -> 262233.04 | AA5: =(X5+(X5*$J5)+(X5*$M5)+(X5*$N5)+(X5*$O5)+(X5*$P5)+(X5*$Q5)+($R5)+(X5*((52+$S5)/52))*(1+$T5))*1/$L5 -> 366928.17 | AB5: =Y5/52/$K5 -> 79.725668 | AC5: =Z5/52/$K5 -> 132.70903 | AD5: =AA5/52/$K5 -> 185.69239 | AE5: =($V5*(1+(($U5/100)*1))) -> 61213.181 | AF5: =($W5*(1+(($U5/100)*1))) -> 101893.68 | AG5: =($X5*(1+(($U5/100)*1))) -> 142574.18 | AH5: =(AE5+(AE5*$J5)+(AE5*$M5)+(AE5*$N5)+(AE5*$O5)+(AE5*$P5)+(AE5*$Q5)+($R5)+(AE5*((52+$S5)/52))*(1+$T5))*1/$L5 -> 157561.55 | AI5: =(AF5+(AF5*$J5)+(AF5*$M5)+(AF5*$N5)+(AF5*$O5)+(AF5*$P5)+(AF5*$Q5)+($R5)+(AF5*((52+$S5)/52))*(1+$T5))*1/$L5 -> 262272.38 | AJ5: =(AG5+(AG5*$J5)+(AG5*$M5)+(AG5*$N5)+(AG5*$O5)+(AG5*$P5)+(AG5*$Q5)+($R5)+(AG5*((52+$S5)/52))*(1+$T5))*1/$L5 -> 366983.21 | AK5: =AH5/52/$K5 -> 79.737626 | AL5: =AI5/52/$K5 -> 132.72894 | AM5: =AJ5/52/$K5 -> 185.72025 | AN5: =($V5*(1+(($U5/100)*2))) -> 61222.361 | AO5: =($W5*(1+(($U5/100)*2))) -> 101908.96 | AP5: =($X5*(1+(($U5/100)*2))) -> 142595.57 | AQ5: =(AN5+(AN5*$J5)+(AN5*$M5)+(AN5*$N5)+(AN5*$O5)+(AN5*$P5)+(AN5*$Q5)+($R5)+(AN5*((52+$S5)/52))*(1+$T5))*1/$L5 -> 157585.18 | AR5: =(AO5+(AO5*$J5)+(AO5*$M5)+(AO5*$N5)+(AO5*$O5)+(AO5*$P5)+(AO5*$Q5)+($R5)+(AO5*((52+$S5)/52))*(1+$T5))*1/$L5 -> 262311.71 | AS5: =(AP5+(AP5*$J5)+(AP5*$M5)+(AP5*$N5)+(AP5*$O5)+(AP5*$P5)+(AP5*$Q5)+($R5)+(AP5*((52+$S5)/52))*(1+$T5))*1/$L5 -> 367038.24 | AT5: =AQ5/52/$K5 -> 79.749585 | AU5: =AR5/52/$K5 -> 132.74884 | AV5: =AS5/52/$K5 -> 185.7481 | AW5: =($V5*(1+(($U5/100)*3))) -> 61231.542 | AX5: =($W5*(1+(($U5/100)*3))) -> 101924.25 | AY5: =($X5*(1+(($U5/100)*3))) -> 142616.95 | AZ5: =(AW5+(AW5*$J5)+(AW5*$M5)+(AW5*$N5)+(AW5*$O5)+(AW5*$P5)+(AW5*$Q5)+($R5)+(AW5*((52+$S5)/52))*(1+$T5))*1/$L5 -> 157608.81 | BA5: =(AX5+(AX5*$J5)+(AX5*$M5)+(AX5*$N5)+(AX5*$O5)+(AX5*$P5)+(AX5*$Q5)+($R5)+(AX5*((52+$S5)/52))*(1+$T5))*1/$L5 -> 262351.05 | BB5: =(AY5+(AY5*$J5)+(AY5*$M5)+(AY5*$N5)+(AY5*$O5)+(AY5*$P5)+(AY5*$Q5)+($R5)+(AY5*((52+$S5)/52))*(1+$T5))*1/$L5 -> 367093.28 | BC5: =AZ5/52/$K5 -> 79.761544 | BD5: =BA5/52/$K5 -> 132.76875 | BE5: =BB5/52/$K5 -> 185.77595 | BF5: =($V5*(1+(($U5/100)*4))) -> 61240.722 | BG5: =($W5*(1+(($U5/100)*4))) -> 101939.53 | BH5: =($X5*(1+(($U5/100)*4))) -> 142638.33 | BI5: =(BF5+(BF5*$J5)+(BF5*$M5)+(BF5*$N5)+(BF5*$O5)+(BF5*$P5)+(BF5*$Q5)+($R5)+(BF5*((52+$S5)/52))*(1+$T5))*1/$L5 -> 157632.44 | BJ5: =(BG5+(BG5*$J5)+(BG5*$M5)+(BG5*$N5)+(BG5*$O5)+(BG5*$P5)+(BG5*$Q5)+($R5)+(BG5*((52+$S5)/52))*(1+$T5))*1/$L5 -> 262390.38 | BK5: =(BH5+(BH5*$J5)+(BH5*$M5)+(BH5*$N5)+(BH5*$O5)+(BH5*$P5)+(BH5*$Q5)+($R5)+(BH5*((52+$S5)/52))*(1+$T5))*1/$L5 -> 367148.32 | BL5: =BI5/52/$K5 -> 79.773503 | BM5: =BJ5/52/$K5 -> 132.78865 | BN5: =BK5/52/$K5 -> 185.80381
A6: VIC | B6: Admin staff | C6: AS | D6: HPA | E6: 3-5 | G6: pp247 HS5-HS7 (July 22) | H6: 1785.7-2257.10 | I6: 2022 | J6: 0.105 | K6: 38 | L6: 1 | M6: 0.1 | N6: 0.035 | O6: 0 | P6: 0 | Q6: 0.046 | R6: 0 | S6: 4 | T6: 0.175 | U6: 0.015 | V6: 63701 | W6: =V6+((X6-V6)/2) -> 77580.5 | X6: 91460 | Y6: =(V6+(V6*$J6)+(V6*$M6)+(V6*$N6)+(V6*$O6)+(V6*$P6)+(V6*$Q6)+($R6)+(V6*((52+$S6)/52))*(1+$T6))*1/$L6 -> 162525.75 | Z6: =(W6+(W6*$J6)+(W6*$M6)+(W6*$N6)+(W6*$O6)+(W6*$P6)+(W6*$Q6)+($R6)+(W6*((52+$S6)/52))*(1+$T6))*1/$L6 -> 197937.69 | AA6: =(X6+(X6*$J6)+(X6*$M6)+(X6*$N6)+(X6*$O6)+(X6*$P6)+(X6*$Q6)+($R6)+(X6*((52+$S6)/52))*(1+$T6))*1/$L6 -> 233349.64 | AB6: =Y6/52/$K6 -> 82.249874 | AC6: =Z6/52/$K6 -> 100.1709 | AD6: =AA6/52/$K6 -> 118.09192 | AE6: =($V6*(1+(($U6/100)*1))) -> 63710.555 | AF6: =($W6*(1+(($U6/100)*1))) -> 77592.137 | AG6: =($X6*(1+(($U6/100)*1))) -> 91473.719 | AH6: =(AE6+(AE6*$J6)+(AE6*$M6)+(AE6*$N6)+(AE6*$O6)+(AE6*$P6)+(AE6*$Q6)+($R6)+(AE6*((52+$S6)/52))*(1+$T6))*1/$L6 -> 162550.13 | AI6: =(AF6+(AF6*$J6)+(AF6*$M6)+(AF6*$N6)+(AF6*$O6)+(AF6*$P6)+(AF6*$Q6)+($R6)+(AF6*((52+$S6)/52))*(1+$T6))*1/$L6 -> 197967.38 | AJ6: =(AG6+(AG6*$J6)+(AG6*$M6)+(AG6*$N6)+(AG6*$O6)+(AG6*$P6)+(AG6*$Q6)+($R6)+(AG6*((52+$S6)/52))*(1+$T6))*1/$L6 -> 233384.64 | AK6: =AH6/52/$K6 -> 82.262212 | AL6: =AI6/52/$K6 -> 100.18592 | AM6: =AJ6/52/$K6 -> 118.10964 | AN6: =($V6*(1+(($U6/100)*2))) -> 63720.11 | AO6: =($W6*(1+(($U6/100)*2))) -> 77603.774 | AP6: =($X6*(1+(($U6/100)*2))) -> 91487.438 | AQ6: =(AN6+(AN6*$J6)+(AN6*$M6)+(AN6*$N6)+(AN6*$O6)+(AN6*$P6)+(AN6*$Q6)+($R6)+(AN6*((52+$S6)/52))*(1+$T6))*1/$L6 -> 162574.51 | AR6: =(AO6+(AO6*$J6)+(AO6*$M6)+(AO6*$N6)+(AO6*$O6)+(AO6*$P6)+(AO6*$Q6)+($R6)+(AO6*((52+$S6)/52))*(1+$T6))*1/$L6 -> 197997.08 | AS6: =(AP6+(AP6*$J6)+(AP6*$M6)+(AP6*$N6)+(AP6*$O6)+(AP6*$P6)+(AP6*$Q6)+($R6)+(AP6*((52+$S6)/52))*(1+$T6))*1/$L6 -> 233419.64 | AT6: =AQ6/52/$K6 -> 82.274549 | AU6: =AR6/52/$K6 -> 100.20095 | AV6: =AS6/52/$K6 -> 118.12735 | AW6: =($V6*(1+(($U6/100)*3))) -> 63729.665 | AX6: =($W6*(1+(($U6/100)*3))) -> 77615.411 | AY6: =($X6*(1+(($U6/100)*3))) -> 91501.157 | AZ6: =(AW6+(AW6*$J6)+(AW6*$M6)+(AW6*$N6)+(AW6*$O6)+(AW6*$P6)+(AW6*$Q6)+($R6)+(AW6*((52+$S6)/52))*(1+$T6))*1/$L6 -> 162598.89 | BA6: =(AX6+(AX6*$J6)+(AX6*$M6)+(AX6*$N6)+(AX6*$O6)+(AX6*$P6)+(AX6*$Q6)+($R6)+(AX6*((52+$S6)/52))*(1+$T6))*1/$L6 -> 198026.77 | BB6: =(AY6+(AY6*$J6)+(AY6*$M6)+(AY6*$N6)+(AY6*$O6)+(AY6*$P6)+(AY6*$Q6)+($R6)+(AY6*((52+$S6)/52))*(1+$T6))*1/$L6 -> 233454.64 | BC6: =AZ6/52/$K6 -> 82.286887 | BD6: =BA6/52/$K6 -> 100.21597 | BE6: =BB6/52/$K6 -> 118.14506 | BF6: =($V6*(1+(($U6/100)*4))) -> 63739.221 | BG6: =($W6*(1+(($U6/100)*4))) -> 77627.048 | BH6: =($X6*(1+(($U6/100)*4))) -> 91514.876 | BI6: =(BF6+(BF6*$J6)+(BF6*$M6)+(BF6*$N6)+(BF6*$O6)+(BF6*$P6)+(BF6*$Q6)+($R6)+(BF6*((52+$S6)/52))*(1+$T6))*1/$L6 -> 162623.27 | BJ6: =(BG6+(BG6*$J6)+(BG6*$M6)+(BG6*$N6)+(BG6*$O6)+(BG6*$P6)+(BG6*$Q6)+($R6)+(BG6*((52+$S6)/52))*(1+$T6))*1/$L6 -> 198056.46 | BK6: =(BH6+(BH6*$J6)+(BH6*$M6)+(BH6*$N6)+(BH6*$O6)+(BH6*$P6)+(BH6*$Q6)+($R6)+(BH6*((52+$S6)/52))*(1+$T6))*1/$L6 -> 233489.65 | BL6: =BI6/52/$K6 -> 82.299224 | BM6: =BJ6/52/$K6 -> 100.231 | BN6: =BK6/52/$K6 -> 118.16278
A7: VIC | B7: Bioinformatics staff | C7: BI | D7: MCRI Professional and Administrative Salaries | E7: 5-8 | G7: pp247 HS5-HS7 (July 22) | H7: 1785.7-2525.90 | I7: 2022 | J7: 0.105 | K7: 38 | L7: 1 | M7: 0.1 | N7: 0.035 | O7: 0 | P7: 0 | Q7: 0.046 | R7: 0 | S7: 4 | T7: 0.175 | U7: 0.015 | V7: 79624 | W7: =V7+((X7-V7)/2) -> 101861 | X7: 124098 | Y7: =(V7+(V7*$J7)+(V7*$M7)+(V7*$N7)+(V7*$O7)+(V7*$P7)+(V7*$Q7)+($R7)+(V7*((52+$S7)/52))*(1+$T7))*1/$L7 -> 203151.45 | Z7: =(W7+(W7*$J7)+(W7*$M7)+(W7*$N7)+(W7*$O7)+(W7*$P7)+(W7*$Q7)+($R7)+(W7*((52+$S7)/52))*(1+$T7))*1/$L7 -> 259886.59 | AA7: =(X7+(X7*$J7)+(X7*$M7)+(X7*$N7)+(X7*$O7)+(X7*$P7)+(X7*$Q7)+($R7)+(X7*((52+$S7)/52))*(1+$T7))*1/$L7 -> 316621.73 | AB7: =Y7/52/$K7 -> 102.80944 | AC7: =Z7/52/$K7 -> 131.52155 | AD7: =AA7/52/$K7 -> 160.23367 | AE7: =($V7*(1+(($U7/100)*1))) -> 79635.944 | AF7: =($W7*(1+(($U7/100)*1))) -> 101876.28 | AG7: =($X7*(1+(($U7/100)*1))) -> 124116.61 | AH7: =(AE7+(AE7*$J7)+(AE7*$M7)+(AE7*$N7)+(AE7*$O7)+(AE7*$P7)+(AE7*$Q7)+($R7)+(AE7*((52+$S7)/52))*(1+$T7))*1/$L7 -> 203181.92 | AI7: =(AF7+(AF7*$J7)+(AF7*$M7)+(AF7*$N7)+(AF7*$O7)+(AF7*$P7)+(AF7*$Q7)+($R7)+(AF7*((52+$S7)/52))*(1+$T7))*1/$L7 -> 259925.57 | AJ7: =(AG7+(AG7*$J7)+(AG7*$M7)+(AG7*$N7)+(AG7*$O7)+(AG7*$P7)+(AG7*$Q7)+($R7)+(AG7*((52+$S7)/52))*(1+$T7))*1/$L7 -> 316669.22 | AK7: =AH7/52/$K7 -> 102.82486 | AL7: =AI7/52/$K7 -> 131.54128 | AM7: =AJ7/52/$K7 -> 160.2577 | AN7: =($V7*(1+(($U7/100)*2))) -> 79647.887 | AO7: =($W7*(1+(($U7/100)*2))) -> 101891.56 | AP7: =($X7*(1+(($U7/100)*2))) -> 124135.23 | AQ7: =(AN7+(AN7*$J7)+(AN7*$M7)+(AN7*$N7)+(AN7*$O7)+(AN7*$P7)+(AN7*$Q7)+($R7)+(AN7*((52+$S7)/52))*(1+$T7))*1/$L7 -> 203212.39 | AR7: =(AO7+(AO7*$J7)+(AO7*$M7)+(AO7*$N7)+(AO7*$O7)+(AO7*$P7)+(AO7*$Q7)+($R7)+(AO7*((52+$S7)/52))*(1+$T7))*1/$L7 -> 259964.55 | AS7: =(AP7+(AP7*$J7)+(AP7*$M7)+(AP7*$N7)+(AP7*$O7)+(AP7*$P7)+(AP7*$Q7)+($R7)+(AP7*((52+$S7)/52))*(1+$T7))*1/$L7 -> 316716.71 | AT7: =AQ7/52/$K7 -> 102.84028 | AU7: =AR7/52/$K7 -> 131.56101 | AV7: =AS7/52/$K7 -> 160.28174 | AW7: =($V7*(1+(($U7/100)*3))) -> 79659.831 | AX7: =($W7*(1+(($U7/100)*3))) -> 101906.84 | AY7: =($X7*(1+(($U7/100)*3))) -> 124153.84 | AZ7: =(AW7+(AW7*$J7)+(AW7*$M7)+(AW7*$N7)+(AW7*$O7)+(AW7*$P7)+(AW7*$Q7)+($R7)+(AW7*((52+$S7)/52))*(1+$T7))*1/$L7 -> 203242.87 | BA7: =(AX7+(AX7*$J7)+(AX7*$M7)+(AX7*$N7)+(AX7*$O7)+(AX7*$P7)+(AX7*$Q7)+($R7)+(AX7*((52+$S7)/52))*(1+$T7))*1/$L7 -> 260003.54 | BB7: =(AY7+(AY7*$J7)+(AY7*$M7)+(AY7*$N7)+(AY7*$O7)+(AY7*$P7)+(AY7*$Q7)+($R7)+(AY7*((52+$S7)/52))*(1+$T7))*1/$L7 -> 316764.21 | BC7: =AZ7/52/$K7 -> 102.8557 | BD7: =BA7/52/$K7 -> 131.58074 | BE7: =BB7/52/$K7 -> 160.30577 | BF7: =($V7*(1+(($U7/100)*4))) -> 79671.774 | BG7: =($W7*(1+(($U7/100)*4))) -> 101922.12 | BH7: =($X7*(1+(($U7/100)*4))) -> 124172.46 | BI7: =(BF7+(BF7*$J7)+(BF7*$M7)+(BF7*$N7)+(BF7*$O7)+(BF7*$P7)+(BF7*$Q7)+($R7)+(BF7*((52+$S7)/52))*(1+$T7))*1/$L7 -> 203273.34 | BJ7: =(BG7+(BG7*$J7)+(BG7*$M7)+(BG7*$N7)+(BG7*$O7)+(BG7*$P7)+(BG7*$Q7)+($R7)+(BG7*((52+$S7)/52))*(1+$T7))*1/$L7 -> 260042.52 | BK7: =(BH7+(BH7*$J7)+(BH7*$M7)+(BH7*$N7)+(BH7*$O7)+(BH7*$P7)+(BH7*$Q7)+($R7)+(BH7*((52+$S7)/52))*(1+$T7))*1/$L7 -> 316811.7 | BL7: =BI7/52/$K7 -> 102.87112 | BM7: =BJ7/52/$K7 -> 131.60047 | BN7: =BK7/52/$K7 -> 160.32981
A8: VIC | B8: Pathologists | C8: MP | D8: MEDICAL SPECIALISTS (VICTORIAN PUBLIC HEALTH SECTOR) (AMA VICTORIA/ASMOF) (SINGLE INTEREST EMPLOYERS) ENTERPRISE AGREEMENT 2022 – 2026 | E8: Assume year 9, full time | F8: rightward skewed | G8: - | H8: 6420.1-7383.20 | I8: 2022 | J8: 0.105 | K8: 38 | L8: 1 | M8: 0 | N8: 0.035 | O8: 0 | P8: 0 | Q8: 0.046 | R8: 29000.16 | S8: 4 | T8: 0.175 | U8: 0.015 | V8: =4797.5*52 -> 249470 | W8: =V8+((X8-V8)/2) -> 296247.9 | X8: =6596.65*52 -> 343025.8 | Y8: =(V8+(V8*$J8)+(V8*$M8)+(V8*$N8)+(V8*$O8)+(V8*$P8)+(V8*$Q8)+($R8)+(V8*((52+$S8)/52))*(1+$T8))*1/$L8 -> 640547.08 | Z8: =(W8+(W8*$J8)+(W8*$M8)+(W8*$N8)+(W8*$O8)+(W8*$P8)+(W8*$Q8)+($R8)+(W8*((52+$S8)/52))*(1+$T8))*1/$L8 -> 755217.7 | AA8: =(X8+(X8*$J8)+(X8*$M8)+(X8*$N8)+(X8*$O8)+(X8*$P8)+(X8*$Q8)+($R8)+(X8*((52+$S8)/52))*(1+$T8))*1/$L8 -> 869888.33 | AB8: =Y8/52/$K8 -> 324.1635 | AC8: =Z8/52/$K8 -> 382.19519 | AD8: =AA8/52/$K8 -> 440.22689 | AE8: =($V8*(1+(($U8/100)*1))) -> 249507.42 | AF8: =($W8*(1+(($U8/100)*1))) -> 296292.34 | AG8: =($X8*(1+(($U8/100)*1))) -> 343077.25 | AH8: =(AE8+(AE8*$J8)+(AE8*$M8)+(AE8*$N8)+(AE8*$O8)+(AE8*$P8)+(AE8*$Q8)+($R8)+(AE8*((52+$S8)/52))*(1+$T8))*1/$L8 -> 640638.81 | AI8: =(AF8+(AF8*$J8)+(AF8*$M8)+(AF8*$N8)+(AF8*$O8)+(AF8*$P8)+(AF8*$Q8)+($R8)+(AF8*((52+$S8)/52))*(1+$T8))*1/$L8 -> 755326.64 | AJ8: =(AG8+(AG8*$J8)+(AG8*$M8)+(AG8*$N8)+(AG8*$O8)+(AG8*$P8)+(AG8*$Q8)+($R8)+(AG8*((52+$S8)/52))*(1+$T8))*1/$L8 -> 870014.46 | AK8: =AH8/52/$K8 -> 324.20993 | AL8: =AI8/52/$K8 -> 382.25032 | AM8: =AJ8/52/$K8 -> 440.29072 | AN8: =($V8*(1+(($U8/100)*2))) -> 249544.84 | AO8: =($W8*(1+(($U8/100)*2))) -> 296336.77 | AP8: =($X8*(1+(($U8/100)*2))) -> 343128.71 | AQ8: =(AN8+(AN8*$J8)+(AN8*$M8)+(AN8*$N8)+(AN8*$O8)+(AN8*$P8)+(AN8*$Q8)+($R8)+(AN8*((52+$S8)/52))*(1+$T8))*1/$L8 -> 640730.54 | AR8: =(AO8+(AO8*$J8)+(AO8*$M8)+(AO8*$N8)+(AO8*$O8)+(AO8*$P8)+(AO8*$Q8)+($R8)+(AO8*((52+$S8)/52))*(1+$T8))*1/$L8 -> 755435.57 | AS8: =(AP8+(AP8*$J8)+(AP8*$M8)+(AP8*$N8)+(AP8*$O8)+(AP8*$P8)+(AP8*$Q8)+($R8)+(AP8*((52+$S8)/52))*(1+$T8))*1/$L8 -> 870140.6 | AT8: =AQ8/52/$K8 -> 324.25635 | AU8: =AR8/52/$K8 -> 382.30545 | AV8: =AS8/52/$K8 -> 440.35455 | AW8: =($V8*(1+(($U8/100)*3))) -> 249582.26 | AX8: =($W8*(1+(($U8/100)*3))) -> 296381.21 | AY8: =($X8*(1+(($U8/100)*3))) -> 343180.16 | AZ8: =(AW8+(AW8*$J8)+(AW8*$M8)+(AW8*$N8)+(AW8*$O8)+(AW8*$P8)+(AW8*$Q8)+($R8)+(AW8*((52+$S8)/52))*(1+$T8))*1/$L8 -> 640822.28 | BA8: =(AX8+(AX8*$J8)+(AX8*$M8)+(AX8*$N8)+(AX8*$O8)+(AX8*$P8)+(AX8*$Q8)+($R8)+(AX8*((52+$S8)/52))*(1+$T8))*1/$L8 -> 755544.5 | BB8: =(AY8+(AY8*$J8)+(AY8*$M8)+(AY8*$N8)+(AY8*$O8)+(AY8*$P8)+(AY8*$Q8)+($R8)+(AY8*((52+$S8)/52))*(1+$T8))*1/$L8 -> 870266.73 | BC8: =AZ8/52/$K8 -> 324.30277 | BD8: =BA8/52/$K8 -> 382.36058 | BE8: =BB8/52/$K8 -> 440.41838 | BF8: =($V8*(1+(($U8/100)*4))) -> 249619.68 | BG8: =($W8*(1+(($U8/100)*4))) -> 296425.65 | BH8: =($X8*(1+(($U8/100)*4))) -> 343231.62 | BI8: =(BF8+(BF8*$J8)+(BF8*$M8)+(BF8*$N8)+(BF8*$O8)+(BF8*$P8)+(BF8*$Q8)+($R8)+(BF8*((52+$S8)/52))*(1+$T8))*1/$L8 -> 640914.01 | BJ8: =(BG8+(BG8*$J8)+(BG8*$M8)+(BG8*$N8)+(BG8*$O8)+(BG8*$P8)+(BG8*$Q8)+($R8)+(BG8*((52+$S8)/52))*(1+$T8))*1/$L8 -> 755653.43 | BK8: =(BH8+(BH8*$J8)+(BH8*$M8)+(BH8*$N8)+(BH8*$O8)+(BH8*$P8)+(BH8*$Q8)+($R8)+(BH8*((52+$S8)/52))*(1+$T8))*1/$L8 -> 870392.86 | BL8: =BI8/52/$K8 -> 324.34919 | BM8: =BJ8/52/$K8 -> 382.41571 | BN8: =BK8/52/$K8 -> 440.48222
A10: SA | B10: Lab technician | C10: LT | D10: S.A. PUBLIC SECTOR SALARIED EMPLOYEES INTERIM AWARD | E10: TG0-1 - TGO-3 | G10: SA Health Costing Table | I10: 2022 | J10: 0.105 | K10: 37.5 | L10: 1 | M10: 0.1 | N10: 0.035 | O10: 0 | P10: 0 | Q10: 0.046 | R10: 0 | S10: 4 | T10: 0 | U10: 0.015 | V10: 54364 | W10: =V10+((X10-V10)/2) -> 77673 | X10: 100982 | Y10: =(V10+(V10*$J10)+(V10*$M10)+(V10*$N10)+(V10*$O10)+(V10*$P10)+(V10*$Q10)+($R10)+(V10*((52+$S10)/52))*(1+$T10))*1/$L10 -> 128457.95 | Z10: =(W10+(W10*$J10)+(W10*$M10)+(W10*$N10)+(W10*$O10)+(W10*$P10)+(W10*$Q10)+($R10)+(W10*((52+$S10)/52))*(1+$T10))*1/$L10 -> 183535.32 | AA10: =(X10+(X10*$J10)+(X10*$M10)+(X10*$N10)+(X10*$O10)+(X10*$P10)+(X10*$Q10)+($R10)+(X10*((52+$S10)/52))*(1+$T10))*1/$L10 -> 238612.7 | AB10: =Y10/52/$K10 -> 65.875872 | AC10: =Z10/52/$K10 -> 94.120679 | AD10: =AA10/52/$K10 -> 122.36549 | AE10: =($V10*(1+(($U10/100)*1))) -> 54372.155 | AF10: =($W10*(1+(($U10/100)*1))) -> 77684.651 | AG10: =($X10*(1+(($U10/100)*1))) -> 100997.15 | AH10: =(AE10+(AE10*$J10)+(AE10*$M10)+(AE10*$N10)+(AE10*$O10)+(AE10*$P10)+(AE10*$Q10)+($R10)+(AE10*((52+$S10)/52))*(1+$T10))*1/$L10 -> 128477.22 | AI10: =(AF10+(AF10*$J10)+(AF10*$M10)+(AF10*$N10)+(AF10*$O10)+(AF10*$P10)+(AF10*$Q10)+($R10)+(AF10*((52+$S10)/52))*(1+$T10))*1/$L10 -> 183562.85 | AJ10: =(AG10+(AG10*$J10)+(AG10*$M10)+(AG10*$N10)+(AG10*$O10)+(AG10*$P10)+(AG10*$Q10)+($R10)+(AG10*((52+$S10)/52))*(1+$T10))*1/$L10 -> 238648.49 | AK10: =AH10/52/$K10 -> 65.885753 | AL10: =AI10/52/$K10 -> 94.134797 | AM10: =AJ10/52/$K10 -> 122.38384 | AN10: =($V10*(1+(($U10/100)*2))) -> 54380.309 | AO10: =($W10*(1+(($U10/100)*2))) -> 77696.302 | AP10: =($X10*(1+(($U10/100)*2))) -> 101012.29 | AQ10: =(AN10+(AN10*$J10)+(AN10*$M10)+(AN10*$N10)+(AN10*$O10)+(AN10*$P10)+(AN10*$Q10)+($R10)+(AN10*((52+$S10)/52))*(1+$T10))*1/$L10 -> 128496.49 | AR10: =(AO10+(AO10*$J10)+(AO10*$M10)+(AO10*$N10)+(AO10*$O10)+(AO10*$P10)+(AO10*$Q10)+($R10)+(AO10*((52+$S10)/52))*(1+$T10))*1/$L10 -> 183590.38 | AS10: =(AP10+(AP10*$J10)+(AP10*$M10)+(AP10*$N10)+(AP10*$O10)+(AP10*$P10)+(AP10*$Q10)+($R10)+(AP10*((52+$S10)/52))*(1+$T10))*1/$L10 -> 238684.28 | AT10: =AQ10/52/$K10 -> 65.895635 | AU10: =AR10/52/$K10 -> 94.148915 | AV10: =AS10/52/$K10 -> 122.4022 | AW10: =($V10*(1+(($U10/100)*3))) -> 54388.464 | AX10: =($W10*(1+(($U10/100)*3))) -> 77707.953 | AY10: =($X10*(1+(($U10/100)*3))) -> 101027.44 | AZ10: =(AW10+(AW10*$J10)+(AW10*$M10)+(AW10*$N10)+(AW10*$O10)+(AW10*$P10)+(AW10*$Q10)+($R10)+(AW10*((52+$S10)/52))*(1+$T10))*1/$L10 -> 128515.76 | BA10: =(AX10+(AX10*$J10)+(AX10*$M10)+(AX10*$N10)+(AX10*$O10)+(AX10*$P10)+(AX10*$Q10)+($R10)+(AX10*((52+$S10)/52))*(1+$T10))*1/$L10 -> 183617.92 | BB10: =(AY10+(AY10*$J10)+(AY10*$M10)+(AY10*$N10)+(AY10*$O10)+(AY10*$P10)+(AY10*$Q10)+($R10)+(AY10*((52+$S10)/52))*(1+$T10))*1/$L10 -> 238720.07 | BC10: =AZ10/52/$K10 -> 65.905516 | BD10: =BA10/52/$K10 -> 94.163033 | BE10: =BB10/52/$K10 -> 122.42055 | BF10: =($V10*(1+(($U10/100)*4))) -> 54396.618 | BG10: =($W10*(1+(($U10/100)*4))) -> 77719.604 | BH10: =($X10*(1+(($U10/100)*4))) -> 101042.59 | BI10: =(BF10+(BF10*$J10)+(BF10*$M10)+(BF10*$N10)+(BF10*$O10)+(BF10*$P10)+(BF10*$Q10)+($R10)+(BF10*((52+$S10)/52))*(1+$T10))*1/$L10 -> 128535.02 | BJ10: =(BG10+(BG10*$J10)+(BG10*$M10)+(BG10*$N10)+(BG10*$O10)+(BG10*$P10)+(BG10*$Q10)+($R10)+(BG10*((52+$S10)/52))*(1+$T10))*1/$L10 -> 183645.45 | BK10: =(BH10+(BH10*$J10)+(BH10*$M10)+(BH10*$N10)+(BH10*$O10)+(BH10*$P10)+(BH10*$Q10)+($R10)+(BH10*((52+$S10)/52))*(1+$T10))*1/$L10 -> 238755.87 | BL10: =BI10/52/$K10 -> 65.915397 | BM10: =BJ10/52/$K10 -> 94.177151 | BN10: =BK10/52/$K10 -> 122.43891
A11: SA | B11: Medical scientist | C11: MS | D11: MEDICAL SCIENTISTS (SOUTH AUSTRALIAN PUBLIC SECTOR) AWARD | E11: MS1 - MS4 | F11: - | G11: pp38 (Schedule 4, pg 1) | H11: 1145.45-2310.89 | I11: 2022 | J11: 0.105 | K11: 37.5 | L11: 1 | M11: 0.1 | N11: 0.035 | O11: 0 | P11: 0 | Q11: 0.046 | R11: 0 | S11: 5 | T11: 0 | U11: 0.015 | V11: 66386 | W11: =V11+((X11-V11)/2) -> 104238 | X11: 142090 | Y11: =(V11+(V11*$J11)+(V11*$M11)+(V11*$N11)+(V11*$O11)+(V11*$P11)+(V11*$Q11)+($R11)+(V11*((52+$S11)/52))*(1+$T11))*1/$L11 -> 158141.67 | Z11: =(W11+(W11*$J11)+(W11*$M11)+(W11*$N11)+(W11*$O11)+(W11*$P11)+(W11*$Q11)+($R11)+(W11*((52+$S11)/52))*(1+$T11))*1/$L11 -> 248310.95 | AA11: =(X11+(X11*$J11)+(X11*$M11)+(X11*$N11)+(X11*$O11)+(X11*$P11)+(X11*$Q11)+($R11)+(X11*((52+$S11)/52))*(1+$T11))*1/$L11 -> 338480.24 | AB11: =Y11/52/$K11 -> 81.09829 | AC11: =Z11/52/$K11 -> 127.33895 | AD11: =AA11/52/$K11 -> 173.57961 | AE11: =($V11*(1+(($U11/100)*1))) -> 66395.958 | AF11: =($W11*(1+(($U11/100)*1))) -> 104253.64 | AG11: =($X11*(1+(($U11/100)*1))) -> 142111.31 | AH11: =(AE11+(AE11*$J11)+(AE11*$M11)+(AE11*$N11)+(AE11*$O11)+(AE11*$P11)+(AE11*$Q11)+($R11)+(AE11*((52+$S11)/52))*(1+$T11))*1/$L11 -> 158165.39 | AI11: =(AF11+(AF11*$J11)+(AF11*$M11)+(AF11*$N11)+(AF11*$O11)+(AF11*$P11)+(AF11*$Q11)+($R11)+(AF11*((52+$S11)/52))*(1+$T11))*1/$L11 -> 248348.2 | AJ11: =(AG11+(AG11*$J11)+(AG11*$M11)+(AG11*$N11)+(AG11*$O11)+(AG11*$P11)+(AG11*$Q11)+($R11)+(AG11*((52+$S11)/52))*(1+$T11))*1/$L11 -> 338531.01 | AK11: =AH11/52/$K11 -> 81.110455 | AL11: =AI11/52/$K11 -> 127.35805 | AM11: =AJ11/52/$K11 -> 173.60565 | AN11: =($V11*(1+(($U11/100)*2))) -> 66405.916 | AO11: =($W11*(1+(($U11/100)*2))) -> 104269.27 | AP11: =($X11*(1+(($U11/100)*2))) -> 142132.63 | AQ11: =(AN11+(AN11*$J11)+(AN11*$M11)+(AN11*$N11)+(AN11*$O11)+(AN11*$P11)+(AN11*$Q11)+($R11)+(AN11*((52+$S11)/52))*(1+$T11))*1/$L11 -> 158189.11 | AR11: =(AO11+(AO11*$J11)+(AO11*$M11)+(AO11*$N11)+(AO11*$O11)+(AO11*$P11)+(AO11*$Q11)+($R11)+(AO11*((52+$S11)/52))*(1+$T11))*1/$L11 -> 248385.45 | AS11: =(AP11+(AP11*$J11)+(AP11*$M11)+(AP11*$N11)+(AP11*$O11)+(AP11*$P11)+(AP11*$Q11)+($R11)+(AP11*((52+$S11)/52))*(1+$T11))*1/$L11 -> 338581.78 | AT11: =AQ11/52/$K11 -> 81.122619 | AU11: =AR11/52/$K11 -> 127.37715 | AV11: =AS11/52/$K11 -> 173.63168 | AW11: =($V11*(1+(($U11/100)*3))) -> 66415.874 | AX11: =($W11*(1+(($U11/100)*3))) -> 104284.91 | AY11: =($X11*(1+(($U11/100)*3))) -> 142153.94 | AZ11: =(AW11+(AW11*$J11)+(AW11*$M11)+(AW11*$N11)+(AW11*$O11)+(AW11*$P11)+(AW11*$Q11)+($R11)+(AW11*((52+$S11)/52))*(1+$T11))*1/$L11 -> 158212.83 | BA11: =(AX11+(AX11*$J11)+(AX11*$M11)+(AX11*$N11)+(AX11*$O11)+(AX11*$P11)+(AX11*$Q11)+($R11)+(AX11*((52+$S11)/52))*(1+$T11))*1/$L11 -> 248422.69 | BB11: =(AY11+(AY11*$J11)+(AY11*$M11)+(AY11*$N11)+(AY11*$O11)+(AY11*$P11)+(AY11*$Q11)+($R11)+(AY11*((52+$S11)/52))*(1+$T11))*1/$L11 -> 338632.56 | BC11: =AZ11/52/$K11 -> 81.134784 | BD11: =BA11/52/$K11 -> 127.39625 | BE11: =BB11/52/$K11 -> 173.65772 | BF11: =($V11*(1+(($U11/100)*4))) -> 66425.832 | BG11: =($W11*(1+(($U11/100)*4))) -> 104300.54 | BH11: =($X11*(1+(($U11/100)*4))) -> 142175.25 | BI11: =(BF11+(BF11*$J11)+(BF11*$M11)+(BF11*$N11)+(BF11*$O11)+(BF11*$P11)+(BF11*$Q11)+($R11)+(BF11*((52+$S11)/52))*(1+$T11))*1/$L11 -> 158236.55 | BJ11: =(BG11+(BG11*$J11)+(BG11*$M11)+(BG11*$N11)+(BG11*$O11)+(BG11*$P11)+(BG11*$Q11)+($R11)+(BG11*((52+$S11)/52))*(1+$T11))*1/$L11 -> 248459.94 | BK11: =(BH11+(BH11*$J11)+(BH11*$M11)+(BH11*$N11)+(BH11*$O11)+(BH11*$P11)+(BH11*$Q11)+($R11)+(BH11*((52+$S11)/52))*(1+$T11))*1/$L11 -> 338683.33 | BL11: =BI11/52/$K11 -> 81.146949 | BM11: =BJ11/52/$K11 -> 127.41535 | BN11: =BK11/52/$K11 -> 173.68376
A12: SA | B12: Admin staff | C12: AS | D12: S.A. PUBLIC SECTOR SALARIED EMPLOYEES INTERIM AWARD | E12: ASO2-1 - ASO3-3 | I12: 2022 | J12: 0.105 | K12: 37.5 | L12: 1 | M12: 0.1 | N12: 0.035 | O12: 0 | P12: 0 | Q12: 0.046 | R12: 0 | S12: 4 | T12: 0 | U12: 0.015 | V12: 56916 | W12: =V12+((X12-V12)/2) -> 63374 | X12: 69832 | Y12: =(V12+(V12*$J12)+(V12*$M12)+(V12*$N12)+(V12*$O12)+(V12*$P12)+(V12*$Q12)+($R12)+(V12*((52+$S12)/52))*(1+$T12))*1/$L12 -> 134488.13 | Z12: =(W12+(W12*$J12)+(W12*$M12)+(W12*$N12)+(W12*$O12)+(W12*$P12)+(W12*$Q12)+($R12)+(W12*((52+$S12)/52))*(1+$T12))*1/$L12 -> 149747.89 | AA12: =(X12+(X12*$J12)+(X12*$M12)+(X12*$N12)+(X12*$O12)+(X12*$P12)+(X12*$Q12)+($R12)+(X12*((52+$S12)/52))*(1+$T12))*1/$L12 -> 165007.64 | AB12: =Y12/52/$K12 -> 68.968272 | AC12: =Z12/52/$K12 -> 76.793788 | AD12: =AA12/52/$K12 -> 84.619305 | AE12: =($V12*(1+(($U12/100)*1))) -> 56924.537 | AF12: =($W12*(1+(($U12/100)*1))) -> 63383.506 | AG12: =($X12*(1+(($U12/100)*1))) -> 69842.475 | AH12: =(AE12+(AE12*$J12)+(AE12*$M12)+(AE12*$N12)+(AE12*$O12)+(AE12*$P12)+(AE12*$Q12)+($R12)+(AE12*((52+$S12)/52))*(1+$T12))*1/$L12 -> 134508.3 | AI12: =(AF12+(AF12*$J12)+(AF12*$M12)+(AF12*$N12)+(AF12*$O12)+(AF12*$P12)+(AF12*$Q12)+($R12)+(AF12*((52+$S12)/52))*(1+$T12))*1/$L12 -> 149770.35 | AJ12: =(AG12+(AG12*$J12)+(AG12*$M12)+(AG12*$N12)+(AG12*$O12)+(AG12*$P12)+(AG12*$Q12)+($R12)+(AG12*((52+$S12)/52))*(1+$T12))*1/$L12 -> 165032.4 | AK12: =AH12/52/$K12 -> 68.978617 | AL12: =AI12/52/$K12 -> 76.805307 | AM12: =AJ12/52/$K12 -> 84.631998 | AN12: =($V12*(1+(($U12/100)*2))) -> 56933.075 | AO12: =($W12*(1+(($U12/100)*2))) -> 63393.012 | AP12: =($X12*(1+(($U12/100)*2))) -> 69852.95 | AQ12: =(AN12+(AN12*$J12)+(AN12*$M12)+(AN12*$N12)+(AN12*$O12)+(AN12*$P12)+(AN12*$Q12)+($R12)+(AN12*((52+$S12)/52))*(1+$T12))*1/$L12 -> 134528.48 | AR12: =(AO12+(AO12*$J12)+(AO12*$M12)+(AO12*$N12)+(AO12*$O12)+(AO12*$P12)+(AO12*$Q12)+($R12)+(AO12*((52+$S12)/52))*(1+$T12))*1/$L12 -> 149792.81 | AS12: =(AP12+(AP12*$J12)+(AP12*$M12)+(AP12*$N12)+(AP12*$O12)+(AP12*$P12)+(AP12*$Q12)+($R12)+(AP12*((52+$S12)/52))*(1+$T12))*1/$L12 -> 165057.15 | AT12: =AQ12/52/$K12 -> 68.988962 | AU12: =AR12/52/$K12 -> 76.816826 | AV12: =AS12/52/$K12 -> 84.644691 | AW12: =($V12*(1+(($U12/100)*3))) -> 56941.612 | AX12: =($W12*(1+(($U12/100)*3))) -> 63402.518 | AY12: =($X12*(1+(($U12/100)*3))) -> 69863.424 | AZ12: =(AW12+(AW12*$J12)+(AW12*$M12)+(AW12*$N12)+(AW12*$O12)+(AW12*$P12)+(AW12*$Q12)+($R12)+(AW12*((52+$S12)/52))*(1+$T12))*1/$L12 -> 134548.65 | BA12: =(AX12+(AX12*$J12)+(AX12*$M12)+(AX12*$N12)+(AX12*$O12)+(AX12*$P12)+(AX12*$Q12)+($R12)+(AX12*((52+$S12)/52))*(1+$T12))*1/$L12 -> 149815.27 | BB12: =(AY12+(AY12*$J12)+(AY12*$M12)+(AY12*$N12)+(AY12*$O12)+(AY12*$P12)+(AY12*$Q12)+($R12)+(AY12*((52+$S12)/52))*(1+$T12))*1/$L12 -> 165081.9 | BC12: =AZ12/52/$K12 -> 68.999307 | BD12: =BA12/52/$K12 -> 76.828345 | BE12: =BB12/52/$K12 -> 84.657383 | BF12: =($V12*(1+(($U12/100)*4))) -> 56950.15 | BG12: =($W12*(1+(($U12/100)*4))) -> 63412.024 | BH12: =($X12*(1+(($U12/100)*4))) -> 69873.899 | BI12: =(BF12+(BF12*$J12)+(BF12*$M12)+(BF12*$N12)+(BF12*$O12)+(BF12*$P12)+(BF12*$Q12)+($R12)+(BF12*((52+$S12)/52))*(1+$T12))*1/$L12 -> 134568.82 | BJ12: =(BG12+(BG12*$J12)+(BG12*$M12)+(BG12*$N12)+(BG12*$O12)+(BG12*$P12)+(BG12*$Q12)+($R12)+(BG12*((52+$S12)/52))*(1+$T12))*1/$L12 -> 149837.74 | BK12: =(BH12+(BH12*$J12)+(BH12*$M12)+(BH12*$N12)+(BH12*$O12)+(BH12*$P12)+(BH12*$Q12)+($R12)+(BH12*((52+$S12)/52))*(1+$T12))*1/$L12 -> 165106.65 | BL12: =BI12/52/$K12 -> 69.009653 | BM12: =BJ12/52/$K12 -> 76.839865 | BN12: =BK12/52/$K12 -> 84.670076
A13: SA | B13: Bioinformatics staff | C13: BI | D13: S.A. PUBLIC SECTOR SALARIED EMPLOYEES INTERIM AWARD | E13: PO-1 - PO-4 | I13: 2022 | J13: 0.105 | K13: 37.5 | L13: 1 | M13: 0.1 | N13: 0.035 | O13: 0 | P13: 0 | Q13: 0.046 | R13: 0 | S13: 4 | T13: 0 | U13: 0.015 | V13: 66386 | W13: =V13+((X13-V13)/2) -> 91587.5 | X13: 116789 | Y13: =(V13+(V13*$J13)+(V13*$M13)+(V13*$N13)+(V13*$O13)+(V13*$P13)+(V13*$Q13)+($R13)+(V13*((52+$S13)/52))*(1+$T13))*1/$L13 -> 156865.01 | Z13: =(W13+(W13*$J13)+(W13*$M13)+(W13*$N13)+(W13*$O13)+(W13*$P13)+(W13*$Q13)+($R13)+(W13*((52+$S13)/52))*(1+$T13))*1/$L13 -> 216414.22 | AA13: =(X13+(X13*$J13)+(X13*$M13)+(X13*$N13)+(X13*$O13)+(X13*$P13)+(X13*$Q13)+($R13)+(X13*((52+$S13)/52))*(1+$T13))*1/$L13 -> 275963.42 | AB13: =Y13/52/$K13 -> 80.443596 | AC13: =Z13/52/$K13 -> 110.98165 | AD13: =AA13/52/$K13 -> 141.5197 | AE13: =($V13*(1+(($U13/100)*1))) -> 66395.958 | AF13: =($W13*(1+(($U13/100)*1))) -> 91601.238 | AG13: =($X13*(1+(($U13/100)*1))) -> 116806.52 | AH13: =(AE13+(AE13*$J13)+(AE13*$M13)+(AE13*$N13)+(AE13*$O13)+(AE13*$P13)+(AE13*$Q13)+($R13)+(AE13*((52+$S13)/52))*(1+$T13))*1/$L13 -> 156888.54 | AI13: =(AF13+(AF13*$J13)+(AF13*$M13)+(AF13*$N13)+(AF13*$O13)+(AF13*$P13)+(AF13*$Q13)+($R13)+(AF13*((52+$S13)/52))*(1+$T13))*1/$L13 -> 216446.68 | AJ13: =(AG13+(AG13*$J13)+(AG13*$M13)+(AG13*$N13)+(AG13*$O13)+(AG13*$P13)+(AG13*$Q13)+($R13)+(AG13*((52+$S13)/52))*(1+$T13))*1/$L13 -> 276004.82 | AK13: =AH13/52/$K13 -> 80.455662 | AL13: =AI13/52/$K13 -> 110.9983 | AM13: =AJ13/52/$K13 -> 141.54093 | AN13: =($V13*(1+(($U13/100)*2))) -> 66405.916 | AO13: =($W13*(1+(($U13/100)*2))) -> 91614.976 | AP13: =($X13*(1+(($U13/100)*2))) -> 116824.04 | AQ13: =(AN13+(AN13*$J13)+(AN13*$M13)+(AN13*$N13)+(AN13*$O13)+(AN13*$P13)+(AN13*$Q13)+($R13)+(AN13*((52+$S13)/52))*(1+$T13))*1/$L13 -> 156912.07 | AR13: =(AO13+(AO13*$J13)+(AO13*$M13)+(AO13*$N13)+(AO13*$O13)+(AO13*$P13)+(AO13*$Q13)+($R13)+(AO13*((52+$S13)/52))*(1+$T13))*1/$L13 -> 216479.14 | AS13: =(AP13+(AP13*$J13)+(AP13*$M13)+(AP13*$N13)+(AP13*$O13)+(AP13*$P13)+(AP13*$Q13)+($R13)+(AP13*((52+$S13)/52))*(1+$T13))*1/$L13 -> 276046.21 | AT13: =AQ13/52/$K13 -> 80.467729 | AU13: =AR13/52/$K13 -> 111.01494 | AV13: =AS13/52/$K13 -> 141.56216 | AW13: =($V13*(1+(($U13/100)*3))) -> 66415.874 | AX13: =($W13*(1+(($U13/100)*3))) -> 91628.714 | AY13: =($X13*(1+(($U13/100)*3))) -> 116841.56 | AZ13: =(AW13+(AW13*$J13)+(AW13*$M13)+(AW13*$N13)+(AW13*$O13)+(AW13*$P13)+(AW13*$Q13)+($R13)+(AW13*((52+$S13)/52))*(1+$T13))*1/$L13 -> 156935.6 | BA13: =(AX13+(AX13*$J13)+(AX13*$M13)+(AX13*$N13)+(AX13*$O13)+(AX13*$P13)+(AX13*$Q13)+($R13)+(AX13*((52+$S13)/52))*(1+$T13))*1/$L13 -> 216511.6 | BB13: =(AY13+(AY13*$J13)+(AY13*$M13)+(AY13*$N13)+(AY13*$O13)+(AY13*$P13)+(AY13*$Q13)+($R13)+(AY13*((52+$S13)/52))*(1+$T13))*1/$L13 -> 276087.61 | BC13: =AZ13/52/$K13 -> 80.479795 | BD13: =BA13/52/$K13 -> 111.03159 | BE13: =BB13/52/$K13 -> 141.58339 | BF13: =($V13*(1+(($U13/100)*4))) -> 66425.832 | BG13: =($W13*(1+(($U13/100)*4))) -> 91642.452 | BH13: =($X13*(1+(($U13/100)*4))) -> 116859.07 | BI13: =(BF13+(BF13*$J13)+(BF13*$M13)+(BF13*$N13)+(BF13*$O13)+(BF13*$P13)+(BF13*$Q13)+($R13)+(BF13*((52+$S13)/52))*(1+$T13))*1/$L13 -> 156959.13 | BJ13: =(BG13+(BG13*$J13)+(BG13*$M13)+(BG13*$N13)+(BG13*$O13)+(BG13*$P13)+(BG13*$Q13)+($R13)+(BG13*((52+$S13)/52))*(1+$T13))*1/$L13 -> 216544.07 | BK13: =(BH13+(BH13*$J13)+(BH13*$M13)+(BH13*$N13)+(BH13*$O13)+(BH13*$P13)+(BH13*$Q13)+($R13)+(BH13*((52+$S13)/52))*(1+$T13))*1/$L13 -> 276129 | BL13: =BI13/52/$K13 -> 80.491862 | BM13: =BJ13/52/$K13 -> 111.04824 | BN13: =BK13/52/$K13 -> 141.60462
A14: SA | B14: Pathologists | C14: MP | D14: SA Health Salaried Medical Officers Enterprise Agreement 2022 | E14: MD0201 - MD029G | I14: 2022 | J14: 0.105 | K14: 38 | L14: 1 | M14: 0 | N14: 0.035 | O14: 0 | P14: 0.6 | Q14: 0.046 | R14: 26000 | S14: 5 | T14: 0.175 | U14: 0.015 | V14: 221622 | W14: =V14+((X14-V14)/2) -> 256820.5 | X14: 292019 | Y14: =(V14+(V14*$J14)+(V14*$M14)+(V14*$N14)+(V14*$O14)+(V14*$P14)+(V14*$Q14)+($R14)+(V14*((52+$S14)/52))*(1+$T14))*1/$L14 -> 707261.77 | Z14: =(W14+(W14*$J14)+(W14*$M14)+(W14*$N14)+(W14*$O14)+(W14*$P14)+(W14*$Q14)+($R14)+(W14*((52+$S14)/52))*(1+$T14))*1/$L14 -> 815461.28 | AA14: =(X14+(X14*$J14)+(X14*$M14)+(X14*$N14)+(X14*$O14)+(X14*$P14)+(X14*$Q14)+($R14)+(X14*((52+$S14)/52))*(1+$T14))*1/$L14 -> 923660.79 | AB14: =Y14/52/$K14 -> 357.92599 | AC14: =Z14/52/$K14 -> 412.68283 | AD14: =AA14/52/$K14 -> 467.43967 | AE14: =($V14*(1+(($U14/100)*1))) -> 221655.24 | AF14: =($W14*(1+(($U14/100)*1))) -> 256859.02 | AG14: =($X14*(1+(($U14/100)*1))) -> 292062.8 | AH14: =(AE14+(AE14*$J14)+(AE14*$M14)+(AE14*$N14)+(AE14*$O14)+(AE14*$P14)+(AE14*$Q14)+($R14)+(AE14*((52+$S14)/52))*(1+$T14))*1/$L14 -> 707363.96 | AI14: =(AF14+(AF14*$J14)+(AF14*$M14)+(AF14*$N14)+(AF14*$O14)+(AF14*$P14)+(AF14*$Q14)+($R14)+(AF14*((52+$S14)/52))*(1+$T14))*1/$L14 -> 815579.7 | AJ14: =(AG14+(AG14*$J14)+(AG14*$M14)+(AG14*$N14)+(AG14*$O14)+(AG14*$P14)+(AG14*$Q14)+($R14)+(AG14*((52+$S14)/52))*(1+$T14))*1/$L14 -> 923795.44 | AK14: =AH14/52/$K14 -> 357.97771 | AL14: =AI14/52/$K14 -> 412.74276 | AM14: =AJ14/52/$K14 -> 467.50781 | AN14: =($V14*(1+(($U14/100)*2))) -> 221688.49 | AO14: =($W14*(1+(($U14/100)*2))) -> 256897.55 | AP14: =($X14*(1+(($U14/100)*2))) -> 292106.61 | AQ14: =(AN14+(AN14*$J14)+(AN14*$M14)+(AN14*$N14)+(AN14*$O14)+(AN14*$P14)+(AN14*$Q14)+($R14)+(AN14*((52+$S14)/52))*(1+$T14))*1/$L14 -> 707466.14 | AR14: =(AO14+(AO14*$J14)+(AO14*$M14)+(AO14*$N14)+(AO14*$O14)+(AO14*$P14)+(AO14*$Q14)+($R14)+(AO14*((52+$S14)/52))*(1+$T14))*1/$L14 -> 815698.12 | AS14: =(AP14+(AP14*$J14)+(AP14*$M14)+(AP14*$N14)+(AP14*$O14)+(AP14*$P14)+(AP14*$Q14)+($R14)+(AP14*((52+$S14)/52))*(1+$T14))*1/$L14 -> 923930.09 | AT14: =AQ14/52/$K14 -> 358.02943 | AU14: =AR14/52/$K14 -> 412.80269 | AV14: =AS14/52/$K14 -> 467.57596 | AW14: =($V14*(1+(($U14/100)*3))) -> 221721.73 | AX14: =($W14*(1+(($U14/100)*3))) -> 256936.07 | AY14: =($X14*(1+(($U14/100)*3))) -> 292150.41 | AZ14: =(AW14+(AW14*$J14)+(AW14*$M14)+(AW14*$N14)+(AW14*$O14)+(AW14*$P14)+(AW14*$Q14)+($R14)+(AW14*((52+$S14)/52))*(1+$T14))*1/$L14 -> 707568.33 | BA14: =(AX14+(AX14*$J14)+(AX14*$M14)+(AX14*$N14)+(AX14*$O14)+(AX14*$P14)+(AX14*$Q14)+($R14)+(AX14*((52+$S14)/52))*(1+$T14))*1/$L14 -> 815816.54 | BB14: =(AY14+(AY14*$J14)+(AY14*$M14)+(AY14*$N14)+(AY14*$O14)+(AY14*$P14)+(AY14*$Q14)+($R14)+(AY14*((52+$S14)/52))*(1+$T14))*1/$L14 -> 924064.74 | BC14: =AZ14/52/$K14 -> 358.08114 | BD14: =BA14/52/$K14 -> 412.86262 | BE14: =BB14/52/$K14 -> 467.6441 | BF14: =($V14*(1+(($U14/100)*4))) -> 221754.97 | BG14: =($W14*(1+(($U14/100)*4))) -> 256974.59 | BH14: =($X14*(1+(($U14/100)*4))) -> 292194.21 | BI14: =(BF14+(BF14*$J14)+(BF14*$M14)+(BF14*$N14)+(BF14*$O14)+(BF14*$P14)+(BF14*$Q14)+($R14)+(BF14*((52+$S14)/52))*(1+$T14))*1/$L14 -> 707670.52 | BJ14: =(BG14+(BG14*$J14)+(BG14*$M14)+(BG14*$N14)+(BG14*$O14)+(BG14*$P14)+(BG14*$Q14)+($R14)+(BG14*((52+$S14)/52))*(1+$T14))*1/$L14 -> 815934.95 | BK14: =(BH14+(BH14*$J14)+(BH14*$M14)+(BH14*$N14)+(BH14*$O14)+(BH14*$P14)+(BH14*$Q14)+($R14)+(BH14*((52+$S14)/52))*(1+$T14))*1/$L14 -> 924199.39 | BL14: =BI14/52/$K14 -> 358.13286 | BM14: =BJ14/52/$K14 -> 412.92255 | BN14: =BK14/52/$K14 -> 467.71224
A16: NSW | B16: Lab technician | C16: LT | D16: Health Employees (State) Award | E16: Tech Assistant G1-3 | I16: 2022 | J16: 0.105 | K16: 40 | L16: 1 | M16: 0.1 | N16: 0.035 | O16: 0 | P16: 0 | Q16: 0.046 | R16: 0 | S16: 4 | T16: 0 | U16: 0.015 | V16: =1154.19*52 -> 60017.88 | W16: =V16+((X16-V16)/2) -> 77637.56 | X16: =1831.87*52 -> 95257.24 | Y16: =(V16+(V16*$J16)+(V16*$M16)+(V16*$N16)+(V16*$O16)+(V16*$P16)+(V16*$Q16)+($R16)+(V16*((52+$S16)/52))*(1+$T16))*1/$L16 -> 141817.63 | Z16: =(W16+(W16*$J16)+(W16*$M16)+(W16*$N16)+(W16*$O16)+(W16*$P16)+(W16*$Q16)+($R16)+(W16*((52+$S16)/52))*(1+$T16))*1/$L16 -> 183451.58 | AA16: =(X16+(X16*$J16)+(X16*$M16)+(X16*$N16)+(X16*$O16)+(X16*$P16)+(X16*$Q16)+($R16)+(X16*((52+$S16)/52))*(1+$T16))*1/$L16 -> 225085.53 | AB16: =Y16/52/$K16 -> 68.181555 | AC16: =Z16/52/$K16 -> 88.197876 | AD16: =AA16/52/$K16 -> 108.2142 | AE16: =($V16*(1+(($U16/100)*1))) -> 60026.883 | AF16: =($W16*(1+(($U16/100)*1))) -> 77649.206 | AG16: =($X16*(1+(($U16/100)*1))) -> 95271.529 | AH16: =(AE16+(AE16*$J16)+(AE16*$M16)+(AE16*$N16)+(AE16*$O16)+(AE16*$P16)+(AE16*$Q16)+($R16)+(AE16*((52+$S16)/52))*(1+$T16))*1/$L16 -> 141838.91 | AI16: =(AF16+(AF16*$J16)+(AF16*$M16)+(AF16*$N16)+(AF16*$O16)+(AF16*$P16)+(AF16*$Q16)+($R16)+(AF16*((52+$S16)/52))*(1+$T16))*1/$L16 -> 183479.1 | AJ16: =(AG16+(AG16*$J16)+(AG16*$M16)+(AG16*$N16)+(AG16*$O16)+(AG16*$P16)+(AG16*$Q16)+($R16)+(AG16*((52+$S16)/52))*(1+$T16))*1/$L16 -> 225119.29 | AK16: =AH16/52/$K16 -> 68.191782 | AL16: =AI16/52/$K16 -> 88.211106 | AM16: =AJ16/52/$K16 -> 108.23043 | AN16: =($V16*(1+(($U16/100)*2))) -> 60035.885 | AO16: =($W16*(1+(($U16/100)*2))) -> 77660.851 | AP16: =($X16*(1+(($U16/100)*2))) -> 95285.817 | AQ16: =(AN16+(AN16*$J16)+(AN16*$M16)+(AN16*$N16)+(AN16*$O16)+(AN16*$P16)+(AN16*$Q16)+($R16)+(AN16*((52+$S16)/52))*(1+$T16))*1/$L16 -> 141860.18 | AR16: =(AO16+(AO16*$J16)+(AO16*$M16)+(AO16*$N16)+(AO16*$O16)+(AO16*$P16)+(AO16*$Q16)+($R16)+(AO16*((52+$S16)/52))*(1+$T16))*1/$L16 -> 183506.62 | AS16: =(AP16+(AP16*$J16)+(AP16*$M16)+(AP16*$N16)+(AP16*$O16)+(AP16*$P16)+(AP16*$Q16)+($R16)+(AP16*((52+$S16)/52))*(1+$T16))*1/$L16 -> 225153.06 | AT16: =AQ16/52/$K16 -> 68.202009 | AU16: =AR16/52/$K16 -> 88.224335 | AV16: =AS16/52/$K16 -> 108.24666 | AW16: =($V16*(1+(($U16/100)*3))) -> 60044.888 | AX16: =($W16*(1+(($U16/100)*3))) -> 77672.497 | AY16: =($X16*(1+(($U16/100)*3))) -> 95300.106 | AZ16: =(AW16+(AW16*$J16)+(AW16*$M16)+(AW16*$N16)+(AW16*$O16)+(AW16*$P16)+(AW16*$Q16)+($R16)+(AW16*((52+$S16)/52))*(1+$T16))*1/$L16 -> 141881.45 | BA16: =(AX16+(AX16*$J16)+(AX16*$M16)+(AX16*$N16)+(AX16*$O16)+(AX16*$P16)+(AX16*$Q16)+($R16)+(AX16*((52+$S16)/52))*(1+$T16))*1/$L16 -> 183534.14 | BB16: =(AY16+(AY16*$J16)+(AY16*$M16)+(AY16*$N16)+(AY16*$O16)+(AY16*$P16)+(AY16*$Q16)+($R16)+(AY16*((52+$S16)/52))*(1+$T16))*1/$L16 -> 225186.82 | BC16: =AZ16/52/$K16 -> 68.212236 | BD16: =BA16/52/$K16 -> 88.237565 | BE16: =BB16/52/$K16 -> 108.26289 | BF16: =($V16*(1+(($U16/100)*4))) -> 60053.891 | BG16: =($W16*(1+(($U16/100)*4))) -> 77684.143 | BH16: =($X16*(1+(($U16/100)*4))) -> 95314.394 | BI16: =(BF16+(BF16*$J16)+(BF16*$M16)+(BF16*$N16)+(BF16*$O16)+(BF16*$P16)+(BF16*$Q16)+($R16)+(BF16*((52+$S16)/52))*(1+$T16))*1/$L16 -> 141902.72 | BJ16: =(BG16+(BG16*$J16)+(BG16*$M16)+(BG16*$N16)+(BG16*$O16)+(BG16*$P16)+(BG16*$Q16)+($R16)+(BG16*((52+$S16)/52))*(1+$T16))*1/$L16 -> 183561.65 | BK16: =(BH16+(BH16*$J16)+(BH16*$M16)+(BH16*$N16)+(BH16*$O16)+(BH16*$P16)+(BH16*$Q16)+($R16)+(BH16*((52+$S16)/52))*(1+$T16))*1/$L16 -> 225220.58 | BL16: =BI16/52/$K16 -> 68.222464 | BM16: =BJ16/52/$K16 -> 88.250795 | BN16: =BK16/52/$K16 -> 108.27913
A17: NSW | B17: Medical scientist | C17: MS | D17: Hospital Scientists (State) Award | E17: 1-3 | I17: 2022 | J17: 0.105 | K17: 38 | L17: 1 | M17: 0.1 | N17: 0.035 | O17: 0 | P17: 0 | Q17: 0.046 | R17: 0 | S17: 4 | T17: 0.175 | U17: 0.015 | V17: =1292.77*52 -> 67224.04 | W17: =V17+((X17-V17)/2) -> 102899.68 | X17: =2664.91*52 -> 138575.32 | Y17: =(V17+(V17*$J17)+(V17*$M17)+(V17*$N17)+(V17*$O17)+(V17*$P17)+(V17*$Q17)+($R17)+(V17*((52+$S17)/52))*(1+$T17))*1/$L17 -> 171514.38 | Z17: =(W17+(W17*$J17)+(W17*$M17)+(W17*$N17)+(W17*$O17)+(W17*$P17)+(W17*$Q17)+($R17)+(W17*((52+$S17)/52))*(1+$T17))*1/$L17 -> 262536.66 | AA17: =(X17+(X17*$J17)+(X17*$M17)+(X17*$N17)+(X17*$O17)+(X17*$P17)+(X17*$Q17)+($R17)+(X17*((52+$S17)/52))*(1+$T17))*1/$L17 -> 353558.94 | AB17: =Y17/52/$K17 -> 86.798776 | AC17: =Z17/52/$K17 -> 132.86268 | AD17: =AA17/52/$K17 -> 178.92659 | AE17: =($V17*(1+(($U17/100)*1))) -> 67234.124 | AF17: =($W17*(1+(($U17/100)*1))) -> 102915.11 | AG17: =($X17*(1+(($U17/100)*1))) -> 138596.11 | AH17: =(AE17+(AE17*$J17)+(AE17*$M17)+(AE17*$N17)+(AE17*$O17)+(AE17*$P17)+(AE17*$Q17)+($R17)+(AE17*((52+$S17)/52))*(1+$T17))*1/$L17 -> 171540.11 | AI17: =(AF17+(AF17*$J17)+(AF17*$M17)+(AF17*$N17)+(AF17*$O17)+(AF17*$P17)+(AF17*$Q17)+($R17)+(AF17*((52+$S17)/52))*(1+$T17))*1/$L17 -> 262576.04 | AJ17: =(AG17+(AG17*$J17)+(AG17*$M17)+(AG17*$N17)+(AG17*$O17)+(AG17*$P17)+(AG17*$Q17)+($R17)+(AG17*((52+$S17)/52))*(1+$T17))*1/$L17 -> 353611.97 | AK17: =AH17/52/$K17 -> 86.811796 | AL17: =AI17/52/$K17 -> 132.88261 | AM17: =AJ17/52/$K17 -> 178.95343 | AN17: =($V17*(1+(($U17/100)*2))) -> 67244.207 | AO17: =($W17*(1+(($U17/100)*2))) -> 102930.55 | AP17: =($X17*(1+(($U17/100)*2))) -> 138616.89 | AQ17: =(AN17+(AN17*$J17)+(AN17*$M17)+(AN17*$N17)+(AN17*$O17)+(AN17*$P17)+(AN17*$Q17)+($R17)+(AN17*((52+$S17)/52))*(1+$T17))*1/$L17 -> 171565.84 | AR17: =(AO17+(AO17*$J17)+(AO17*$M17)+(AO17*$N17)+(AO17*$O17)+(AO17*$P17)+(AO17*$Q17)+($R17)+(AO17*((52+$S17)/52))*(1+$T17))*1/$L17 -> 262615.42 | AS17: =(AP17+(AP17*$J17)+(AP17*$M17)+(AP17*$N17)+(AP17*$O17)+(AP17*$P17)+(AP17*$Q17)+($R17)+(AP17*((52+$S17)/52))*(1+$T17))*1/$L17 -> 353665.01 | AT17: =AQ17/52/$K17 -> 86.824816 | AU17: =AR17/52/$K17 -> 132.90254 | AV17: =AS17/52/$K17 -> 178.98027 | AW17: =($V17*(1+(($U17/100)*3))) -> 67254.291 | AX17: =($W17*(1+(($U17/100)*3))) -> 102945.98 | AY17: =($X17*(1+(($U17/100)*3))) -> 138637.68 | AZ17: =(AW17+(AW17*$J17)+(AW17*$M17)+(AW17*$N17)+(AW17*$O17)+(AW17*$P17)+(AW17*$Q17)+($R17)+(AW17*((52+$S17)/52))*(1+$T17))*1/$L17 -> 171591.56 | BA17: =(AX17+(AX17*$J17)+(AX17*$M17)+(AX17*$N17)+(AX17*$O17)+(AX17*$P17)+(AX17*$Q17)+($R17)+(AX17*((52+$S17)/52))*(1+$T17))*1/$L17 -> 262654.8 | BB17: =(AY17+(AY17*$J17)+(AY17*$M17)+(AY17*$N17)+(AY17*$O17)+(AY17*$P17)+(AY17*$Q17)+($R17)+(AY17*((52+$S17)/52))*(1+$T17))*1/$L17 -> 353718.04 | BC17: =AZ17/52/$K17 -> 86.837835 | BD17: =BA17/52/$K17 -> 132.92247 | BE17: =BB17/52/$K17 -> 179.00711 | BF17: =($V17*(1+(($U17/100)*4))) -> 67264.374 | BG17: =($W17*(1+(($U17/100)*4))) -> 102961.42 | BH17: =($X17*(1+(($U17/100)*4))) -> 138658.47 | BI17: =(BF17+(BF17*$J17)+(BF17*$M17)+(BF17*$N17)+(BF17*$O17)+(BF17*$P17)+(BF17*$Q17)+($R17)+(BF17*((52+$S17)/52))*(1+$T17))*1/$L17 -> 171617.29 | BJ17: =(BG17+(BG17*$J17)+(BG17*$M17)+(BG17*$N17)+(BG17*$O17)+(BG17*$P17)+(BG17*$Q17)+($R17)+(BG17*((52+$S17)/52))*(1+$T17))*1/$L17 -> 262694.18 | BK17: =(BH17+(BH17*$J17)+(BH17*$M17)+(BH17*$N17)+(BH17*$O17)+(BH17*$P17)+(BH17*$Q17)+($R17)+(BH17*((52+$S17)/52))*(1+$T17))*1/$L17 -> 353771.07 | BL17: =BI17/52/$K17 -> 86.850855 | BM17: =BJ17/52/$K17 -> 132.9424 | BN17: =BK17/52/$K17 -> 179.03394
A18: NSW | B18: Admin staff | C18: AS | I18: 2022 | J18: 0.105 | K18: 40 | L18: 1 | M18: 0.1 | N18: 0.035 | O18: 0 | P18: 0 | Q18: 0.046 | R18: 0 | S18: 4 | T18: 0 | U18: 0.015 | V18: =926.56*52 -> 48181.12 | W18: =V18+((X18-V18)/2) -> 57943.08 | X18: =1302.02*52 -> 67705.04 | Y18: =(V18+(V18*$J18)+(V18*$M18)+(V18*$N18)+(V18*$O18)+(V18*$P18)+(V18*$Q18)+($R18)+(V18*((52+$S18)/52))*(1+$T18))*1/$L18 -> 113848.28 | Z18: =(W18+(W18*$J18)+(W18*$M18)+(W18*$N18)+(W18*$O18)+(W18*$P18)+(W18*$Q18)+($R18)+(W18*((52+$S18)/52))*(1+$T18))*1/$L18 -> 136915.04 | AA18: =(X18+(X18*$J18)+(X18*$M18)+(X18*$N18)+(X18*$O18)+(X18*$P18)+(X18*$Q18)+($R18)+(X18*((52+$S18)/52))*(1+$T18))*1/$L18 -> 159981.8 | AB18: =Y18/52/$K18 -> 54.73475 | AC18: =Z18/52/$K18 -> 65.824539 | AD18: =AA18/52/$K18 -> 76.914328 | AE18: =($V18*(1+(($U18/100)*1))) -> 48188.347 | AF18: =($W18*(1+(($U18/100)*1))) -> 57951.771 | AG18: =($X18*(1+(($U18/100)*1))) -> 67715.196 | AH18: =(AE18+(AE18*$J18)+(AE18*$M18)+(AE18*$N18)+(AE18*$O18)+(AE18*$P18)+(AE18*$Q18)+($R18)+(AE18*((52+$S18)/52))*(1+$T18))*1/$L18 -> 113865.36 | AI18: =(AF18+(AF18*$J18)+(AF18*$M18)+(AF18*$N18)+(AF18*$O18)+(AF18*$P18)+(AF18*$Q18)+($R18)+(AF18*((52+$S18)/52))*(1+$T18))*1/$L18 -> 136935.58 | AJ18: =(AG18+(AG18*$J18)+(AG18*$M18)+(AG18*$N18)+(AG18*$O18)+(AG18*$P18)+(AG18*$Q18)+($R18)+(AG18*((52+$S18)/52))*(1+$T18))*1/$L18 -> 160005.8 | AK18: =AH18/52/$K18 -> 54.74296 | AL18: =AI18/52/$K18 -> 65.834413 | AM18: =AJ18/52/$K18 -> 76.925865 | AN18: =($V18*(1+(($U18/100)*2))) -> 48195.574 | AO18: =($W18*(1+(($U18/100)*2))) -> 57960.463 | AP18: =($X18*(1+(($U18/100)*2))) -> 67725.352 | AQ18: =(AN18+(AN18*$J18)+(AN18*$M18)+(AN18*$N18)+(AN18*$O18)+(AN18*$P18)+(AN18*$Q18)+($R18)+(AN18*((52+$S18)/52))*(1+$T18))*1/$L18 -> 113882.43 | AR18: =(AO18+(AO18*$J18)+(AO18*$M18)+(AO18*$N18)+(AO18*$O18)+(AO18*$P18)+(AO18*$Q18)+($R18)+(AO18*((52+$S18)/52))*(1+$T18))*1/$L18 -> 136956.12 | AS18: =(AP18+(AP18*$J18)+(AP18*$M18)+(AP18*$N18)+(AP18*$O18)+(AP18*$P18)+(AP18*$Q18)+($R18)+(AP18*((52+$S18)/52))*(1+$T18))*1/$L18 -> 160029.8 | AT18: =AQ18/52/$K18 -> 54.751171 | AU18: =AR18/52/$K18 -> 65.844286 | AV18: =AS18/52/$K18 -> 76.937402 | AW18: =($V18*(1+(($U18/100)*3))) -> 48202.802 | AX18: =($W18*(1+(($U18/100)*3))) -> 57969.154 | AY18: =($X18*(1+(($U18/100)*3))) -> 67735.507 | AZ18: =(AW18+(AW18*$J18)+(AW18*$M18)+(AW18*$N18)+(AW18*$O18)+(AW18*$P18)+(AW18*$Q18)+($R18)+(AW18*((52+$S18)/52))*(1+$T18))*1/$L18 -> 113899.51 | BA18: =(AX18+(AX18*$J18)+(AX18*$M18)+(AX18*$N18)+(AX18*$O18)+(AX18*$P18)+(AX18*$Q18)+($R18)+(AX18*((52+$S18)/52))*(1+$T18))*1/$L18 -> 136976.65 | BB18: =(AY18+(AY18*$J18)+(AY18*$M18)+(AY18*$N18)+(AY18*$O18)+(AY18*$P18)+(AY18*$Q18)+($R18)+(AY18*((52+$S18)/52))*(1+$T18))*1/$L18 -> 160053.79 | BC18: =AZ18/52/$K18 -> 54.759381 | BD18: =BA18/52/$K18 -> 65.85416 | BE18: =BB18/52/$K18 -> 76.948939 | BF18: =($V18*(1+(($U18/100)*4))) -> 48210.029 | BG18: =($W18*(1+(($U18/100)*4))) -> 57977.846 | BH18: =($X18*(1+(($U18/100)*4))) -> 67745.663 | BI18: =(BF18+(BF18*$J18)+(BF18*$M18)+(BF18*$N18)+(BF18*$O18)+(BF18*$P18)+(BF18*$Q18)+($R18)+(BF18*((52+$S18)/52))*(1+$T18))*1/$L18 -> 113916.59 | BJ18: =(BG18+(BG18*$J18)+(BG18*$M18)+(BG18*$N18)+(BG18*$O18)+(BG18*$P18)+(BG18*$Q18)+($R18)+(BG18*((52+$S18)/52))*(1+$T18))*1/$L18 -> 136997.19 | BK18: =(BH18+(BH18*$J18)+(BH18*$M18)+(BH18*$N18)+(BH18*$O18)+(BH18*$P18)+(BH18*$Q18)+($R18)+(BH18*((52+$S18)/52))*(1+$T18))*1/$L18 -> 160077.79 | BL18: =BI18/52/$K18 -> 54.767591 | BM18: =BJ18/52/$K18 -> 65.864034 | BN18: =BK18/52/$K18 -> 76.960476
A19: NSW | B19: Bioinformatics staff | C19: BI | D19: Hospital Scientists (State) Award | E19: 1-3 | I19: 2022 | J19: 0.105 | K19: 40 | L19: 1 | M19: 0.1 | N19: 0.035 | O19: 0 | P19: 0 | Q19: 0.046 | R19: 0 | S19: 4 | T19: 0.175 | U19: 0.015 | V19: 66106 | W19: =V19+((X19-V19)/2) -> 90434.5 | X19: 114763 | Y19: =(V19+(V19*$J19)+(V19*$M19)+(V19*$N19)+(V19*$O19)+(V19*$P19)+(V19*$Q19)+($R19)+(V19*((52+$S19)/52))*(1+$T19))*1/$L19 -> 168661.83 | Z19: =(W19+(W19*$J19)+(W19*$M19)+(W19*$N19)+(W19*$O19)+(W19*$P19)+(W19*$Q19)+($R19)+(W19*((52+$S19)/52))*(1+$T19))*1/$L19 -> 230733.19 | AA19: =(X19+(X19*$J19)+(X19*$M19)+(X19*$N19)+(X19*$O19)+(X19*$P19)+(X19*$Q19)+($R19)+(X19*((52+$S19)/52))*(1+$T19))*1/$L19 -> 292804.55 | AB19: =Y19/52/$K19 -> 81.087419 | AC19: =Z19/52/$K19 -> 110.92942 | AD19: =AA19/52/$K19 -> 140.77142 | AE19: =($V19*(1+(($U19/100)*1))) -> 66115.916 | AF19: =($W19*(1+(($U19/100)*1))) -> 90448.065 | AG19: =($X19*(1+(($U19/100)*1))) -> 114780.21 | AH19: =(AE19+(AE19*$J19)+(AE19*$M19)+(AE19*$N19)+(AE19*$O19)+(AE19*$P19)+(AE19*$Q19)+($R19)+(AE19*((52+$S19)/52))*(1+$T19))*1/$L19 -> 168687.13 | AI19: =(AF19+(AF19*$J19)+(AF19*$M19)+(AF19*$N19)+(AF19*$O19)+(AF19*$P19)+(AF19*$Q19)+($R19)+(AF19*((52+$S19)/52))*(1+$T19))*1/$L19 -> 230767.8 | AJ19: =(AG19+(AG19*$J19)+(AG19*$M19)+(AG19*$N19)+(AG19*$O19)+(AG19*$P19)+(AG19*$Q19)+($R19)+(AG19*((52+$S19)/52))*(1+$T19))*1/$L19 -> 292848.47 | AK19: =AH19/52/$K19 -> 81.099582 | AL19: =AI19/52/$K19 -> 110.94606 | AM19: =AJ19/52/$K19 -> 140.79254 | AN19: =($V19*(1+(($U19/100)*2))) -> 66125.832 | AO19: =($W19*(1+(($U19/100)*2))) -> 90461.63 | AP19: =($X19*(1+(($U19/100)*2))) -> 114797.43 | AQ19: =(AN19+(AN19*$J19)+(AN19*$M19)+(AN19*$N19)+(AN19*$O19)+(AN19*$P19)+(AN19*$Q19)+($R19)+(AN19*((52+$S19)/52))*(1+$T19))*1/$L19 -> 168712.43 | AR19: =(AO19+(AO19*$J19)+(AO19*$M19)+(AO19*$N19)+(AO19*$O19)+(AO19*$P19)+(AO19*$Q19)+($R19)+(AO19*((52+$S19)/52))*(1+$T19))*1/$L19 -> 230802.41 | AS19: =(AP19+(AP19*$J19)+(AP19*$M19)+(AP19*$N19)+(AP19*$O19)+(AP19*$P19)+(AP19*$Q19)+($R19)+(AP19*((52+$S19)/52))*(1+$T19))*1/$L19 -> 292892.39 | AT19: =AQ19/52/$K19 -> 81.111745 | AU19: =AR19/52/$K19 -> 110.9627 | AV19: =AS19/52/$K19 -> 140.81365 | AW19: =($V19*(1+(($U19/100)*3))) -> 66135.748 | AX19: =($W19*(1+(($U19/100)*3))) -> 90475.196 | AY19: =($X19*(1+(($U19/100)*3))) -> 114814.64 | AZ19: =(AW19+(AW19*$J19)+(AW19*$M19)+(AW19*$N19)+(AW19*$O19)+(AW19*$P19)+(AW19*$Q19)+($R19)+(AW19*((52+$S19)/52))*(1+$T19))*1/$L19 -> 168737.73 | BA19: =(AX19+(AX19*$J19)+(AX19*$M19)+(AX19*$N19)+(AX19*$O19)+(AX19*$P19)+(AX19*$Q19)+($R19)+(AX19*((52+$S19)/52))*(1+$T19))*1/$L19 -> 230837.02 | BB19: =(AY19+(AY19*$J19)+(AY19*$M19)+(AY19*$N19)+(AY19*$O19)+(AY19*$P19)+(AY19*$Q19)+($R19)+(AY19*((52+$S19)/52))*(1+$T19))*1/$L19 -> 292936.31 | BC19: =AZ19/52/$K19 -> 81.123908 | BD19: =BA19/52/$K19 -> 110.97934 | BE19: =BB19/52/$K19 -> 140.83477 | BF19: =($V19*(1+(($U19/100)*4))) -> 66145.664 | BG19: =($W19*(1+(($U19/100)*4))) -> 90488.761 | BH19: =($X19*(1+(($U19/100)*4))) -> 114831.86 | BI19: =(BF19+(BF19*$J19)+(BF19*$M19)+(BF19*$N19)+(BF19*$O19)+(BF19*$P19)+(BF19*$Q19)+($R19)+(BF19*((52+$S19)/52))*(1+$T19))*1/$L19 -> 168763.03 | BJ19: =(BG19+(BG19*$J19)+(BG19*$M19)+(BG19*$N19)+(BG19*$O19)+(BG19*$P19)+(BG19*$Q19)+($R19)+(BG19*((52+$S19)/52))*(1+$T19))*1/$L19 -> 230871.63 | BK19: =(BH19+(BH19*$J19)+(BH19*$M19)+(BH19*$N19)+(BH19*$O19)+(BH19*$P19)+(BH19*$Q19)+($R19)+(BH19*((52+$S19)/52))*(1+$T19))*1/$L19 -> 292980.24 | BL19: =BI19/52/$K19 -> 81.136071 | BM19: =BJ19/52/$K19 -> 110.99598 | BN19: =BK19/52/$K19 -> 140.85588
A20: NSW | B20: Pathologists | C20: MP | D20: STAFF SPECIALISTS (STATE) AWARD 2022 | E20: SS1-SS5 | F20: - | G20: - | H20: 179078-241940 | I20: 2022 | J20: 0.105 | K20: 40 | L20: 1 | M20: 0 | N20: 0.035 | O20: 0.2 | P20: 0.174 | Q20: 0.046 | R20: 38000 | S20: 5 | T20: 0.175 | U20: 0.015 | V20: 179078 | W20: =V20+((X20-V20)/2) -> 210509 | X20: 241940 | Y20: =(V20+(V20*$J20)+(V20*$M20)+(V20*$N20)+(V20*$O20)+(V20*$P20)+(V20*$Q20)+($R20)+(V20*((52+$S20)/52))*(1+$T20))*1/$L20 -> 548010.7 | Z20: =(W20+(W20*$J20)+(W20*$M20)+(W20*$N20)+(W20*$O20)+(W20*$P20)+(W20*$Q20)+($R20)+(W20*((52+$S20)/52))*(1+$T20))*1/$L20 -> 637525.58 | AA20: =(X20+(X20*$J20)+(X20*$M20)+(X20*$N20)+(X20*$O20)+(X20*$P20)+(X20*$Q20)+($R20)+(X20*((52+$S20)/52))*(1+$T20))*1/$L20 -> 727040.47 | AB20: =Y20/52/$K20 -> 263.46668 | AC20: =Z20/52/$K20 -> 306.50268 | AD20: =AA20/52/$K20 -> 349.53869 | AE20: =($V20*(1+(($U20/100)*1))) -> 179104.86 | AF20: =($W20*(1+(($U20/100)*1))) -> 210540.58 | AG20: =($X20*(1+(($U20/100)*1))) -> 241976.29 | AH20: =(AE20+(AE20*$J20)+(AE20*$M20)+(AE20*$N20)+(AE20*$O20)+(AE20*$P20)+(AE20*$Q20)+($R20)+(AE20*((52+$S20)/52))*(1+$T20))*1/$L20 -> 548087.2 | AI20: =(AF20+(AF20*$J20)+(AF20*$M20)+(AF20*$N20)+(AF20*$O20)+(AF20*$P20)+(AF20*$Q20)+($R20)+(AF20*((52+$S20)/52))*(1+$T20))*1/$L20 -> 637615.51 | AJ20: =(AG20+(AG20*$J20)+(AG20*$M20)+(AG20*$N20)+(AG20*$O20)+(AG20*$P20)+(AG20*$Q20)+($R20)+(AG20*((52+$S20)/52))*(1+$T20))*1/$L20 -> 727143.82 | AK20: =AH20/52/$K20 -> 263.50346 | AL20: =AI20/52/$K20 -> 306.54592 | AM20: =AJ20/52/$K20 -> 349.58838 | AN20: =($V20*(1+(($U20/100)*2))) -> 179131.72 | AO20: =($W20*(1+(($U20/100)*2))) -> 210572.15 | AP20: =($X20*(1+(($U20/100)*2))) -> 242012.58 | AQ20: =(AN20+(AN20*$J20)+(AN20*$M20)+(AN20*$N20)+(AN20*$O20)+(AN20*$P20)+(AN20*$Q20)+($R20)+(AN20*((52+$S20)/52))*(1+$T20))*1/$L20 -> 548163.7 | AR20: =(AO20+(AO20*$J20)+(AO20*$M20)+(AO20*$N20)+(AO20*$O20)+(AO20*$P20)+(AO20*$Q20)+($R20)+(AO20*((52+$S20)/52))*(1+$T20))*1/$L20 -> 637705.44 | AS20: =(AP20+(AP20*$J20)+(AP20*$M20)+(AP20*$N20)+(AP20*$O20)+(AP20*$P20)+(AP20*$Q20)+($R20)+(AP20*((52+$S20)/52))*(1+$T20))*1/$L20 -> 727247.18 | AT20: =AQ20/52/$K20 -> 263.54024 | AU20: =AR20/52/$K20 -> 306.58915 | AV20: =AS20/52/$K20 -> 349.63807 | AW20: =($V20*(1+(($U20/100)*3))) -> 179158.59 | AX20: =($W20*(1+(($U20/100)*3))) -> 210603.73 | AY20: =($X20*(1+(($U20/100)*3))) -> 242048.87 | AZ20: =(AW20+(AW20*$J20)+(AW20*$M20)+(AW20*$N20)+(AW20*$O20)+(AW20*$P20)+(AW20*$Q20)+($R20)+(AW20*((52+$S20)/52))*(1+$T20))*1/$L20 -> 548240.21 | BA20: =(AX20+(AX20*$J20)+(AX20*$M20)+(AX20*$N20)+(AX20*$O20)+(AX20*$P20)+(AX20*$Q20)+($R20)+(AX20*((52+$S20)/52))*(1+$T20))*1/$L20 -> 637795.37 | BB20: =(AY20+(AY20*$J20)+(AY20*$M20)+(AY20*$N20)+(AY20*$O20)+(AY20*$P20)+(AY20*$Q20)+($R20)+(AY20*((52+$S20)/52))*(1+$T20))*1/$L20 -> 727350.54 | BC20: =AZ20/52/$K20 -> 263.57702 | BD20: =BA20/52/$K20 -> 306.63239 | BE20: =BB20/52/$K20 -> 349.68776 | BF20: =($V20*(1+(($U20/100)*4))) -> 179185.45 | BG20: =($W20*(1+(($U20/100)*4))) -> 210635.31 | BH20: =($X20*(1+(($U20/100)*4))) -> 242085.16 | BI20: =(BF20+(BF20*$J20)+(BF20*$M20)+(BF20*$N20)+(BF20*$O20)+(BF20*$P20)+(BF20*$Q20)+($R20)+(BF20*((52+$S20)/52))*(1+$T20))*1/$L20 -> 548316.71 | BJ20: =(BG20+(BG20*$J20)+(BG20*$M20)+(BG20*$N20)+(BG20*$O20)+(BG20*$P20)+(BG20*$Q20)+($R20)+(BG20*((52+$S20)/52))*(1+$T20))*1/$L20 -> 637885.3 | BK20: =(BH20+(BH20*$J20)+(BH20*$M20)+(BH20*$N20)+(BH20*$O20)+(BH20*$P20)+(BH20*$Q20)+($R20)+(BH20*((52+$S20)/52))*(1+$T20))*1/$L20 -> 727453.89 | BL20: =BI20/52/$K20 -> 263.6138 | BM20: =BJ20/52/$K20 -> 306.67562 | BN20: =BK20/52/$K20 -> 349.73745
A22: QLD | B22: Lab technician | C22: LT | D22: Hospital and Health Service General Employees (Queensland Health) Award - State 2015 | I22: 2022 | J22: 0.1275 | K22: 36.25 | L22: 1 | M22: 0.1 | N22: 0.035 | O22: 0 | P22: 0 | Q22: 0.046 | R22: 1826 | S22: 4 | T22: 0 | U22: 0.015 | V22: 48552 | W22: =V22+((X22-V22)/2) -> 70196 | X22: 91840 | Y22: =(V22+(V22*$J22)+(V22*$M22)+(V22*$N22)+(V22*$O22)+(V22*$P22)+(V22*$Q22)+($R22)+(V22*((52+$S22)/52))*(1+$T22))*1/$L22 -> 117643.06 | Z22: =(W22+(W22*$J22)+(W22*$M22)+(W22*$N22)+(W22*$O22)+(W22*$P22)+(W22*$Q22)+($R22)+(W22*((52+$S22)/52))*(1+$T22))*1/$L22 -> 169273.16 | AA22: =(X22+(X22*$J22)+(X22*$M22)+(X22*$N22)+(X22*$O22)+(X22*$P22)+(X22*$Q22)+($R22)+(X22*((52+$S22)/52))*(1+$T22))*1/$L22 -> 220903.26 | AB22: =Y22/52/$K22 -> 62.410112 | AC22: =Z22/52/$K22 -> 89.800084 | AD22: =AA22/52/$K22 -> 117.19006 | AE22: =($V22*(1+(($U22/100)*1))) -> 48559.283 | AF22: =($W22*(1+(($U22/100)*1))) -> 70206.529 | AG22: =($X22*(1+(($U22/100)*1))) -> 91853.776 | AH22: =(AE22+(AE22*$J22)+(AE22*$M22)+(AE22*$N22)+(AE22*$O22)+(AE22*$P22)+(AE22*$Q22)+($R22)+(AE22*((52+$S22)/52))*(1+$T22))*1/$L22 -> 117660.43 | AI22: =(AF22+(AF22*$J22)+(AF22*$M22)+(AF22*$N22)+(AF22*$O22)+(AF22*$P22)+(AF22*$Q22)+($R22)+(AF22*((52+$S22)/52))*(1+$T22))*1/$L22 -> 169298.28 | AJ22: =(AG22+(AG22*$J22)+(AG22*$M22)+(AG22*$N22)+(AG22*$O22)+(AG22*$P22)+(AG22*$Q22)+($R22)+(AG22*((52+$S22)/52))*(1+$T22))*1/$L22 -> 220936.12 | AK22: =AH22/52/$K22 -> 62.419328 | AL22: =AI22/52/$K22 -> 89.813409 | AM22: =AJ22/52/$K22 -> 117.20749 | AN22: =($V22*(1+(($U22/100)*2))) -> 48566.566 | AO22: =($W22*(1+(($U22/100)*2))) -> 70217.059 | AP22: =($X22*(1+(($U22/100)*2))) -> 91867.552 | AQ22: =(AN22+(AN22*$J22)+(AN22*$M22)+(AN22*$N22)+(AN22*$O22)+(AN22*$P22)+(AN22*$Q22)+($R22)+(AN22*((52+$S22)/52))*(1+$T22))*1/$L22 -> 117677.81 | AR22: =(AO22+(AO22*$J22)+(AO22*$M22)+(AO22*$N22)+(AO22*$O22)+(AO22*$P22)+(AO22*$Q22)+($R22)+(AO22*((52+$S22)/52))*(1+$T22))*1/$L22 -> 169323.39 | AS22: =(AP22+(AP22*$J22)+(AP22*$M22)+(AP22*$N22)+(AP22*$O22)+(AP22*$P22)+(AP22*$Q22)+($R22)+(AP22*((52+$S22)/52))*(1+$T22))*1/$L22 -> 220968.98 | AT22: =AQ22/52/$K22 -> 62.428544 | AU22: =AR22/52/$K22 -> 89.826733 | AV22: =AS22/52/$K22 -> 117.22492 | AW22: =($V22*(1+(($U22/100)*3))) -> 48573.848 | AX22: =($W22*(1+(($U22/100)*3))) -> 70227.588 | AY22: =($X22*(1+(($U22/100)*3))) -> 91881.328 | AZ22: =(AW22+(AW22*$J22)+(AW22*$M22)+(AW22*$N22)+(AW22*$O22)+(AW22*$P22)+(AW22*$Q22)+($R22)+(AW22*((52+$S22)/52))*(1+$T22))*1/$L22 -> 117695.18 | BA22: =(AX22+(AX22*$J22)+(AX22*$M22)+(AX22*$N22)+(AX22*$O22)+(AX22*$P22)+(AX22*$Q22)+($R22)+(AX22*((52+$S22)/52))*(1+$T22))*1/$L22 -> 169348.51 | BB22: =(AY22+(AY22*$J22)+(AY22*$M22)+(AY22*$N22)+(AY22*$O22)+(AY22*$P22)+(AY22*$Q22)+($R22)+(AY22*((52+$S22)/52))*(1+$T22))*1/$L22 -> 221001.84 | BC22: =AZ22/52/$K22 -> 62.437761 | BD22: =BA22/52/$K22 -> 89.840058 | BE22: =BB22/52/$K22 -> 117.24236 | BF22: =($V22*(1+(($U22/100)*4))) -> 48581.131 | BG22: =($W22*(1+(($U22/100)*4))) -> 70238.118 | BH22: =($X22*(1+(($U22/100)*4))) -> 91895.104 | BI22: =(BF22+(BF22*$J22)+(BF22*$M22)+(BF22*$N22)+(BF22*$O22)+(BF22*$P22)+(BF22*$Q22)+($R22)+(BF22*((52+$S22)/52))*(1+$T22))*1/$L22 -> 117712.55 | BJ22: =(BG22+(BG22*$J22)+(BG22*$M22)+(BG22*$N22)+(BG22*$O22)+(BG22*$P22)+(BG22*$Q22)+($R22)+(BG22*((52+$S22)/52))*(1+$T22))*1/$L22 -> 169373.63 | BK22: =(BH22+(BH22*$J22)+(BH22*$M22)+(BH22*$N22)+(BH22*$O22)+(BH22*$P22)+(BH22*$Q22)+($R22)+(BH22*((52+$S22)/52))*(1+$T22))*1/$L22 -> 221034.7 | BL22: =BI22/52/$K22 -> 62.446977 | BM22: =BJ22/52/$K22 -> 89.853383 | BN22: =BK22/52/$K22 -> 117.25979
A23: QLD | B23: Medical scientist | C23: MS | D23: Hospital and Health Service General Employees (Queensland Health) Award - State 2015 | E23: HP2-3 | I23: 2022 | J23: 0.1275 | K23: 36.25 | L23: 1 | M23: 0.1 | N23: 0.035 | O23: 0 | P23: 0 | Q23: 0.046 | R23: 1826 | S23: 4 | T23: 0 | U23: 0.015 | V23: 69031 | W23: =V23+((X23-V23)/2) -> 104303.5 | X23: 139576 | Y23: =(V23+(V23*$J23)+(V23*$M23)+(V23*$N23)+(V23*$O23)+(V23*$P23)+(V23*$Q23)+($R23)+(V23*((52+$S23)/52))*(1+$T23))*1/$L23 -> 166494.14 | Z23: =(W23+(W23*$J23)+(W23*$M23)+(W23*$N23)+(W23*$O23)+(W23*$P23)+(W23*$Q23)+($R23)+(W23*((52+$S23)/52))*(1+$T23))*1/$L23 -> 250633.98 | AA23: =(X23+(X23*$J23)+(X23*$M23)+(X23*$N23)+(X23*$O23)+(X23*$P23)+(X23*$Q23)+($R23)+(X23*((52+$S23)/52))*(1+$T23))*1/$L23 -> 334773.81 | AB23: =Y23/52/$K23 -> 88.325804 | AC23: =Z23/52/$K23 -> 132.96232 | AD23: =AA23/52/$K23 -> 177.59884 | AE23: =($V23*(1+(($U23/100)*1))) -> 69041.355 | AF23: =($W23*(1+(($U23/100)*1))) -> 104319.15 | AG23: =($X23*(1+(($U23/100)*1))) -> 139596.94 | AH23: =(AE23+(AE23*$J23)+(AE23*$M23)+(AE23*$N23)+(AE23*$O23)+(AE23*$P23)+(AE23*$Q23)+($R23)+(AE23*((52+$S23)/52))*(1+$T23))*1/$L23 -> 166518.84 | AI23: =(AF23+(AF23*$J23)+(AF23*$M23)+(AF23*$N23)+(AF23*$O23)+(AF23*$P23)+(AF23*$Q23)+($R23)+(AF23*((52+$S23)/52))*(1+$T23))*1/$L23 -> 250671.3 | AJ23: =(AG23+(AG23*$J23)+(AG23*$M23)+(AG23*$N23)+(AG23*$O23)+(AG23*$P23)+(AG23*$Q23)+($R23)+(AG23*((52+$S23)/52))*(1+$T23))*1/$L23 -> 334823.75 | AK23: =AH23/52/$K23 -> 88.338908 | AL23: =AI23/52/$K23 -> 132.98212 | AM23: =AJ23/52/$K23 -> 177.62533 | AN23: =($V23*(1+(($U23/100)*2))) -> 69051.709 | AO23: =($W23*(1+(($U23/100)*2))) -> 104334.79 | AP23: =($X23*(1+(($U23/100)*2))) -> 139617.87 | AQ23: =(AN23+(AN23*$J23)+(AN23*$M23)+(AN23*$N23)+(AN23*$O23)+(AN23*$P23)+(AN23*$Q23)+($R23)+(AN23*((52+$S23)/52))*(1+$T23))*1/$L23 -> 166543.54 | AR23: =(AO23+(AO23*$J23)+(AO23*$M23)+(AO23*$N23)+(AO23*$O23)+(AO23*$P23)+(AO23*$Q23)+($R23)+(AO23*((52+$S23)/52))*(1+$T23))*1/$L23 -> 250708.62 | AS23: =(AP23+(AP23*$J23)+(AP23*$M23)+(AP23*$N23)+(AP23*$O23)+(AP23*$P23)+(AP23*$Q23)+($R23)+(AP23*((52+$S23)/52))*(1+$T23))*1/$L23 -> 334873.7 | AT23: =AQ23/52/$K23 -> 88.352011 | AU23: =AR23/52/$K23 -> 133.00192 | AV23: =AS23/52/$K23 -> 177.65183 | AW23: =($V23*(1+(($U23/100)*3))) -> 69062.064 | AX23: =($W23*(1+(($U23/100)*3))) -> 104350.44 | AY23: =($X23*(1+(($U23/100)*3))) -> 139638.81 | AZ23: =(AW23+(AW23*$J23)+(AW23*$M23)+(AW23*$N23)+(AW23*$O23)+(AW23*$P23)+(AW23*$Q23)+($R23)+(AW23*((52+$S23)/52))*(1+$T23))*1/$L23 -> 166568.24 | BA23: =(AX23+(AX23*$J23)+(AX23*$M23)+(AX23*$N23)+(AX23*$O23)+(AX23*$P23)+(AX23*$Q23)+($R23)+(AX23*((52+$S23)/52))*(1+$T23))*1/$L23 -> 250745.94 | BB23: =(AY23+(AY23*$J23)+(AY23*$M23)+(AY23*$N23)+(AY23*$O23)+(AY23*$P23)+(AY23*$Q23)+($R23)+(AY23*((52+$S23)/52))*(1+$T23))*1/$L23 -> 334923.64 | BC23: =AZ23/52/$K23 -> 88.365115 | BD23: =BA23/52/$K23 -> 133.02172 | BE23: =BB23/52/$K23 -> 177.67832 | BF23: =($V23*(1+(($U23/100)*4))) -> 69072.419 | BG23: =($W23*(1+(($U23/100)*4))) -> 104366.08 | BH23: =($X23*(1+(($U23/100)*4))) -> 139659.75 | BI23: =(BF23+(BF23*$J23)+(BF23*$M23)+(BF23*$N23)+(BF23*$O23)+(BF23*$P23)+(BF23*$Q23)+($R23)+(BF23*((52+$S23)/52))*(1+$T23))*1/$L23 -> 166592.94 | BJ23: =(BG23+(BG23*$J23)+(BG23*$M23)+(BG23*$N23)+(BG23*$O23)+(BG23*$P23)+(BG23*$Q23)+($R23)+(BG23*((52+$S23)/52))*(1+$T23))*1/$L23 -> 250783.26 | BK23: =(BH23+(BH23*$J23)+(BH23*$M23)+(BH23*$N23)+(BH23*$O23)+(BH23*$P23)+(BH23*$Q23)+($R23)+(BH23*((52+$S23)/52))*(1+$T23))*1/$L23 -> 334973.58 | BL23: =BI23/52/$K23 -> 88.378218 | BM23: =BJ23/52/$K23 -> 133.04152 | BN23: =BK23/52/$K23 -> 177.70482
A24: QLD | B24: Admin staff | C24: AS | D24: Hospital and Health Service General Employees (Queensland Health) Award - State 2015 | I24: 2022 | J24: 0.1275 | K24: 36.25 | L24: 1 | M24: 0.1 | N24: 0.035 | O24: 0 | P24: 0 | Q24: 0.046 | R24: 1826 | S24: 4 | T24: 0 | U24: 0.015 | V24: 47704 | W24: =V24+((X24-V24)/2) -> 63802.5 | X24: 79901 | Y24: =(V24+(V24*$J24)+(V24*$M24)+(V24*$N24)+(V24*$O24)+(V24*$P24)+(V24*$Q24)+($R24)+(V24*((52+$S24)/52))*(1+$T24))*1/$L24 -> 115620.22 | Z24: =(W24+(W24*$J24)+(W24*$M24)+(W24*$N24)+(W24*$O24)+(W24*$P24)+(W24*$Q24)+($R24)+(W24*((52+$S24)/52))*(1+$T24))*1/$L24 -> 154021.96 | AA24: =(X24+(X24*$J24)+(X24*$M24)+(X24*$N24)+(X24*$O24)+(X24*$P24)+(X24*$Q24)+($R24)+(X24*((52+$S24)/52))*(1+$T24))*1/$L24 -> 192423.69 | AB24: =Y24/52/$K24 -> 61.336988 | AC24: =Z24/52/$K24 -> 81.70926 | AD24: =AA24/52/$K24 -> 102.08153 | AE24: =($V24*(1+(($U24/100)*1))) -> 47711.156 | AF24: =($W24*(1+(($U24/100)*1))) -> 63812.07 | AG24: =($X24*(1+(($U24/100)*1))) -> 79912.985 | AH24: =(AE24+(AE24*$J24)+(AE24*$M24)+(AE24*$N24)+(AE24*$O24)+(AE24*$P24)+(AE24*$Q24)+($R24)+(AE24*((52+$S24)/52))*(1+$T24))*1/$L24 -> 115637.29 | AI24: =(AF24+(AF24*$J24)+(AF24*$M24)+(AF24*$N24)+(AF24*$O24)+(AF24*$P24)+(AF24*$Q24)+($R24)+(AF24*((52+$S24)/52))*(1+$T24))*1/$L24 -> 154044.79 | AJ24: =(AG24+(AG24*$J24)+(AG24*$M24)+(AG24*$N24)+(AG24*$O24)+(AG24*$P24)+(AG24*$Q24)+($R24)+(AG24*((52+$S24)/52))*(1+$T24))*1/$L24 -> 192452.28 | AK24: =AH24/52/$K24 -> 61.346043 | AL24: =AI24/52/$K24 -> 81.721371 | AM24: =AJ24/52/$K24 -> 102.0967 | AN24: =($V24*(1+(($U24/100)*2))) -> 47718.311 | AO24: =($W24*(1+(($U24/100)*2))) -> 63821.641 | AP24: =($X24*(1+(($U24/100)*2))) -> 79924.97 | AQ24: =(AN24+(AN24*$J24)+(AN24*$M24)+(AN24*$N24)+(AN24*$O24)+(AN24*$P24)+(AN24*$Q24)+($R24)+(AN24*((52+$S24)/52))*(1+$T24))*1/$L24 -> 115654.36 | AR24: =(AO24+(AO24*$J24)+(AO24*$M24)+(AO24*$N24)+(AO24*$O24)+(AO24*$P24)+(AO24*$Q24)+($R24)+(AO24*((52+$S24)/52))*(1+$T24))*1/$L24 -> 154067.61 | AS24: =(AP24+(AP24*$J24)+(AP24*$M24)+(AP24*$N24)+(AP24*$O24)+(AP24*$P24)+(AP24*$Q24)+($R24)+(AP24*((52+$S24)/52))*(1+$T24))*1/$L24 -> 192480.87 | AT24: =AQ24/52/$K24 -> 61.355099 | AU24: =AR24/52/$K24 -> 81.733483 | AV24: =AS24/52/$K24 -> 102.11187 | AW24: =($V24*(1+(($U24/100)*3))) -> 47725.467 | AX24: =($W24*(1+(($U24/100)*3))) -> 63831.211 | AY24: =($X24*(1+(($U24/100)*3))) -> 79936.955 | AZ24: =(AW24+(AW24*$J24)+(AW24*$M24)+(AW24*$N24)+(AW24*$O24)+(AW24*$P24)+(AW24*$Q24)+($R24)+(AW24*((52+$S24)/52))*(1+$T24))*1/$L24 -> 115671.43 | BA24: =(AX24+(AX24*$J24)+(AX24*$M24)+(AX24*$N24)+(AX24*$O24)+(AX24*$P24)+(AX24*$Q24)+($R24)+(AX24*((52+$S24)/52))*(1+$T24))*1/$L24 -> 154090.44 | BB24: =(AY24+(AY24*$J24)+(AY24*$M24)+(AY24*$N24)+(AY24*$O24)+(AY24*$P24)+(AY24*$Q24)+($R24)+(AY24*((52+$S24)/52))*(1+$T24))*1/$L24 -> 192509.46 | BC24: =AZ24/52/$K24 -> 61.364154 | BD24: =BA24/52/$K24 -> 81.745594 | BE24: =BB24/52/$K24 -> 102.12703 | BF24: =($V24*(1+(($U24/100)*4))) -> 47732.622 | BG24: =($W24*(1+(($U24/100)*4))) -> 63840.781 | BH24: =($X24*(1+(($U24/100)*4))) -> 79948.941 | BI24: =(BF24+(BF24*$J24)+(BF24*$M24)+(BF24*$N24)+(BF24*$O24)+(BF24*$P24)+(BF24*$Q24)+($R24)+(BF24*((52+$S24)/52))*(1+$T24))*1/$L24 -> 115688.5 | BJ24: =(BG24+(BG24*$J24)+(BG24*$M24)+(BG24*$N24)+(BG24*$O24)+(BG24*$P24)+(BG24*$Q24)+($R24)+(BG24*((52+$S24)/52))*(1+$T24))*1/$L24 -> 154113.27 | BK24: =(BH24+(BH24*$J24)+(BH24*$M24)+(BH24*$N24)+(BH24*$O24)+(BH24*$P24)+(BH24*$Q24)+($R24)+(BH24*((52+$S24)/52))*(1+$T24))*1/$L24 -> 192538.05 | BL24: =BI24/52/$K24 -> 61.373209 | BM24: =BJ24/52/$K24 -> 81.757705 | BN24: =BK24/52/$K24 -> 102.1422
A25: QLD | B25: Bioinformatics staff | C25: BI | D25: Hospital and Health Service General Employees (Queensland Health) Award - State 2015 | I25: 2022 | J25: 0.1275 | K25: 36.25 | L25: 1 | M25: 0.1 | N25: 0.035 | O25: 0 | P25: 0 | Q25: 0.046 | R25: 1826 | S25: 4 | T25: 0 | U25: 0.015 | V25: 69031 | W25: =V25+((X25-V25)/2) -> 104303.5 | X25: 139576 | Y25: =(V25+(V25*$J25)+(V25*$M25)+(V25*$N25)+(V25*$O25)+(V25*$P25)+(V25*$Q25)+($R25)+(V25*((52+$S25)/52))*(1+$T25))*1/$L25 -> 166494.14 | Z25: =(W25+(W25*$J25)+(W25*$M25)+(W25*$N25)+(W25*$O25)+(W25*$P25)+(W25*$Q25)+($R25)+(W25*((52+$S25)/52))*(1+$T25))*1/$L25 -> 250633.98 | AA25: =(X25+(X25*$J25)+(X25*$M25)+(X25*$N25)+(X25*$O25)+(X25*$P25)+(X25*$Q25)+($R25)+(X25*((52+$S25)/52))*(1+$T25))*1/$L25 -> 334773.81 | AB25: =Y25/52/$K25 -> 88.325804 | AC25: =Z25/52/$K25 -> 132.96232 | AD25: =AA25/52/$K25 -> 177.59884 | AE25: =($V25*(1+(($U25/100)*1))) -> 69041.355 | AF25: =($W25*(1+(($U25/100)*1))) -> 104319.15 | AG25: =($X25*(1+(($U25/100)*1))) -> 139596.94 | AH25: =(AE25+(AE25*$J25)+(AE25*$M25)+(AE25*$N25)+(AE25*$O25)+(AE25*$P25)+(AE25*$Q25)+($R25)+(AE25*((52+$S25)/52))*(1+$T25))*1/$L25 -> 166518.84 | AI25: =(AF25+(AF25*$J25)+(AF25*$M25)+(AF25*$N25)+(AF25*$O25)+(AF25*$P25)+(AF25*$Q25)+($R25)+(AF25*((52+$S25)/52))*(1+$T25))*1/$L25 -> 250671.3 | AJ25: =(AG25+(AG25*$J25)+(AG25*$M25)+(AG25*$N25)+(AG25*$O25)+(AG25*$P25)+(AG25*$Q25)+($R25)+(AG25*((52+$S25)/52))*(1+$T25))*1/$L25 -> 334823.75 | AK25: =AH25/52/$K25 -> 88.338908 | AL25: =AI25/52/$K25 -> 132.98212 | AM25: =AJ25/52/$K25 -> 177.62533 | AN25: =($V25*(1+(($U25/100)*2))) -> 69051.709 | AO25: =($W25*(1+(($U25/100)*2))) -> 104334.79 | AP25: =($X25*(1+(($U25/100)*2))) -> 139617.87 | AQ25: =(AN25+(AN25*$J25)+(AN25*$M25)+(AN25*$N25)+(AN25*$O25)+(AN25*$P25)+(AN25*$Q25)+($R25)+(AN25*((52+$S25)/52))*(1+$T25))*1/$L25 -> 166543.54 | AR25: =(AO25+(AO25*$J25)+(AO25*$M25)+(AO25*$N25)+(AO25*$O25)+(AO25*$P25)+(AO25*$Q25)+($R25)+(AO25*((52+$S25)/52))*(1+$T25))*1/$L25 -> 250708.62 | AS25: =(AP25+(AP25*$J25)+(AP25*$M25)+(AP25*$N25)+(AP25*$O25)+(AP25*$P25)+(AP25*$Q25)+($R25)+(AP25*((52+$S25)/52))*(1+$T25))*1/$L25 -> 334873.7 | AT25: =AQ25/52/$K25 -> 88.352011 | AU25: =AR25/52/$K25 -> 133.00192 | AV25: =AS25/52/$K25 -> 177.65183 | AW25: =($V25*(1+(($U25/100)*3))) -> 69062.064 | AX25: =($W25*(1+(($U25/100)*3))) -> 104350.44 | AY25: =($X25*(1+(($U25/100)*3))) -> 139638.81 | AZ25: =(AW25+(AW25*$J25)+(AW25*$M25)+(AW25*$N25)+(AW25*$O25)+(AW25*$P25)+(AW25*$Q25)+($R25)+(AW25*((52+$S25)/52))*(1+$T25))*1/$L25 -> 166568.24 | BA25: =(AX25+(AX25*$J25)+(AX25*$M25)+(AX25*$N25)+(AX25*$O25)+(AX25*$P25)+(AX25*$Q25)+($R25)+(AX25*((52+$S25)/52))*(1+$T25))*1/$L25 -> 250745.94 | BB25: =(AY25+(AY25*$J25)+(AY25*$M25)+(AY25*$N25)+(AY25*$O25)+(AY25*$P25)+(AY25*$Q25)+($R25)+(AY25*((52+$S25)/52))*(1+$T25))*1/$L25 -> 334923.64 | BC25: =AZ25/52/$K25 -> 88.365115 | BD25: =BA25/52/$K25 -> 133.02172 | BE25: =BB25/52/$K25 -> 177.67832 | BF25: =($V25*(1+(($U25/100)*4))) -> 69072.419 | BG25: =($W25*(1+(($U25/100)*4))) -> 104366.08 | BH25: =($X25*(1+(($U25/100)*4))) -> 139659.75 | BI25: =(BF25+(BF25*$J25)+(BF25*$M25)+(BF25*$N25)+(BF25*$O25)+(BF25*$P25)+(BF25*$Q25)+($R25)+(BF25*((52+$S25)/52))*(1+$T25))*1/$L25 -> 166592.94 | BJ25: =(BG25+(BG25*$J25)+(BG25*$M25)+(BG25*$N25)+(BG25*$O25)+(BG25*$P25)+(BG25*$Q25)+($R25)+(BG25*((52+$S25)/52))*(1+$T25))*1/$L25 -> 250783.26 | BK25: =(BH25+(BH25*$J25)+(BH25*$M25)+(BH25*$N25)+(BH25*$O25)+(BH25*$P25)+(BH25*$Q25)+($R25)+(BH25*((52+$S25)/52))*(1+$T25))*1/$L25 -> 334973.58 | BL25: =BI25/52/$K25 -> 88.378218 | BM25: =BJ25/52/$K25 -> 133.04152 | BN25: =BK25/52/$K25 -> 177.70482
A26: QLD | B26: Pathologists | C26: MP | D26: MEDICAL OFFICERS (QUEENSLAND HEALTH) AWARD – STATE 2015 | E26: L18-L27 | H26: 189406-262090 | I26: 2022 | J26: 0.1275 | K26: 38 | L26: 1 | M26: 0 | N26: 0.035 | O26: 0 | P26: 0.5 | Q26: 0.046 | R26: 21500 | S26: 4 | T26: 0 | U26: 0.015 | V26: 189406 | W26: =V26+((X26-V26)/2) -> 225748 | X26: 262090 | Y26: =(V26+(V26*$J26)+(V26*$M26)+(V26*$N26)+(V26*$O26)+(V26*$P26)+(V26*$Q26)+($R26)+(V26*((52+$S26)/52))*(1+$T26))*1/$L26 -> 549075.84 | Z26: =(W26+(W26*$J26)+(W26*$M26)+(W26*$N26)+(W26*$O26)+(W26*$P26)+(W26*$Q26)+($R26)+(W26*((52+$S26)/52))*(1+$T26))*1/$L26 -> 650303.69 | AA26: =(X26+(X26*$J26)+(X26*$M26)+(X26*$N26)+(X26*$O26)+(X26*$P26)+(X26*$Q26)+($R26)+(X26*((52+$S26)/52))*(1+$T26))*1/$L26 -> 751531.53 | AB26: =Y26/52/$K26 -> 277.87239 | AC26: =Z26/52/$K26 -> 329.10106 | AD26: =AA26/52/$K26 -> 380.32972 | AE26: =($V26*(1+(($U26/100)*1))) -> 189434.41 | AF26: =($W26*(1+(($U26/100)*1))) -> 225781.86 | AG26: =($X26*(1+(($U26/100)*1))) -> 262129.31 | AH26: =(AE26+(AE26*$J26)+(AE26*$M26)+(AE26*$N26)+(AE26*$O26)+(AE26*$P26)+(AE26*$Q26)+($R26)+(AE26*((52+$S26)/52))*(1+$T26))*1/$L26 -> 549154.98 | AI26: =(AF26+(AF26*$J26)+(AF26*$M26)+(AF26*$N26)+(AF26*$O26)+(AF26*$P26)+(AF26*$Q26)+($R26)+(AF26*((52+$S26)/52))*(1+$T26))*1/$L26 -> 650398.01 | AJ26: =(AG26+(AG26*$J26)+(AG26*$M26)+(AG26*$N26)+(AG26*$O26)+(AG26*$P26)+(AG26*$Q26)+($R26)+(AG26*((52+$S26)/52))*(1+$T26))*1/$L26 -> 751641.04 | AK26: =AH26/52/$K26 -> 277.91244 | AL26: =AI26/52/$K26 -> 329.14879 | AM26: =AJ26/52/$K26 -> 380.38514 | AN26: =($V26*(1+(($U26/100)*2))) -> 189462.82 | AO26: =($W26*(1+(($U26/100)*2))) -> 225815.72 | AP26: =($X26*(1+(($U26/100)*2))) -> 262168.63 | AQ26: =(AN26+(AN26*$J26)+(AN26*$M26)+(AN26*$N26)+(AN26*$O26)+(AN26*$P26)+(AN26*$Q26)+($R26)+(AN26*((52+$S26)/52))*(1+$T26))*1/$L26 -> 549234.12 | AR26: =(AO26+(AO26*$J26)+(AO26*$M26)+(AO26*$N26)+(AO26*$O26)+(AO26*$P26)+(AO26*$Q26)+($R26)+(AO26*((52+$S26)/52))*(1+$T26))*1/$L26 -> 650492.33 | AS26: =(AP26+(AP26*$J26)+(AP26*$M26)+(AP26*$N26)+(AP26*$O26)+(AP26*$P26)+(AP26*$Q26)+($R26)+(AP26*((52+$S26)/52))*(1+$T26))*1/$L26 -> 751750.54 | AT26: =AQ26/52/$K26 -> 277.95249 | AU26: =AR26/52/$K26 -> 329.19652 | AV26: =AS26/52/$K26 -> 380.44056 | AW26: =($V26*(1+(($U26/100)*3))) -> 189491.23 | AX26: =($W26*(1+(($U26/100)*3))) -> 225849.59 | AY26: =($X26*(1+(($U26/100)*3))) -> 262207.94 | AZ26: =(AW26+(AW26*$J26)+(AW26*$M26)+(AW26*$N26)+(AW26*$O26)+(AW26*$P26)+(AW26*$Q26)+($R26)+(AW26*((52+$S26)/52))*(1+$T26))*1/$L26 -> 549313.25 | BA26: =(AX26+(AX26*$J26)+(AX26*$M26)+(AX26*$N26)+(AX26*$O26)+(AX26*$P26)+(AX26*$Q26)+($R26)+(AX26*((52+$S26)/52))*(1+$T26))*1/$L26 -> 650586.65 | BB26: =(AY26+(AY26*$J26)+(AY26*$M26)+(AY26*$N26)+(AY26*$O26)+(AY26*$P26)+(AY26*$Q26)+($R26)+(AY26*((52+$S26)/52))*(1+$T26))*1/$L26 -> 751860.05 | BC26: =AZ26/52/$K26 -> 277.99254 | BD26: =BA26/52/$K26 -> 329.24426 | BE26: =BB26/52/$K26 -> 380.49598 | BF26: =($V26*(1+(($U26/100)*4))) -> 189519.64 | BG26: =($W26*(1+(($U26/100)*4))) -> 225883.45 | BH26: =($X26*(1+(($U26/100)*4))) -> 262247.25 | BI26: =(BF26+(BF26*$J26)+(BF26*$M26)+(BF26*$N26)+(BF26*$O26)+(BF26*$P26)+(BF26*$Q26)+($R26)+(BF26*((52+$S26)/52))*(1+$T26))*1/$L26 -> 549392.39 | BJ26: =(BG26+(BG26*$J26)+(BG26*$M26)+(BG26*$N26)+(BG26*$O26)+(BG26*$P26)+(BG26*$Q26)+($R26)+(BG26*((52+$S26)/52))*(1+$T26))*1/$L26 -> 650680.97 | BK26: =(BH26+(BH26*$J26)+(BH26*$M26)+(BH26*$N26)+(BH26*$O26)+(BH26*$P26)+(BH26*$Q26)+($R26)+(BH26*((52+$S26)/52))*(1+$T26))*1/$L26 -> 751969.55 | BL26: =BI26/52/$K26 -> 278.03259 | BM26: =BJ26/52/$K26 -> 329.29199 | BN26: =BK26/52/$K26 -> 380.55139
A28: WA | B28: Lab technician | C28: LT | D28: Health Salaried Officers Agreement | E28: G1-3 | I28: 2022 | J28: 0.105 | K28: 38 | L28: 1 | M28: 0.1 | N28: 0.035 | O28: 0 | P28: 0 | Q28: 0.046 | R28: 0 | S28: 4 | T28: 0.2 | U28: 0.015 | V28: 57579 | W28: =V28+((X28-V28)/2) -> 71368 | X28: 85157 | Y28: =(V28+(V28*$J28)+(V28*$M28)+(V28*$N28)+(V28*$O28)+(V28*$P28)+(V28*$Q28)+($R28)+(V28*((52+$S28)/52))*(1+$T28))*1/$L28 -> 148456.38 | Z28: =(W28+(W28*$J28)+(W28*$M28)+(W28*$N28)+(W28*$O28)+(W28*$P28)+(W28*$Q28)+($R28)+(W28*((52+$S28)/52))*(1+$T28))*1/$L28 -> 184008.66 | AA28: =(X28+(X28*$J28)+(X28*$M28)+(X28*$N28)+(X28*$O28)+(X28*$P28)+(X28*$Q28)+($R28)+(X28*((52+$S28)/52))*(1+$T28))*1/$L28 -> 219560.95 | AB28: =Y28/52/$K28 -> 75.129746 | AC28: =Z28/52/$K28 -> 93.121793 | AD28: =AA28/52/$K28 -> 111.11384 | AE28: =($V28*(1+(($U28/100)*1))) -> 57587.637 | AF28: =($W28*(1+(($U28/100)*1))) -> 71378.705 | AG28: =($X28*(1+(($U28/100)*1))) -> 85169.774 | AH28: =(AE28+(AE28*$J28)+(AE28*$M28)+(AE28*$N28)+(AE28*$O28)+(AE28*$P28)+(AE28*$Q28)+($R28)+(AE28*((52+$S28)/52))*(1+$T28))*1/$L28 -> 148478.65 | AI28: =(AF28+(AF28*$J28)+(AF28*$M28)+(AF28*$N28)+(AF28*$O28)+(AF28*$P28)+(AF28*$Q28)+($R28)+(AF28*((52+$S28)/52))*(1+$T28))*1/$L28 -> 184036.26 | AJ28: =(AG28+(AG28*$J28)+(AG28*$M28)+(AG28*$N28)+(AG28*$O28)+(AG28*$P28)+(AG28*$Q28)+($R28)+(AG28*((52+$S28)/52))*(1+$T28))*1/$L28 -> 219593.88 | AK28: =AH28/52/$K28 -> 75.141016 | AL28: =AI28/52/$K28 -> 93.135761 | AM28: =AJ28/52/$K28 -> 111.13051 | AN28: =($V28*(1+(($U28/100)*2))) -> 57596.274 | AO28: =($W28*(1+(($U28/100)*2))) -> 71389.41 | AP28: =($X28*(1+(($U28/100)*2))) -> 85182.547 | AQ28: =(AN28+(AN28*$J28)+(AN28*$M28)+(AN28*$N28)+(AN28*$O28)+(AN28*$P28)+(AN28*$Q28)+($R28)+(AN28*((52+$S28)/52))*(1+$T28))*1/$L28 -> 148500.92 | AR28: =(AO28+(AO28*$J28)+(AO28*$M28)+(AO28*$N28)+(AO28*$O28)+(AO28*$P28)+(AO28*$Q28)+($R28)+(AO28*((52+$S28)/52))*(1+$T28))*1/$L28 -> 184063.87 | AS28: =(AP28+(AP28*$J28)+(AP28*$M28)+(AP28*$N28)+(AP28*$O28)+(AP28*$P28)+(AP28*$Q28)+($R28)+(AP28*((52+$S28)/52))*(1+$T28))*1/$L28 -> 219626.82 | AT28: =AQ28/52/$K28 -> 75.152285 | AU28: =AR28/52/$K28 -> 93.14973 | AV28: =AS28/52/$K28 -> 111.14717 | AW28: =($V28*(1+(($U28/100)*3))) -> 57604.911 | AX28: =($W28*(1+(($U28/100)*3))) -> 71400.116 | AY28: =($X28*(1+(($U28/100)*3))) -> 85195.321 | AZ28: =(AW28+(AW28*$J28)+(AW28*$M28)+(AW28*$N28)+(AW28*$O28)+(AW28*$P28)+(AW28*$Q28)+($R28)+(AW28*((52+$S28)/52))*(1+$T28))*1/$L28 -> 148523.18 | BA28: =(AX28+(AX28*$J28)+(AX28*$M28)+(AX28*$N28)+(AX28*$O28)+(AX28*$P28)+(AX28*$Q28)+($R28)+(AX28*((52+$S28)/52))*(1+$T28))*1/$L28 -> 184091.47 | BB28: =(AY28+(AY28*$J28)+(AY28*$M28)+(AY28*$N28)+(AY28*$O28)+(AY28*$P28)+(AY28*$Q28)+($R28)+(AY28*((52+$S28)/52))*(1+$T28))*1/$L28 -> 219659.75 | BC28: =AZ28/52/$K28 -> 75.163555 | BD28: =BA28/52/$K28 -> 93.163698 | BE28: =BB28/52/$K28 -> 111.16384 | BF28: =($V28*(1+(($U28/100)*4))) -> 57613.547 | BG28: =($W28*(1+(($U28/100)*4))) -> 71410.821 | BH28: =($X28*(1+(($U28/100)*4))) -> 85208.094 | BI28: =(BF28+(BF28*$J28)+(BF28*$M28)+(BF28*$N28)+(BF28*$O28)+(BF28*$P28)+(BF28*$Q28)+($R28)+(BF28*((52+$S28)/52))*(1+$T28))*1/$L28 -> 148545.45 | BJ28: =(BG28+(BG28*$J28)+(BG28*$M28)+(BG28*$N28)+(BG28*$O28)+(BG28*$P28)+(BG28*$Q28)+($R28)+(BG28*((52+$S28)/52))*(1+$T28))*1/$L28 -> 184119.07 | BK28: =(BH28+(BH28*$J28)+(BH28*$M28)+(BH28*$N28)+(BH28*$O28)+(BH28*$P28)+(BH28*$Q28)+($R28)+(BH28*((52+$S28)/52))*(1+$T28))*1/$L28 -> 219692.68 | BL28: =BI28/52/$K28 -> 75.174824 | BM28: =BJ28/52/$K28 -> 93.177666 | BN28: =BK28/52/$K28 -> 111.18051
A29: WA | B29: Medical scientist | C29: MS | D29: Health Salaried Officers Agreement | E29: P1-5 | I29: 2022 | J29: 0.105 | K29: 38 | L29: 1 | M29: 0.1 | N29: 0.035 | O29: 0 | P29: 0 | Q29: 0.046 | R29: 0 | S29: 4 | T29: 0.2 | U29: 0.015 | V29: 77833 | W29: =V29+((X29-V29)/2) -> 109041 | X29: 140249 | Y29: =(V29+(V29*$J29)+(V29*$M29)+(V29*$N29)+(V29*$O29)+(V29*$P29)+(V29*$Q29)+($R29)+(V29*((52+$S29)/52))*(1+$T29))*1/$L29 -> 200677.42 | Z29: =(W29+(W29*$J29)+(W29*$M29)+(W29*$N29)+(W29*$O29)+(W29*$P29)+(W29*$Q29)+($R29)+(W29*((52+$S29)/52))*(1+$T29))*1/$L29 -> 281141.25 | AA29: =(X29+(X29*$J29)+(X29*$M29)+(X29*$N29)+(X29*$O29)+(X29*$P29)+(X29*$Q29)+($R29)+(X29*((52+$S29)/52))*(1+$T29))*1/$L29 -> 361605.08 | AB29: =Y29/52/$K29 -> 101.5574 | AC29: =Z29/52/$K29 -> 142.27796 | AD29: =AA29/52/$K29 -> 182.99852 | AE29: =($V29*(1+(($U29/100)*1))) -> 77844.675 | AF29: =($W29*(1+(($U29/100)*1))) -> 109057.36 | AG29: =($X29*(1+(($U29/100)*1))) -> 140270.04 | AH29: =(AE29+(AE29*$J29)+(AE29*$M29)+(AE29*$N29)+(AE29*$O29)+(AE29*$P29)+(AE29*$Q29)+($R29)+(AE29*((52+$S29)/52))*(1+$T29))*1/$L29 -> 200707.52 | AI29: =(AF29+(AF29*$J29)+(AF29*$M29)+(AF29*$N29)+(AF29*$O29)+(AF29*$P29)+(AF29*$Q29)+($R29)+(AF29*((52+$S29)/52))*(1+$T29))*1/$L29 -> 281183.42 | AJ29: =(AG29+(AG29*$J29)+(AG29*$M29)+(AG29*$N29)+(AG29*$O29)+(AG29*$P29)+(AG29*$Q29)+($R29)+(AG29*((52+$S29)/52))*(1+$T29))*1/$L29 -> 361659.32 | AK29: =AH29/52/$K29 -> 101.57263 | AL29: =AI29/52/$K29 -> 142.2993 | AM29: =AJ29/52/$K29 -> 183.02597 | AN29: =($V29*(1+(($U29/100)*2))) -> 77856.35 | AO29: =($W29*(1+(($U29/100)*2))) -> 109073.71 | AP29: =($X29*(1+(($U29/100)*2))) -> 140291.07 | AQ29: =(AN29+(AN29*$J29)+(AN29*$M29)+(AN29*$N29)+(AN29*$O29)+(AN29*$P29)+(AN29*$Q29)+($R29)+(AN29*((52+$S29)/52))*(1+$T29))*1/$L29 -> 200737.63 | AR29: =(AO29+(AO29*$J29)+(AO29*$M29)+(AO29*$N29)+(AO29*$O29)+(AO29*$P29)+(AO29*$Q29)+($R29)+(AO29*((52+$S29)/52))*(1+$T29))*1/$L29 -> 281225.59 | AS29: =(AP29+(AP29*$J29)+(AP29*$M29)+(AP29*$N29)+(AP29*$O29)+(AP29*$P29)+(AP29*$Q29)+($R29)+(AP29*((52+$S29)/52))*(1+$T29))*1/$L29 -> 361713.56 | AT29: =AQ29/52/$K29 -> 101.58787 | AU29: =AR29/52/$K29 -> 142.32064 | AV29: =AS29/52/$K29 -> 183.05342 | AW29: =($V29*(1+(($U29/100)*3))) -> 77868.025 | AX29: =($W29*(1+(($U29/100)*3))) -> 109090.07 | AY29: =($X29*(1+(($U29/100)*3))) -> 140312.11 | AZ29: =(AW29+(AW29*$J29)+(AW29*$M29)+(AW29*$N29)+(AW29*$O29)+(AW29*$P29)+(AW29*$Q29)+($R29)+(AW29*((52+$S29)/52))*(1+$T29))*1/$L29 -> 200767.73 | BA29: =(AX29+(AX29*$J29)+(AX29*$M29)+(AX29*$N29)+(AX29*$O29)+(AX29*$P29)+(AX29*$Q29)+($R29)+(AX29*((52+$S29)/52))*(1+$T29))*1/$L29 -> 281267.76 | BB29: =(AY29+(AY29*$J29)+(AY29*$M29)+(AY29*$N29)+(AY29*$O29)+(AY29*$P29)+(AY29*$Q29)+($R29)+(AY29*((52+$S29)/52))*(1+$T29))*1/$L29 -> 361767.8 | BC29: =AZ29/52/$K29 -> 101.6031 | BD29: =BA29/52/$K29 -> 142.34199 | BE29: =BB29/52/$K29 -> 183.08087 | BF29: =($V29*(1+(($U29/100)*4))) -> 77879.7 | BG29: =($W29*(1+(($U29/100)*4))) -> 109106.42 | BH29: =($X29*(1+(($U29/100)*4))) -> 140333.15 | BI29: =(BF29+(BF29*$J29)+(BF29*$M29)+(BF29*$N29)+(BF29*$O29)+(BF29*$P29)+(BF29*$Q29)+($R29)+(BF29*((52+$S29)/52))*(1+$T29))*1/$L29 -> 200797.83 | BJ29: =(BG29+(BG29*$J29)+(BG29*$M29)+(BG29*$N29)+(BG29*$O29)+(BG29*$P29)+(BG29*$Q29)+($R29)+(BG29*((52+$S29)/52))*(1+$T29))*1/$L29 -> 281309.93 | BK29: =(BH29+(BH29*$J29)+(BH29*$M29)+(BH29*$N29)+(BH29*$O29)+(BH29*$P29)+(BH29*$Q29)+($R29)+(BH29*((52+$S29)/52))*(1+$T29))*1/$L29 -> 361822.04 | BL29: =BI29/52/$K29 -> 101.61833 | BM29: =BJ29/52/$K29 -> 142.36333 | BN29: =BK29/52/$K29 -> 183.10832
A30: WA | B30: Admin staff | C30: AS | D30: Health Salaried Officers Agreement | E30: G1-2 | I30: 2022 | J30: 0.105 | K30: 38 | L30: 1 | M30: 0.1 | N30: 0.035 | O30: 0 | P30: 0 | Q30: 0.046 | R30: 0 | S30: 4 | T30: 0.2 | U30: 0.015 | V30: 57579 | W30: =V30+((X30-V30)/2) -> 63314 | X30: 69049 | Y30: =(V30+(V30*$J30)+(V30*$M30)+(V30*$N30)+(V30*$O30)+(V30*$P30)+(V30*$Q30)+($R30)+(V30*((52+$S30)/52))*(1+$T30))*1/$L30 -> 148456.38 | Z30: =(W30+(W30*$J30)+(W30*$M30)+(W30*$N30)+(W30*$O30)+(W30*$P30)+(W30*$Q30)+($R30)+(W30*((52+$S30)/52))*(1+$T30))*1/$L30 -> 163242.97 | AA30: =(X30+(X30*$J30)+(X30*$M30)+(X30*$N30)+(X30*$O30)+(X30*$P30)+(X30*$Q30)+($R30)+(X30*((52+$S30)/52))*(1+$T30))*1/$L30 -> 178029.57 | AB30: =Y30/52/$K30 -> 75.129746 | AC30: =Z30/52/$K30 -> 82.612841 | AD30: =AA30/52/$K30 -> 90.095935 | AE30: =($V30*(1+(($U30/100)*1))) -> 57587.637 | AF30: =($W30*(1+(($U30/100)*1))) -> 63323.497 | AG30: =($X30*(1+(($U30/100)*1))) -> 69059.357 | AH30: =(AE30+(AE30*$J30)+(AE30*$M30)+(AE30*$N30)+(AE30*$O30)+(AE30*$P30)+(AE30*$Q30)+($R30)+(AE30*((52+$S30)/52))*(1+$T30))*1/$L30 -> 148478.65 | AI30: =(AF30+(AF30*$J30)+(AF30*$M30)+(AF30*$N30)+(AF30*$O30)+(AF30*$P30)+(AF30*$Q30)+($R30)+(AF30*((52+$S30)/52))*(1+$T30))*1/$L30 -> 163267.46 | AJ30: =(AG30+(AG30*$J30)+(AG30*$M30)+(AG30*$N30)+(AG30*$O30)+(AG30*$P30)+(AG30*$Q30)+($R30)+(AG30*((52+$S30)/52))*(1+$T30))*1/$L30 -> 178056.27 | AK30: =AH30/52/$K30 -> 75.141016 | AL30: =AI30/52/$K30 -> 82.625233 | AM30: =AJ30/52/$K30 -> 90.10945 | AN30: =($V30*(1+(($U30/100)*2))) -> 57596.274 | AO30: =($W30*(1+(($U30/100)*2))) -> 63332.994 | AP30: =($X30*(1+(($U30/100)*2))) -> 69069.715 | AQ30: =(AN30+(AN30*$J30)+(AN30*$M30)+(AN30*$N30)+(AN30*$O30)+(AN30*$P30)+(AN30*$Q30)+($R30)+(AN30*((52+$S30)/52))*(1+$T30))*1/$L30 -> 148500.92 | AR30: =(AO30+(AO30*$J30)+(AO30*$M30)+(AO30*$N30)+(AO30*$O30)+(AO30*$P30)+(AO30*$Q30)+($R30)+(AO30*((52+$S30)/52))*(1+$T30))*1/$L30 -> 163291.95 | AS30: =(AP30+(AP30*$J30)+(AP30*$M30)+(AP30*$N30)+(AP30*$O30)+(AP30*$P30)+(AP30*$Q30)+($R30)+(AP30*((52+$S30)/52))*(1+$T30))*1/$L30 -> 178082.98 | AT30: =AQ30/52/$K30 -> 75.152285 | AU30: =AR30/52/$K30 -> 82.637625 | AV30: =AS30/52/$K30 -> 90.122964 | AW30: =($V30*(1+(($U30/100)*3))) -> 57604.911 | AX30: =($W30*(1+(($U30/100)*3))) -> 63342.491 | AY30: =($X30*(1+(($U30/100)*3))) -> 69080.072 | AZ30: =(AW30+(AW30*$J30)+(AW30*$M30)+(AW30*$N30)+(AW30*$O30)+(AW30*$P30)+(AW30*$Q30)+($R30)+(AW30*((52+$S30)/52))*(1+$T30))*1/$L30 -> 148523.18 | BA30: =(AX30+(AX30*$J30)+(AX30*$M30)+(AX30*$N30)+(AX30*$O30)+(AX30*$P30)+(AX30*$Q30)+($R30)+(AX30*((52+$S30)/52))*(1+$T30))*1/$L30 -> 163316.43 | BB30: =(AY30+(AY30*$J30)+(AY30*$M30)+(AY30*$N30)+(AY30*$O30)+(AY30*$P30)+(AY30*$Q30)+($R30)+(AY30*((52+$S30)/52))*(1+$T30))*1/$L30 -> 178109.68 | BC30: =AZ30/52/$K30 -> 75.163555 | BD30: =BA30/52/$K30 -> 82.650016 | BE30: =BB30/52/$K30 -> 90.136478 | BF30: =($V30*(1+(($U30/100)*4))) -> 57613.547 | BG30: =($W30*(1+(($U30/100)*4))) -> 63351.988 | BH30: =($X30*(1+(($U30/100)*4))) -> 69090.429 | BI30: =(BF30+(BF30*$J30)+(BF30*$M30)+(BF30*$N30)+(BF30*$O30)+(BF30*$P30)+(BF30*$Q30)+($R30)+(BF30*((52+$S30)/52))*(1+$T30))*1/$L30 -> 148545.45 | BJ30: =(BG30+(BG30*$J30)+(BG30*$M30)+(BG30*$N30)+(BG30*$O30)+(BG30*$P30)+(BG30*$Q30)+($R30)+(BG30*((52+$S30)/52))*(1+$T30))*1/$L30 -> 163340.92 | BK30: =(BH30+(BH30*$J30)+(BH30*$M30)+(BH30*$N30)+(BH30*$O30)+(BH30*$P30)+(BH30*$Q30)+($R30)+(BH30*((52+$S30)/52))*(1+$T30))*1/$L30 -> 178136.39 | BL30: =BI30/52/$K30 -> 75.174824 | BM30: =BJ30/52/$K30 -> 82.662408 | BN30: =BK30/52/$K30 -> 90.149993
A31: WA | B31: Bioinformatics staff | C31: BI | D31: Health Salaried Officers Agreement | E31: G4-5 | I31: 2022 | J31: 0.105 | K31: 38 | L31: 1 | M31: 0.1 | N31: 0.035 | O31: 0 | P31: 0 | Q31: 0.046 | R31: 0 | S31: 4 | T31: 0.2 | U31: 0.015 | V31: 79898 | W31: =V31+((X31-V31)/2) -> 86781 | X31: 93664 | Y31: =(V31+(V31*$J31)+(V31*$M31)+(V31*$N31)+(V31*$O31)+(V31*$P31)+(V31*$Q31)+($R31)+(V31*((52+$S31)/52))*(1+$T31))*1/$L31 -> 206001.63 | Z31: =(W31+(W31*$J31)+(W31*$M31)+(W31*$N31)+(W31*$O31)+(W31*$P31)+(W31*$Q31)+($R31)+(W31*((52+$S31)/52))*(1+$T31))*1/$L31 -> 223748.12 | AA31: =(X31+(X31*$J31)+(X31*$M31)+(X31*$N31)+(X31*$O31)+(X31*$P31)+(X31*$Q31)+($R31)+(X31*((52+$S31)/52))*(1+$T31))*1/$L31 -> 241494.61 | AB31: =Y31/52/$K31 -> 104.25184 | AC31: =Z31/52/$K31 -> 113.23285 | AD31: =AA31/52/$K31 -> 122.21387 | AE31: =($V31*(1+(($U31/100)*1))) -> 79909.985 | AF31: =($W31*(1+(($U31/100)*1))) -> 86794.017 | AG31: =($X31*(1+(($U31/100)*1))) -> 93678.05 | AH31: =(AE31+(AE31*$J31)+(AE31*$M31)+(AE31*$N31)+(AE31*$O31)+(AE31*$P31)+(AE31*$Q31)+($R31)+(AE31*((52+$S31)/52))*(1+$T31))*1/$L31 -> 206032.53 | AI31: =(AF31+(AF31*$J31)+(AF31*$M31)+(AF31*$N31)+(AF31*$O31)+(AF31*$P31)+(AF31*$Q31)+($R31)+(AF31*((52+$S31)/52))*(1+$T31))*1/$L31 -> 223781.68 | AJ31: =(AG31+(AG31*$J31)+(AG31*$M31)+(AG31*$N31)+(AG31*$O31)+(AG31*$P31)+(AG31*$Q31)+($R31)+(AG31*((52+$S31)/52))*(1+$T31))*1/$L31 -> 241530.84 | AK31: =AH31/52/$K31 -> 104.26747 | AL31: =AI31/52/$K31 -> 113.24984 | AM31: =AJ31/52/$K31 -> 122.2322 | AN31: =($V31*(1+(($U31/100)*2))) -> 79921.969 | AO31: =($W31*(1+(($U31/100)*2))) -> 86807.034 | AP31: =($X31*(1+(($U31/100)*2))) -> 93692.099 | AQ31: =(AN31+(AN31*$J31)+(AN31*$M31)+(AN31*$N31)+(AN31*$O31)+(AN31*$P31)+(AN31*$Q31)+($R31)+(AN31*((52+$S31)/52))*(1+$T31))*1/$L31 -> 206063.43 | AR31: =(AO31+(AO31*$J31)+(AO31*$M31)+(AO31*$N31)+(AO31*$O31)+(AO31*$P31)+(AO31*$Q31)+($R31)+(AO31*((52+$S31)/52))*(1+$T31))*1/$L31 -> 223815.24 | AS31: =(AP31+(AP31*$J31)+(AP31*$M31)+(AP31*$N31)+(AP31*$O31)+(AP31*$P31)+(AP31*$Q31)+($R31)+(AP31*((52+$S31)/52))*(1+$T31))*1/$L31 -> 241567.06 | AT31: =AQ31/52/$K31 -> 104.28311 | AU31: =AR31/52/$K31 -> 113.26682 | AV31: =AS31/52/$K31 -> 122.25054 | AW31: =($V31*(1+(($U31/100)*3))) -> 79933.954 | AX31: =($W31*(1+(($U31/100)*3))) -> 86820.051 | AY31: =($X31*(1+(($U31/100)*3))) -> 93706.149 | AZ31: =(AW31+(AW31*$J31)+(AW31*$M31)+(AW31*$N31)+(AW31*$O31)+(AW31*$P31)+(AW31*$Q31)+($R31)+(AW31*((52+$S31)/52))*(1+$T31))*1/$L31 -> 206094.33 | BA31: =(AX31+(AX31*$J31)+(AX31*$M31)+(AX31*$N31)+(AX31*$O31)+(AX31*$P31)+(AX31*$Q31)+($R31)+(AX31*((52+$S31)/52))*(1+$T31))*1/$L31 -> 223848.81 | BB31: =(AY31+(AY31*$J31)+(AY31*$M31)+(AY31*$N31)+(AY31*$O31)+(AY31*$P31)+(AY31*$Q31)+($R31)+(AY31*((52+$S31)/52))*(1+$T31))*1/$L31 -> 241603.28 | BC31: =AZ31/52/$K31 -> 104.29875 | BD31: =BA31/52/$K31 -> 113.28381 | BE31: =BB31/52/$K31 -> 122.26887 | BF31: =($V31*(1+(($U31/100)*4))) -> 79945.939 | BG31: =($W31*(1+(($U31/100)*4))) -> 86833.069 | BH31: =($X31*(1+(($U31/100)*4))) -> 93720.198 | BI31: =(BF31+(BF31*$J31)+(BF31*$M31)+(BF31*$N31)+(BF31*$O31)+(BF31*$P31)+(BF31*$Q31)+($R31)+(BF31*((52+$S31)/52))*(1+$T31))*1/$L31 -> 206125.23 | BJ31: =(BG31+(BG31*$J31)+(BG31*$M31)+(BG31*$N31)+(BG31*$O31)+(BG31*$P31)+(BG31*$Q31)+($R31)+(BG31*((52+$S31)/52))*(1+$T31))*1/$L31 -> 223882.37 | BK31: =(BH31+(BH31*$J31)+(BH31*$M31)+(BH31*$N31)+(BH31*$O31)+(BH31*$P31)+(BH31*$Q31)+($R31)+(BH31*((52+$S31)/52))*(1+$T31))*1/$L31 -> 241639.51 | BL31: =BI31/52/$K31 -> 104.31439 | BM31: =BJ31/52/$K31 -> 113.30079 | BN31: =BK31/52/$K31 -> 122.2872
A32: WA | B32: Pathologists | C32: MP | D32: WA HEALTH SYSTEM – MEDICAL PRACTITIONERS – AMA INDUSTRIAL AGREEMENT 2022 | E32: Consultant Year 1-9 | I32: 2022 | J32: 0.105 | K32: 40 | L32: 1 | M32: 0 | N32: 0.035 | O32: 0 | P32: 0 | Q32: 0.046 | R32: 28909 | S32: =160/40 -> 4 | T32: 0 | U32: 0.015 | V32: 297757 | W32: =V32+((X32-V32)/2) -> 342136 | X32: 386515 | Y32: =(V32+(V32*$J32)+(V32*$M32)+(V32*$N32)+(V32*$O32)+(V32*$P32)+(V32*$Q32)+($R32)+(V32*((52+$S32)/52))*(1+$T32))*1/$L32 -> 702710.19 | Z32: =(W32+(W32*$J32)+(W32*$M32)+(W32*$N32)+(W32*$O32)+(W32*$P32)+(W32*$Q32)+($R32)+(W32*((52+$S32)/52))*(1+$T32))*1/$L32 -> 803136.45 | AA32: =(X32+(X32*$J32)+(X32*$M32)+(X32*$N32)+(X32*$O32)+(X32*$P32)+(X32*$Q32)+($R32)+(X32*((52+$S32)/52))*(1+$T32))*1/$L32 -> 903562.71 | AB32: =Y32/52/$K32 -> 337.84144 | AC32: =Z32/52/$K32 -> 386.12329 | AD32: =AA32/52/$K32 -> 434.40515 | AE32: =($V32*(1+(($U32/100)*1))) -> 297801.66 | AF32: =($W32*(1+(($U32/100)*1))) -> 342187.32 | AG32: =($X32*(1+(($U32/100)*1))) -> 386572.98 | AH32: =(AE32+(AE32*$J32)+(AE32*$M32)+(AE32*$N32)+(AE32*$O32)+(AE32*$P32)+(AE32*$Q32)+($R32)+(AE32*((52+$S32)/52))*(1+$T32))*1/$L32 -> 702811.26 | AI32: =(AF32+(AF32*$J32)+(AF32*$M32)+(AF32*$N32)+(AF32*$O32)+(AF32*$P32)+(AF32*$Q32)+($R32)+(AF32*((52+$S32)/52))*(1+$T32))*1/$L32 -> 803252.58 | AJ32: =(AG32+(AG32*$J32)+(AG32*$M32)+(AG32*$N32)+(AG32*$O32)+(AG32*$P32)+(AG32*$Q32)+($R32)+(AG32*((52+$S32)/52))*(1+$T32))*1/$L32 -> 903693.91 | AK32: =AH32/52/$K32 -> 337.89003 | AL32: =AI32/52/$K32 -> 386.17913 | AM32: =AJ32/52/$K32 -> 434.46823 | AN32: =($V32*(1+(($U32/100)*2))) -> 297846.33 | AO32: =($W32*(1+(($U32/100)*2))) -> 342238.64 | AP32: =($X32*(1+(($U32/100)*2))) -> 386630.95 | AQ32: =(AN32+(AN32*$J32)+(AN32*$M32)+(AN32*$N32)+(AN32*$O32)+(AN32*$P32)+(AN32*$Q32)+($R32)+(AN32*((52+$S32)/52))*(1+$T32))*1/$L32 -> 702912.33 | AR32: =(AO32+(AO32*$J32)+(AO32*$M32)+(AO32*$N32)+(AO32*$O32)+(AO32*$P32)+(AO32*$Q32)+($R32)+(AO32*((52+$S32)/52))*(1+$T32))*1/$L32 -> 803368.72 | AS32: =(AP32+(AP32*$J32)+(AP32*$M32)+(AP32*$N32)+(AP32*$O32)+(AP32*$P32)+(AP32*$Q32)+($R32)+(AP32*((52+$S32)/52))*(1+$T32))*1/$L32 -> 903825.11 | AT32: =AQ32/52/$K32 -> 337.93862 | AU32: =AR32/52/$K32 -> 386.23496 | AV32: =AS32/52/$K32 -> 434.5313 | AW32: =($V32*(1+(($U32/100)*3))) -> 297890.99 | AX32: =($W32*(1+(($U32/100)*3))) -> 342289.96 | AY32: =($X32*(1+(($U32/100)*3))) -> 386688.93 | AZ32: =(AW32+(AW32*$J32)+(AW32*$M32)+(AW32*$N32)+(AW32*$O32)+(AW32*$P32)+(AW32*$Q32)+($R32)+(AW32*((52+$S32)/52))*(1+$T32))*1/$L32 -> 703013.4 | BA32: =(AX32+(AX32*$J32)+(AX32*$M32)+(AX32*$N32)+(AX32*$O32)+(AX32*$P32)+(AX32*$Q32)+($R32)+(AX32*((52+$S32)/52))*(1+$T32))*1/$L32 -> 803484.85 | BB32: =(AY32+(AY32*$J32)+(AY32*$M32)+(AY32*$N32)+(AY32*$O32)+(AY32*$P32)+(AY32*$Q32)+($R32)+(AY32*((52+$S32)/52))*(1+$T32))*1/$L32 -> 903956.31 | BC32: =AZ32/52/$K32 -> 337.98721 | BD32: =BA32/52/$K32 -> 386.29079 | BE32: =BB32/52/$K32 -> 434.59438 | BF32: =($V32*(1+(($U32/100)*4))) -> 297935.65 | BG32: =($W32*(1+(($U32/100)*4))) -> 342341.28 | BH32: =($X32*(1+(($U32/100)*4))) -> 386746.91 | BI32: =(BF32+(BF32*$J32)+(BF32*$M32)+(BF32*$N32)+(BF32*$O32)+(BF32*$P32)+(BF32*$Q32)+($R32)+(BF32*((52+$S32)/52))*(1+$T32))*1/$L32 -> 703114.47 | BJ32: =(BG32+(BG32*$J32)+(BG32*$M32)+(BG32*$N32)+(BG32*$O32)+(BG32*$P32)+(BG32*$Q32)+($R32)+(BG32*((52+$S32)/52))*(1+$T32))*1/$L32 -> 803600.99 | BK32: =(BH32+(BH32*$J32)+(BH32*$M32)+(BH32*$N32)+(BH32*$O32)+(BH32*$P32)+(BH32*$Q32)+($R32)+(BH32*((52+$S32)/52))*(1+$T32))*1/$L32 -> 904087.51 | BL32: =BI32/52/$K32 -> 338.0358 | BM32: =BJ32/52/$K32 -> 386.34663 | BN32: =BK32/52/$K32 -> 434.65745
A34: ALL | B34: Lab technician | J34: =AVERAGE(J28,J22,J16,J10,J4) -> 0.1095 | K34: =AVERAGE(K28,K22,K16,K10,K4) -> 37.95 | L34: =AVERAGE(L28,L22,L16,L10,L4) -> 1 | M34: =AVERAGE(M28,M22,M16,M10,M4) -> 0.1 | N34: =AVERAGE(N28,N22,N16,N10,N4) -> 0.035 | O34: =AVERAGE(O28,O22,O16,O10,O4) -> 0 | P34: =AVERAGE(P28,P22,P16,P10,P4) -> 0 | Q34: =AVERAGE(Q28,Q22,Q16,Q10,Q4) -> 0.046 | ... U34: =AVERAGE(U28,U22,U16,U10,U4) -> 0.015 | V34: =MIN(V28,V22,V16,V10,V4) -> 48552 | W34: =AVERAGE(W28,W22,W16,W10,W4) -> 78368.712 | X34: =MAX(X28,X22,X16,X10,X4) -> 110314 | Y34: =MIN(Y28,Y22,Y16,Y10,Y4) -> 117643.06 | Z34: =AVERAGE(Z28,Z22,Z16,Z10,Z4) -> 192514.23 | AA34: =MAX(AA28,AA22,AA16,AA10,AA4) -> 281453.44 | AB34: =MIN(AB28,AB22,AB16,AB10,AB4) -> 62.410112 | AC34: =AVERAGE(AC28,AC22,AC16,AC10,AC4) -> 97.572625 | AD34: =MAX(AD28,AD22,AD16,AD10,AD4) -> 142.43595 | AE34: =MIN(AE28,AE22,AE16,AE10,AE4) -> 48559.283 | AF34: =AVERAGE(AF28,AF22,AF16,AF10,AF4) -> 78380.467 | AG34: =MAX(AG28,AG22,AG16,AG10,AG4) -> 110330.55 | AH34: =MIN(AH28,AH22,AH16,AH10,AH4) -> 117660.43 | AI34: =AVERAGE(AI28,AI22,AI16,AI10,AI4) -> 192543.06 | AJ34: =MAX(AJ28,AJ22,AJ16,AJ10,AJ4) -> 281495.66 | AK34: =MIN(AK28,AK22,AK16,AK10,AK4) -> 62.419328 | AL34: =AVERAGE(AL28,AL22,AL16,AL10,AL4) -> 97.587232 | AM34: =MAX(AM28,AM22,AM16,AM10,AM4) -> 142.45732 | AN34: =MIN(AN28,AN22,AN16,AN10,AN4) -> 48566.566 | AO34: =AVERAGE(AO28,AO22,AO16,AO10,AO4) -> 78392.223 | AP34: =MAX(AP28,AP22,AP16,AP10,AP4) -> 110347.09 | AQ34: =MIN(AQ28,AQ22,AQ16,AQ10,AQ4) -> 117677.81 | AR34: =AVERAGE(AR28,AR22,AR16,AR10,AR4) -> 192571.88 | AS34: =MAX(AS28,AS22,AS16,AS10,AS4) -> 281537.88 | AT34: =MIN(AT28,AT22,AT16,AT10,AT4) -> 62.428544 | AU34: =AVERAGE(AU28,AU22,AU16,AU10,AU4) -> 97.601839 | AV34: =MAX(AV28,AV22,AV16,AV10,AV4) -> 142.47868 | AW34: =MIN(AW28,AW22,AW16,AW10,AW4) -> 48573.848 | AX34: =AVERAGE(AX28,AX22,AX16,AX10,AX4) -> 78403.978 | AY34: =MAX(AY28,AY22,AY16,AY10,AY4) -> 110363.64 | AZ34: =MIN(AZ28,AZ22,AZ16,AZ10,AZ4) -> 117695.18 | BA34: =AVERAGE(BA28,BA22,BA16,BA10,BA4) -> 192600.7 | BB34: =MAX(BB28,BB22,BB16,BB10,BB4) -> 281580.1 | BC34: =MIN(BC28,BC22,BC16,BC10,BC4) -> 62.437761 | BD34: =AVERAGE(BD28,BD22,BD16,BD10,BD4) -> 97.616446 | BE34: =MAX(BE28,BE22,BE16,BE10,BE4) -> 142.50005 | BF34: =MIN(BF28,BF22,BF16,BF10,BF4) -> 48581.131 | BG34: =AVERAGE(BG28,BG22,BG16,BG10,BG4) -> 78415.733 | BH34: =MAX(BH28,BH22,BH16,BH10,BH4) -> 110380.19 | BI34: =MIN(BI28,BI22,BI16,BI10,BI4) -> 117712.55 | BJ34: =AVERAGE(BJ28,BJ22,BJ16,BJ10,BJ4) -> 192629.52 | BK34: =MAX(BK28,BK22,BK16,BK10,BK4) -> 281622.31 | BL34: =MIN(BL28,BL22,BL16,BL10,BL4) -> 62.446977 | BM34: =AVERAGE(BM28,BM22,BM16,BM10,BM4) -> 97.631053 | BN34: =MAX(BN28,BN22,BN16,BN10,BN4) -> 142.52141
A35: ALL | B35: Medical scientist | J35: =AVERAGE(J29,J23,J17,J11,J5) -> 0.1095 | K35: =AVERAGE(K29,K23,K17,K11,K5) -> 37.55 | L35: =AVERAGE(L29,L23,L17,L11,L5) -> 1 | M35: =AVERAGE(M29,M23,M17,M11,M5) -> 0.1 | N35: =AVERAGE(N29,N23,N17,N11,N5) -> 0.035 | O35: =AVERAGE(O29,O23,O17,O11,O5) -> 0 | P35: =AVERAGE(P29,P23,P17,P11,P5) -> 0 | Q35: =AVERAGE(Q29,Q23,Q17,Q11,Q5) -> 0.046 | ... U35: =AVERAGE(U29,U23,U17,U11,U5) -> 0.015 | V35: =MIN(V29,V23,V17,V11,V5) -> 61204 | W35: =AVERAGE(W29,W23,W17,W11,W5) -> 104472.12 | X35: =MAX(X29,X23,X17,X11,X5) -> 142552.8 | Y35: =MIN(Y29,Y23,Y17,Y11,Y5) -> 157537.92 | Z35: =AVERAGE(Z29,Z23,Z17,Z11,Z5) -> 260971.18 | AA35: =MAX(AA29,AA23,AA17,AA11,AA5) -> 366928.17 | AB35: =MIN(AB29,AB23,AB17,AB11,AB5) -> 79.725668 | AC35: =AVERAGE(AC29,AC23,AC17,AC11,AC5) -> 133.63019 | AD35: =MAX(AD29,AD23,AD17,AD11,AD5) -> 185.69239 | AE35: =MIN(AE29,AE23,AE17,AE11,AE5) -> 61213.181 | AF35: =AVERAGE(AF29,AF23,AF17,AF11,AF5) -> 104487.79 | AG35: =MAX(AG29,AG23,AG17,AG11,AG5) -> 142574.18 | AH35: =MIN(AH29,AH23,AH17,AH11,AH5) -> 157561.55 | AI35: =AVERAGE(AI29,AI23,AI17,AI11,AI5) -> 261010.27 | AJ35: =MAX(AJ29,AJ23,AJ17,AJ11,AJ5) -> 366983.21 | AK35: =MIN(AK29,AK23,AK17,AK11,AK5) -> 79.737626 | AL35: =AVERAGE(AL29,AL23,AL17,AL11,AL5) -> 133.6502 | AM35: =MAX(AM29,AM23,AM17,AM11,AM5) -> 185.72025 | AN35: =MIN(AN29,AN23,AN17,AN11,AN5) -> 61222.361 | AO35: =AVERAGE(AO29,AO23,AO17,AO11,AO5) -> 104503.46 | AP35: =MAX(AP29,AP23,AP17,AP11,AP5) -> 142595.57 | AQ35: =MIN(AQ29,AQ23,AQ17,AQ11,AQ5) -> 157585.18 | AR35: =AVERAGE(AR29,AR23,AR17,AR11,AR5) -> 261049.36 | AS35: =MAX(AS29,AS23,AS17,AS11,AS5) -> 367038.24 | AT35: =MIN(AT29,AT23,AT17,AT11,AT5) -> 79.749585 | AU35: =AVERAGE(AU29,AU23,AU17,AU11,AU5) -> 133.67022 | AV35: =MAX(AV29,AV23,AV17,AV11,AV5) -> 185.7481 | AW35: =MIN(AW29,AW23,AW17,AW11,AW5) -> 61231.542 | AX35: =AVERAGE(AX29,AX23,AX17,AX11,AX5) -> 104519.13 | AY35: =MAX(AY29,AY23,AY17,AY11,AY5) -> 142616.95 | AZ35: =MIN(AZ29,AZ23,AZ17,AZ11,AZ5) -> 157608.81 | BA35: =AVERAGE(BA29,BA23,BA17,BA11,BA5) -> 261088.45 | BB35: =MAX(BB29,BB23,BB17,BB11,BB5) -> 367093.28 | BC35: =MIN(BC29,BC23,BC17,BC11,BC5) -> 79.761544 | BD35: =AVERAGE(BD29,BD23,BD17,BD11,BD5) -> 133.69024 | BE35: =MAX(BE29,BE23,BE17,BE11,BE5) -> 185.77595 | BF35: =MIN(BF29,BF23,BF17,BF11,BF5) -> 61240.722 | BG35: =AVERAGE(BG29,BG23,BG17,BG11,BG5) -> 104534.8 | BH35: =MAX(BH29,BH23,BH17,BH11,BH5) -> 142638.33 | BI35: =MIN(BI29,BI23,BI17,BI11,BI5) -> 157632.44 | BJ35: =AVERAGE(BJ29,BJ23,BJ17,BJ11,BJ5) -> 261127.54 | BK35: =MAX(BK29,BK23,BK17,BK11,BK5) -> 367148.32 | BL35: =MIN(BL29,BL23,BL17,BL11,BL5) -> 79.773503 | BM35: =AVERAGE(BM29,BM23,BM17,BM11,BM5) -> 133.71025 | BN35: =MAX(BN29,BN23,BN17,BN11,BN5) -> 185.80381
A36: ALL | B36: Admin staff | J36: =AVERAGE(J30,J24,J18,J12,J6) -> 0.1095 | K36: =AVERAGE(K30,K24,K18,K12,K6) -> 37.95 | L36: =AVERAGE(L30,L24,L18,L12,L6) -> 1 | M36: =AVERAGE(M30,M24,M18,M12,M6) -> 0.1 | N36: =AVERAGE(N30,N24,N18,N12,N6) -> 0.035 | O36: =AVERAGE(O30,O24,O18,O12,O6) -> 0 | P36: =AVERAGE(P30,P24,P18,P12,P6) -> 0 | Q36: =AVERAGE(Q30,Q24,Q18,Q12,Q6) -> 0.046 | ... U36: =AVERAGE(U30,U24,U18,U12,U6) -> 0.015 | V36: =MIN(V30,V24,V18,V12,V6) -> 47704 | W36: =AVERAGE(W30,W24,W18,W12,W6) -> 65202.816 | X36: =MAX(X30,X24,X18,X12,X6) -> 91460 | Y36: =MIN(Y30,Y24,Y18,Y12,Y6) -> 113848.28 | Z36: =AVERAGE(Z30,Z24,Z18,Z12,Z6) -> 160373.11 | AA36: =MAX(AA30,AA24,AA18,AA12,AA6) -> 233349.64 | AB36: =MIN(AB30,AB24,AB18,AB12,AB6) -> 54.73475 | AC36: =AVERAGE(AC30,AC24,AC18,AC12,AC6) -> 81.422265 | AD36: =MAX(AD30,AD24,AD18,AD12,AD6) -> 118.09192 | AE36: =MIN(AE30,AE24,AE18,AE12,AE6) -> 47711.156 | AF36: =AVERAGE(AF30,AF24,AF18,AF12,AF6) -> 65212.596 | AG36: =MAX(AG30,AG24,AG18,AG12,AG6) -> 91473.719 | AH36: =MIN(AH30,AH24,AH18,AH12,AH6) -> 113865.36 | AI36: =AVERAGE(AI30,AI24,AI18,AI12,AI6) -> 160397.11 | AJ36: =MAX(AJ30,AJ24,AJ18,AJ12,AJ6) -> 233384.64 | AK36: =MIN(AK30,AK24,AK18,AK12,AK6) -> 54.74296 | AL36: =AVERAGE(AL30,AL24,AL18,AL12,AL6) -> 81.434449 | AM36: =MAX(AM30,AM24,AM18,AM12,AM6) -> 118.10964 | AN36: =MIN(AN30,AN24,AN18,AN12,AN6) -> 47718.311 | AO36: =AVERAGE(AO30,AO24,AO18,AO12,AO6) -> 65222.377 | AP36: =MAX(AP30,AP24,AP18,AP12,AP6) -> 91487.438 | AQ36: =MIN(AQ30,AQ24,AQ18,AQ12,AQ6) -> 113882.43 | AR36: =AVERAGE(AR30,AR24,AR18,AR12,AR6) -> 160421.11 | AS36: =MAX(AS30,AS24,AS18,AS12,AS6) -> 233419.64 | AT36: =MIN(AT30,AT24,AT18,AT12,AT6) -> 54.751171 | AU36: =AVERAGE(AU30,AU24,AU18,AU12,AU6) -> 81.446634 | AV36: =MAX(AV30,AV24,AV18,AV12,AV6) -> 118.12735 | AW36: =MIN(AW30,AW24,AW18,AW12,AW6) -> 47725.467 | AX36: =AVERAGE(AX30,AX24,AX18,AX12,AX6) -> 65232.157 | AY36: =MAX(AY30,AY24,AY18,AY12,AY6) -> 91501.157 | AZ36: =MIN(AZ30,AZ24,AZ18,AZ12,AZ6) -> 113899.51 | BA36: =AVERAGE(BA30,BA24,BA18,BA12,BA6) -> 160445.11 | BB36: =MAX(BB30,BB24,BB18,BB12,BB6) -> 233454.64 | BC36: =MIN(BC30,BC24,BC18,BC12,BC6) -> 54.759381 | BD36: =AVERAGE(BD30,BD24,BD18,BD12,BD6) -> 81.458818 | BE36: =MAX(BE30,BE24,BE18,BE12,BE6) -> 118.14506 | BF36: =MIN(BF30,BF24,BF18,BF12,BF6) -> 47732.622 | BG36: =AVERAGE(BG30,BG24,BG18,BG12,BG6) -> 65241.938 | BH36: =MAX(BH30,BH24,BH18,BH12,BH6) -> 91514.876 | BI36: =MIN(BI30,BI24,BI18,BI12,BI6) -> 113916.59 | BJ36: =AVERAGE(BJ30,BJ24,BJ18,BJ12,BJ6) -> 160469.11 | BK36: =MAX(BK30,BK24,BK18,BK12,BK6) -> 233489.65 | BL36: =MIN(BL30,BL24,BL18,BL12,BL6) -> 54.767591 | BM36: =AVERAGE(BM30,BM24,BM18,BM12,BM6) -> 81.471002 | BN36: =MAX(BN30,BN24,BN18,BN12,BN6) -> 118.16278
A37: ALL | B37: Bioinformatics staff | J37: =AVERAGE(J31,J25,J19,J13,J7) -> 0.1095 | K37: =AVERAGE(K31,K25,K19,K13,K7) -> 37.95 | L37: =AVERAGE(L31,L25,L19,L13,L7) -> 1 | M37: =AVERAGE(M31,M25,M19,M13,M7) -> 0.1 | N37: =AVERAGE(N31,N25,N19,N13,N7) -> 0.035 | O37: =AVERAGE(O31,O25,O19,O13,O7) -> 0 | P37: =AVERAGE(P31,P25,P19,P13,P7) -> 0 | Q37: =AVERAGE(Q31,Q25,Q19,Q13,Q7) -> 0.046 | ... U37: =AVERAGE(U31,U25,U19,U13,U7) -> 0.015 | V37: =MIN(V31,V25,V19,V13,V7) -> 66106 | W37: =AVERAGE(W31,W25,W19,W13,W7) -> 94993.5 | X37: =MAX(X31,X25,X19,X13,X7) -> 139576 | Y37: =MIN(Y31,Y25,Y19,Y13,Y7) -> 156865.01 | Z37: =AVERAGE(Z31,Z25,Z19,Z13,Z7) -> 236283.22 | AA37: =MAX(AA31,AA25,AA19,AA13,AA7) -> 334773.81 | AB37: =MIN(AB31,AB25,AB19,AB13,AB7) -> 80.443596 | AC37: =AVERAGE(AC31,AC25,AC19,AC13,AC7) -> 119.92556 | AD37: =MAX(AD31,AD25,AD19,AD13,AD7) -> 177.59884 | AE37: =MIN(AE31,AE25,AE19,AE13,AE7) -> 66115.916 | AF37: =AVERAGE(AF31,AF25,AF19,AF13,AF7) -> 95007.749 | AG37: =MAX(AG31,AG25,AG19,AG13,AG7) -> 139596.94 | AH37: =MIN(AH31,AH25,AH19,AH13,AH7) -> 156888.54 | AI37: =AVERAGE(AI31,AI25,AI19,AI13,AI7) -> 236318.61 | AJ37: =MAX(AJ31,AJ25,AJ19,AJ13,AJ7) -> 334823.75 | AK37: =MIN(AK31,AK25,AK19,AK13,AK7) -> 80.455662 | AL37: =AVERAGE(AL31,AL25,AL19,AL13,AL7) -> 119.94352 | AM37: =MAX(AM31,AM25,AM19,AM13,AM7) -> 177.62533 | AN37: =MIN(AN31,AN25,AN19,AN13,AN7) -> 66125.832 | AO37: =AVERAGE(AO31,AO25,AO19,AO13,AO7) -> 95021.998 | AP37: =MAX(AP31,AP25,AP19,AP13,AP7) -> 139617.87 | AQ37: =MIN(AQ31,AQ25,AQ19,AQ13,AQ7) -> 156912.07 | AR37: =AVERAGE(AR31,AR25,AR19,AR13,AR7) -> 236353.99 | AS37: =MAX(AS31,AS25,AS19,AS13,AS7) -> 334873.7 | AT37: =MIN(AT31,AT25,AT19,AT13,AT7) -> 80.467729 | AU37: =AVERAGE(AU31,AU25,AU19,AU13,AU7) -> 119.96148 | AV37: =MAX(AV31,AV25,AV19,AV13,AV7) -> 177.65183 | AW37: =MIN(AW31,AW25,AW19,AW13,AW7) -> 66135.748 | AX37: =AVERAGE(AX31,AX25,AX19,AX13,AX7) -> 95036.247 | AY37: =MAX(AY31,AY25,AY19,AY13,AY7) -> 139638.81 | AZ37: =MIN(AZ31,AZ25,AZ19,AZ13,AZ7) -> 156935.6 | BA37: =AVERAGE(BA31,BA25,BA19,BA13,BA7) -> 236389.38 | BB37: =MAX(BB31,BB25,BB19,BB13,BB7) -> 334923.64 | BC37: =MIN(BC31,BC25,BC19,BC13,BC7) -> 80.479795 | BD37: =AVERAGE(BD31,BD25,BD19,BD13,BD7) -> 119.97944 | BE37: =MAX(BE31,BE25,BE19,BE13,BE7) -> 177.67832 | BF37: =MIN(BF31,BF25,BF19,BF13,BF7) -> 66145.664 | BG37: =AVERAGE(BG31,BG25,BG19,BG13,BG7) -> 95050.496 | BH37: =MAX(BH31,BH25,BH19,BH13,BH7) -> 139659.75 | BI37: =MIN(BI31,BI25,BI19,BI13,BI7) -> 156959.13 | BJ37: =AVERAGE(BJ31,BJ25,BJ19,BJ13,BJ7) -> 236424.77 | BK37: =MAX(BK31,BK25,BK19,BK13,BK7) -> 334973.58 | BL37: =MIN(BL31,BL25,BL19,BL13,BL7) -> 80.491862 | BM37: =AVERAGE(BM31,BM25,BM19,BM13,BM7) -> 119.9974 | BN37: =MAX(BN31,BN25,BN19,BN13,BN7) -> 177.70482
A38: ALL | B38: Pathologists | J38: =AVERAGE(J32,J26,J20,J14,J8) -> 0.1095 | K38: =AVERAGE(K32,K26,K20,K14,K8) -> 38.8 | L38: =AVERAGE(L32,L26,L20,L14,L8) -> 1 | M38: =AVERAGE(M32,M26,M20,M14,M8) -> 0 | N38: =AVERAGE(N32,N26,N20,N14,N8) -> 0.035 | O38: =AVERAGE(O32,O26,O20,O14,O8) -> 0.04 | P38: =AVERAGE(P32,P26,P20,P14,P8) -> 0.2548 | Q38: =AVERAGE(Q32,Q26,Q20,Q14,Q8) -> 0.046 | ... U38: =AVERAGE(U32,U26,U20,U14,U8) -> 0.015 | V38: =MIN(V32,V26,V20,V14,V8) -> 179078 | W38: =AVERAGE(W32,W26,W20,W14,W8) -> 266292.28 | X38: =MAX(X32,X26,X20,X14,X8) -> 386515 | Y38: =MIN(Y32,Y26,Y20,Y14,Y8) -> 548010.7 | Z38: =AVERAGE(Z32,Z26,Z20,Z14,Z8) -> 732328.94 | AA38: =MAX(AA32,AA26,AA20,AA14,AA8) -> 923660.79 | AB38: =MIN(AB32,AB26,AB20,AB14,AB8) -> 263.46668 | AC38: =AVERAGE(AC32,AC26,AC20,AC14,AC8) -> 363.32101 | AD38: =MAX(AD32,AD26,AD20,AD14,AD8) -> 467.43967 | AE38: =MIN(AE32,AE26,AE20,AE14,AE8) -> 179104.86 | AF38: =AVERAGE(AF32,AF26,AF20,AF14,AF8) -> 266332.22 | AG38: =MAX(AG32,AG26,AG20,AG14,AG8) -> 386572.98 | AH38: =MIN(AH32,AH26,AH20,AH14,AH8) -> 548087.2 | AI38: =AVERAGE(AI32,AI26,AI20,AI14,AI8) -> 732434.49 | AJ38: =MAX(AJ32,AJ26,AJ20,AJ14,AJ8) -> 923795.44 | AK38: =MIN(AK32,AK26,AK20,AK14,AK8) -> 263.50346 | AL38: =AVERAGE(AL32,AL26,AL20,AL14,AL8) -> 363.37338 | AM38: =MAX(AM32,AM26,AM20,AM14,AM8) -> 467.50781 | AN38: =MIN(AN32,AN26,AN20,AN14,AN8) -> 179131.72 | AO38: =AVERAGE(AO32,AO26,AO20,AO14,AO8) -> 266372.17 | AP38: =MAX(AP32,AP26,AP20,AP14,AP8) -> 386630.95 | AQ38: =MIN(AQ32,AQ26,AQ20,AQ14,AQ8) -> 548163.7 | AR38: =AVERAGE(AR32,AR26,AR20,AR14,AR8) -> 732540.04 | AS38: =MAX(AS32,AS26,AS20,AS14,AS8) -> 923930.09 | AT38: =MIN(AT32,AT26,AT20,AT14,AT8) -> 263.54024 | AU38: =AVERAGE(AU32,AU26,AU20,AU14,AU8) -> 363.42576 | AV38: =MAX(AV32,AV26,AV20,AV14,AV8) -> 467.57596 | AW38: =MIN(AW32,AW26,AW20,AW14,AW8) -> 179158.59 | AX38: =AVERAGE(AX32,AX26,AX20,AX14,AX8) -> 266412.11 | AY38: =MAX(AY32,AY26,AY20,AY14,AY8) -> 386688.93 | AZ38: =MIN(AZ32,AZ26,AZ20,AZ14,AZ8) -> 548240.21 | BA38: =AVERAGE(BA32,BA26,BA20,BA14,BA8) -> 732645.58 | BB38: =MAX(BB32,BB26,BB20,BB14,BB8) -> 924064.74 | BC38: =MIN(BC32,BC26,BC20,BC14,BC8) -> 263.57702 | BD38: =AVERAGE(BD32,BD26,BD20,BD14,BD8) -> 363.47813 | BE38: =MAX(BE32,BE26,BE20,BE14,BE8) -> 467.6441 | BF38: =MIN(BF32,BF26,BF20,BF14,BF8) -> 179185.45 | BG38: =AVERAGE(BG32,BG26,BG20,BG14,BG8) -> 266452.06 | BH38: =MAX(BH32,BH26,BH20,BH14,BH8) -> 386746.91 | BI38: =MIN(BI32,BI26,BI20,BI14,BI8) -> 548316.71 | BJ38: =AVERAGE(BJ32,BJ26,BJ20,BJ14,BJ8) -> 732751.13 | BK38: =MAX(BK32,BK26,BK20,BK14,BK8) -> 924199.39 | BL38: =MIN(BL32,BL26,BL20,BL14,BL8) -> 263.6138 | BM38: =AVERAGE(BM32,BM26,BM20,BM14,BM8) -> 363.5305 | BN38: =MAX(BN32,BN26,BN20,BN14,BN8) -> 467.71224
A40: ALL | B40: Lab technician | J40: =TEXT(J34, "0.0%") & " (" & TEXT(MIN(J28,J22,J16,J10,J4), "0.0%") & " - " & TEXT(MAX(J28,J22,J16,J10,J4), "0.0%") & ")" -> 11.0% (10.5% - 12.8%) | K40: =TEXT(K34, "0.0") & " (" & TEXT(MIN(K28,K22,K16,K10,K4), "0.0") & " - " & TEXT(MAX(K28,K22,K16,K10,K4), "0.0") & ")" -> 38.0 (36.3 - 40.0) | L40: =TEXT(L34, "0.0%") & " (" & TEXT(MIN(L28,L22,L16,L10,L4), "0.0%") & " - " & TEXT(MAX(L28,L22,L16,L10,L4), "0.0%") & ")" -> 100.0% (100.0% - 100.0%) | M40: =TEXT(M34, "0.0%") & " (" & TEXT(MIN(M28,M22,M16,M10,M4), "0.0%") & " - " & TEXT(MAX(M28,M22,M16,M10,M4), "0.0%") & ")" -> 10.0% (10.0% - 10.0%) | N40: =TEXT(N34, "0.0%") & " (" & TEXT(MIN(N28,N22,N16,N10,N4), "0.0%") & " - " & TEXT(MAX(N28,N22,N16,N10,N4), "0.0%") & ")" -> 3.5% (3.5% - 3.5%) | O40: =TEXT(O34, "0.0%") & " (" & TEXT(MIN(O28,O22,O16,O10,O4), "0.0%") & " - " & TEXT(MAX(O28,O22,O16,O10,O4), "0.0%") & ")" -> 0.0% (0.0% - 0.0%) | P40: =TEXT(P34, "0.0%") & " (" & TEXT(MIN(P28,P22,P16,P10,P4), "0.0%") & " - " & TEXT(MAX(P28,P22,P16,P10,P4), "0.0%") & ")" -> 0.0% (0.0% - 0.0%) | Q40: =TEXT(Q34, "0.0%") & " (" & TEXT(MIN(Q28,Q22,Q16,Q10,Q4), "0.0%") & " - " & TEXT(MAX(Q28,Q22,Q16,Q10,Q4), "0.0%") & ")" -> 4.6% (4.6% - 4.6%) | R40: =TEXT(R34, "$0.0") & " (" & TEXT(MIN(R28,R22,R16,R10,R4), "$0.0") & " - " & TEXT(MAX(R28,R22,R16,R10,R4), "$0.0") & ")" -> $365.2 ($0.0 - $1826.0) | S40: =TEXT(S34, "0.0") & " (" & TEXT(MIN(S28,S22,S16,S10,S4), "0.0") & " - " & TEXT(MAX(S28,S22,S16,S10,S4), "0.0") & ")" -> 4.0 (4.0 - 4.0) | T40: =TEXT(T34, "0.0%") & " (" & TEXT(MIN(T28,T22,T16,T10,T4), "0.0%") & " - " & TEXT(MAX(T28,T22,T16,T10,T4), "0.0%") & ")" -> 7.5% (0.0% - 20.0%) | U40: =TEXT(U34, "0.0%") & " (" & TEXT(MIN(U28,U22,U16,U10,U4), "0.0%") & " - " & TEXT(MAX(U28,U22,U16,U10,U4), "0.0%") & ")" -> 1.5% (1.5% - 1.5%) | V40: ="AUD " & TEXT(W34, "0,0") & " (" & TEXT(V34, "0,0") & " - " & TEXT(X34, "0,0") & ")" -> AUD 78,369 (48,552 - 110,314) | Y40: ="AUD " & TEXT(Z34, "0,0") & " (" & TEXT(Y34, "0,0") & " - " & TEXT(AA34, "0,0") & ")" -> AUD 192,514 (117,643 - 281,453) | AB40: ="AUD " & TEXT(AC34, "0,0") & " (" & TEXT(AB34, "0,0") & " - " & TEXT(AD34, "0,0") & ")" -> AUD 98 (62 - 142) | AE40: ="AUD " & TEXT(AF34, "0,0") & " (" & TEXT(AE34, "0,0") & " - " & TEXT(AG34, "0,0") & ")" -> AUD 78,380 (48,559 - 110,331) | AH40: ="AUD " & TEXT(AI34, "0,0") & " (" & TEXT(AH34, "0,0") & " - " & TEXT(AJ34, "0,0") & ")" -> AUD 192,543 (117,660 - 281,496) | AK40: ="AUD " & TEXT(AL34, "0,0") & " (" & TEXT(AK34, "0,0") & " - " & TEXT(AM34, "0,0") & ")" -> AUD 98 (62 - 142) | AN40: AUD 78,369 (48,552 - 110,314) | AQ40: ="AUD " & TEXT(AR34, "0,0") & " (" & TEXT(AQ34, "0,0") & " - " & TEXT(AS34, "0,0") & ")" -> AUD 192,572 (117,678 - 281,538) | AT40: ="AUD " & TEXT(AU34, "0,0") & " (" & TEXT(AT34, "0,0") & " - " & TEXT(AV34, "0,0") & ")" -> AUD 98 (62 - 142) | AW40: AUD 78,369 (48,552 - 110,314) | AZ40: ="AUD " & TEXT(BA34, "0,0") & " (" & TEXT(AZ34, "0,0") & " - " & TEXT(BB34, "0,0") & ")" -> AUD 192,601 (117,695 - 281,580) | BC40: ="AUD " & TEXT(BD34, "0,0") & " (" & TEXT(BC34, "0,0") & " - " & TEXT(BE34, "0,0") & ")" -> AUD 98 (62 - 143) | BF40: AUD 78,369 (48,552 - 110,314) | BI40: ="AUD " & TEXT(BJ34, "0,0") & " (" & TEXT(BI34, "0,0") & " - " & TEXT(BK34, "0,0") & ")" -> AUD 192,630 (117,713 - 281,622) | BL40: ="AUD " & TEXT(BM34, "0,0") & " (" & TEXT(BL34, "0,0") & " - " & TEXT(BN34, "0,0") & ")" -> AUD 98 (62 - 143)
A41: ALL | B41: Medical scientist | J41: =TEXT(J35, "0.0%") & " (" & TEXT(MIN(J29,J23,J17,J11,J5), "0.0%") & " - " & TEXT(MAX(J29,J23,J17,J11,J5), "0.0%") & ")" -> 11.0% (10.5% - 12.8%) | K41: =TEXT(K35, "0.0") & " (" & TEXT(MIN(K29,K23,K17,K11,K5), "0.0") & " - " & TEXT(MAX(K29,K23,K17,K11,K5), "0.0") & ")" -> 37.6 (36.3 - 38.0) | L41: =TEXT(L35, "0.0%") & " (" & TEXT(MIN(L29,L23,L17,L11,L5), "0.0%") & " - " & TEXT(MAX(L29,L23,L17,L11,L5), "0.0%") & ")" -> 100.0% (100.0% - 100.0%) | M41: =TEXT(M35, "0.0%") & " (" & TEXT(MIN(M29,M23,M17,M11,M5), "0.0%") & " - " & TEXT(MAX(M29,M23,M17,M11,M5), "0.0%") & ")" -> 10.0% (10.0% - 10.0%) | N41: =TEXT(N35, "0.0%") & " (" & TEXT(MIN(N29,N23,N17,N11,N5), "0.0%") & " - " & TEXT(MAX(N29,N23,N17,N11,N5), "0.0%") & ")" -> 3.5% (3.5% - 3.5%) | O41: =TEXT(O35, "0.0%") & " (" & TEXT(MIN(O29,O23,O17,O11,O5), "0.0%") & " - " & TEXT(MAX(O29,O23,O17,O11,O5), "0.0%") & ")" -> 0.0% (0.0% - 0.0%) | P41: =TEXT(P35, "0.0%") & " (" & TEXT(MIN(P29,P23,P17,P11,P5), "0.0%") & " - " & TEXT(MAX(P29,P23,P17,P11,P5), "0.0%") & ")" -> 0.0% (0.0% - 0.0%) | Q41: =TEXT(Q35, "0.0%") & " (" & TEXT(MIN(Q29,Q23,Q17,Q11,Q5), "0.0%") & " - " & TEXT(MAX(Q29,Q23,Q17,Q11,Q5), "0.0%") & ")" -> 4.6% (4.6% - 4.6%) | R41: =TEXT(R35, "$0.0") & " (" & TEXT(MIN(R29,R23,R17,R11,R5), "$0.0") & " - " & TEXT(MAX(R29,R23,R17,R11,R5), "$0.0") & ")" -> $365.2 ($0.0 - $1826.0) | S41: =TEXT(S35, "0.0") & " (" & TEXT(MIN(S29,S23,S17,S11,S5), "0.0") & " - " & TEXT(MAX(S29,S23,S17,S11,S5), "0.0") & ")" -> 4.4 (4.0 - 5.0) | T41: =TEXT(T35, "0.0%") & " (" & TEXT(MIN(T29,T23,T17,T11,T5), "0.0%") & " - " & TEXT(MAX(T29,T23,T17,T11,T5), "0.0%") & ")" -> 11.0% (0.0% - 20.0%) | U41: =TEXT(U35, "0.0%") & " (" & TEXT(MIN(U29,U23,U17,U11,U5), "0.0%") & " - " & TEXT(MAX(U29,U23,U17,U11,U5), "0.0%") & ")" -> 1.5% (1.5% - 1.5%) | V41: ="AUD " & TEXT(W35, "0,0") & " (" & TEXT(V35, "0,0") & " - " & TEXT(X35, "0,0") & ")" -> AUD 104,472 (61,204 - 142,553) | Y41: ="AUD " & TEXT(Z35, "0,0") & " (" & TEXT(Y35, "0,0") & " - " & TEXT(AA35, "0,0") & ")" -> AUD 260,971 (157,538 - 366,928) | AB41: ="AUD " & TEXT(AC35, "0,0") & " (" & TEXT(AB35, "0,0") & " - " & TEXT(AD35, "0,0") & ")" -> AUD 134 (80 - 186) | AE41: ="AUD " & TEXT(AF35, "0,0") & " (" & TEXT(AE35, "0,0") & " - " & TEXT(AG35, "0,0") & ")" -> AUD 104,488 (61,213 - 142,574) | AH41: ="AUD " & TEXT(AI35, "0,0") & " (" & TEXT(AH35, "0,0") & " - " & TEXT(AJ35, "0,0") & ")" -> AUD 261,010 (157,562 - 366,983) | AK41: ="AUD " & TEXT(AL35, "0,0") & " (" & TEXT(AK35, "0,0") & " - " & TEXT(AM35, "0,0") & ")" -> AUD 134 (80 - 186) | AN41: AUD 104,472 (61,204 - 142,553) | AQ41: ="AUD " & TEXT(AR35, "0,0") & " (" & TEXT(AQ35, "0,0") & " - " & TEXT(AS35, "0,0") & ")" -> AUD 261,049 (157,585 - 367,038) | AT41: ="AUD " & TEXT(AU35, "0,0") & " (" & TEXT(AT35, "0,0") & " - " & TEXT(AV35, "0,0") & ")" -> AUD 134 (80 - 186) | AW41: AUD 104,472 (61,204 - 142,553) | AZ41: ="AUD " & TEXT(BA35, "0,0") & " (" & TEXT(AZ35, "0,0") & " - " & TEXT(BB35, "0,0") & ")" -> AUD 261,088 (157,609 - 367,093) | BC41: ="AUD " & TEXT(BD35, "0,0") & " (" & TEXT(BC35, "0,0") & " - " & TEXT(BE35, "0,0") & ")" -> AUD 134 (80 - 186) | BF41: AUD 104,472 (61,204 - 142,553) | BI41: ="AUD " & TEXT(BJ35, "0,0") & " (" & TEXT(BI35, "0,0") & " - " & TEXT(BK35, "0,0") & ")" -> AUD 261,128 (157,632 - 367,148) | BL41: ="AUD " & TEXT(BM35, "0,0") & " (" & TEXT(BL35, "0,0") & " - " & TEXT(BN35, "0,0") & ")" -> AUD 134 (80 - 186)
A42: ALL | B42: Admin staff | J42: =TEXT(J36, "0.0%") & " (" & TEXT(MIN(J30,J24,J18,J12,J6), "0.0%") & " - " & TEXT(MAX(J30,J24,J18,J12,J6), "0.0%") & ")" -> 11.0% (10.5% - 12.8%) | K42: =TEXT(K36, "0.0") & " (" & TEXT(MIN(K30,K24,K18,K12,K6), "0.0") & " - " & TEXT(MAX(K30,K24,K18,K12,K6), "0.0") & ")" -> 38.0 (36.3 - 40.0) | L42: =TEXT(L36, "0.0%") & " (" & TEXT(MIN(L30,L24,L18,L12,L6), "0.0%") & " - " & TEXT(MAX(L30,L24,L18,L12,L6), "0.0%") & ")" -> 100.0% (100.0% - 100.0%) | M42: =TEXT(M36, "0.0%") & " (" & TEXT(MIN(M30,M24,M18,M12,M6), "0.0%") & " - " & TEXT(MAX(M30,M24,M18,M12,M6), "0.0%") & ")" -> 10.0% (10.0% - 10.0%) | N42: =TEXT(N36, "0.0%") & " (" & TEXT(MIN(N30,N24,N18,N12,N6), "0.0%") & " - " & TEXT(MAX(N30,N24,N18,N12,N6), "0.0%") & ")" -> 3.5% (3.5% - 3.5%) | O42: =TEXT(O36, "0.0%") & " (" & TEXT(MIN(O30,O24,O18,O12,O6), "0.0%") & " - " & TEXT(MAX(O30,O24,O18,O12,O6), "0.0%") & ")" -> 0.0% (0.0% - 0.0%) | P42: =TEXT(P36, "0.0%") & " (" & TEXT(MIN(P30,P24,P18,P12,P6), "0.0%") & " - " & TEXT(MAX(P30,P24,P18,P12,P6), "0.0%") & ")" -> 0.0% (0.0% - 0.0%) | Q42: =TEXT(Q36, "0.0%") & " (" & TEXT(MIN(Q30,Q24,Q18,Q12,Q6), "0.0%") & " - " & TEXT(MAX(Q30,Q24,Q18,Q12,Q6), "0.0%") & ")" -> 4.6% (4.6% - 4.6%) | R42: =TEXT(R36, "$0.0") & " (" & TEXT(MIN(R30,R24,R18,R12,R6), "$0.0") & " - " & TEXT(MAX(R30,R24,R18,R12,R6), "$0.0") & ")" -> $365.2 ($0.0 - $1826.0) | S42: =TEXT(S36, "0.0") & " (" & TEXT(MIN(S30,S24,S18,S12,S6), "0.0") & " - " & TEXT(MAX(S30,S24,S18,S12,S6), "0.0") & ")" -> 4.0 (4.0 - 4.0) | T42: =TEXT(T36, "0.0%") & " (" & TEXT(MIN(T30,T24,T18,T12,T6), "0.0%") & " - " & TEXT(MAX(T30,T24,T18,T12,T6), "0.0%") & ")" -> 7.5% (0.0% - 20.0%) | U42: =TEXT(U36, "0.0%") & " (" & TEXT(MIN(U30,U24,U18,U12,U6), "0.0%") & " - " & TEXT(MAX(U30,U24,U18,U12,U6), "0.0%") & ")" -> 1.5% (1.5% - 1.5%) | V42: ="AUD " & TEXT(W36, "0,0") & " (" & TEXT(V36, "0,0") & " - " & TEXT(X36, "0,0") & ")" -> AUD 65,203 (47,704 - 91,460) | Y42: ="AUD " & TEXT(Z36, "0,0") & " (" & TEXT(Y36, "0,0") & " - " & TEXT(AA36, "0,0") & ")" -> AUD 160,373 (113,848 - 233,350) | AB42: ="AUD " & TEXT(AC36, "0,0") & " (" & TEXT(AB36, "0,0") & " - " & TEXT(AD36, "0,0") & ")" -> AUD 81 (55 - 118) | AE42: ="AUD " & TEXT(AF36, "0,0") & " (" & TEXT(AE36, "0,0") & " - " & TEXT(AG36, "0,0") & ")" -> AUD 65,213 (47,711 - 91,474) | AH42: ="AUD " & TEXT(AI36, "0,0") & " (" & TEXT(AH36, "0,0") & " - " & TEXT(AJ36, "0,0") & ")" -> AUD 160,397 (113,865 - 233,385) | AK42: ="AUD " & TEXT(AL36, "0,0") & " (" & TEXT(AK36, "0,0") & " - " & TEXT(AM36, "0,0") & ")" -> AUD 81 (55 - 118) | AN42: AUD 65,203 (47,704 - 91,460) | AQ42: ="AUD " & TEXT(AR36, "0,0") & " (" & TEXT(AQ36, "0,0") & " - " & TEXT(AS36, "0,0") & ")" -> AUD 160,421 (113,882 - 233,420) | AT42: ="AUD " & TEXT(AU36, "0,0") & " (" & TEXT(AT36, "0,0") & " - " & TEXT(AV36, "0,0") & ")" -> AUD 81 (55 - 118) | AW42: AUD 65,203 (47,704 - 91,460) | AZ42: ="AUD " & TEXT(BA36, "0,0") & " (" & TEXT(AZ36, "0,0") & " - " & TEXT(BB36, "0,0") & ")" -> AUD 160,445 (113,900 - 233,455) | BC42: ="AUD " & TEXT(BD36, "0,0") & " (" & TEXT(BC36, "0,0") & " - " & TEXT(BE36, "0,0") & ")" -> AUD 81 (55 - 118) | BF42: AUD 65,203 (47,704 - 91,460) | BI42: ="AUD " & TEXT(BJ36, "0,0") & " (" & TEXT(BI36, "0,0") & " - " & TEXT(BK36, "0,0") & ")" -> AUD 160,469 (113,917 - 233,490) | BL42: ="AUD " & TEXT(BM36, "0,0") & " (" & TEXT(BL36, "0,0") & " - " & TEXT(BN36, "0,0") & ")" -> AUD 81 (55 - 118)
A43: ALL | B43: Bioinformatics staff | J43: =TEXT(J37, "0.0%") & " (" & TEXT(MIN(J31,J25,J19,J13,J7), "0.0%") & " - " & TEXT(MAX(J31,J25,J19,J13,J7), "0.0%") & ")" -> 11.0% (10.5% - 12.8%) | K43: =TEXT(K37, "0.0") & " (" & TEXT(MIN(K31,K25,K19,K13,K7), "0.0") & " - " & TEXT(MAX(K31,K25,K19,K13,K7), "0.0") & ")" -> 38.0 (36.3 - 40.0) | L43: =TEXT(L37, "0.0%") & " (" & TEXT(MIN(L31,L25,L19,L13,L7), "0.0%") & " - " & TEXT(MAX(L31,L25,L19,L13,L7), "0.0%") & ")" -> 100.0% (100.0% - 100.0%) | M43: =TEXT(M37, "0.0%") & " (" & TEXT(MIN(M31,M25,M19,M13,M7), "0.0%") & " - " & TEXT(MAX(M31,M25,M19,M13,M7), "0.0%") & ")" -> 10.0% (10.0% - 10.0%) | N43: =TEXT(N37, "0.0%") & " (" & TEXT(MIN(N31,N25,N19,N13,N7), "0.0%") & " - " & TEXT(MAX(N31,N25,N19,N13,N7), "0.0%") & ")" -> 3.5% (3.5% - 3.5%) | O43: =TEXT(O37, "0.0%") & " (" & TEXT(MIN(O31,O25,O19,O13,O7), "0.0%") & " - " & TEXT(MAX(O31,O25,O19,O13,O7), "0.0%") & ")" -> 0.0% (0.0% - 0.0%) | P43: =TEXT(P37, "0.0%") & " (" & TEXT(MIN(P31,P25,P19,P13,P7), "0.0%") & " - " & TEXT(MAX(P31,P25,P19,P13,P7), "0.0%") & ")" -> 0.0% (0.0% - 0.0%) | Q43: =TEXT(Q37, "0.0%") & " (" & TEXT(MIN(Q31,Q25,Q19,Q13,Q7), "0.0%") & " - " & TEXT(MAX(Q31,Q25,Q19,Q13,Q7), "0.0%") & ")" -> 4.6% (4.6% - 4.6%) | R43: =TEXT(R37, "$0.0") & " (" & TEXT(MIN(R31,R25,R19,R13,R7), "$0.0") & " - " & TEXT(MAX(R31,R25,R19,R13,R7), "$0.0") & ")" -> $365.2 ($0.0 - $1826.0) | S43: =TEXT(S37, "0.0") & " (" & TEXT(MIN(S31,S25,S19,S13,S7), "0.0") & " - " & TEXT(MAX(S31,S25,S19,S13,S7), "0.0") & ")" -> 4.0 (4.0 - 4.0) | T43: =TEXT(T37, "0.0%") & " (" & TEXT(MIN(T31,T25,T19,T13,T7), "0.0%") & " - " & TEXT(MAX(T31,T25,T19,T13,T7), "0.0%") & ")" -> 11.0% (0.0% - 20.0%) | U43: =TEXT(U37, "0.0%") & " (" & TEXT(MIN(U31,U25,U19,U13,U7), "0.0%") & " - " & TEXT(MAX(U31,U25,U19,U13,U7), "0.0%") & ")" -> 1.5% (1.5% - 1.5%) | V43: ="AUD " & TEXT(W37, "0,0") & " (" & TEXT(V37, "0,0") & " - " & TEXT(X37, "0,0") & ")" -> AUD 94,994 (66,106 - 139,576) | Y43: ="AUD " & TEXT(Z37, "0,0") & " (" & TEXT(Y37, "0,0") & " - " & TEXT(AA37, "0,0") & ")" -> AUD 236,283 (156,865 - 334,774) | AB43: ="AUD " & TEXT(AC37, "0,0") & " (" & TEXT(AB37, "0,0") & " - " & TEXT(AD37, "0,0") & ")" -> AUD 120 (80 - 178) | AE43: ="AUD " & TEXT(AF37, "0,0") & " (" & TEXT(AE37, "0,0") & " - " & TEXT(AG37, "0,0") & ")" -> AUD 95,008 (66,116 - 139,597) | AH43: ="AUD " & TEXT(AI37, "0,0") & " (" & TEXT(AH37, "0,0") & " - " & TEXT(AJ37, "0,0") & ")" -> AUD 236,319 (156,889 - 334,824) | AK43: ="AUD " & TEXT(AL37, "0,0") & " (" & TEXT(AK37, "0,0") & " - " & TEXT(AM37, "0,0") & ")" -> AUD 120 (80 - 178) | AN43: AUD 94,994 (66,106 - 139,576) | AQ43: ="AUD " & TEXT(AR37, "0,0") & " (" & TEXT(AQ37, "0,0") & " - " & TEXT(AS37, "0,0") & ")" -> AUD 236,354 (156,912 - 334,874) | AT43: ="AUD " & TEXT(AU37, "0,0") & " (" & TEXT(AT37, "0,0") & " - " & TEXT(AV37, "0,0") & ")" -> AUD 120 (80 - 178) | AW43: AUD 94,994 (66,106 - 139,576) | AZ43: ="AUD " & TEXT(BA37, "0,0") & " (" & TEXT(AZ37, "0,0") & " - " & TEXT(BB37, "0,0") & ")" -> AUD 236,389 (156,936 - 334,924) | BC43: ="AUD " & TEXT(BD37, "0,0") & " (" & TEXT(BC37, "0,0") & " - " & TEXT(BE37, "0,0") & ")" -> AUD 120 (80 - 178) | BF43: AUD 94,994 (66,106 - 139,576) | BI43: ="AUD " & TEXT(BJ37, "0,0") & " (" & TEXT(BI37, "0,0") & " - " & TEXT(BK37, "0,0") & ")" -> AUD 236,425 (156,959 - 334,974) | BL43: ="AUD " & TEXT(BM37, "0,0") & " (" & TEXT(BL37, "0,0") & " - " & TEXT(BN37, "0,0") & ")" -> AUD 120 (80 - 178)
A44: ALL | B44: Pathologists | J44: =TEXT(J38, "0.0%") & " (" & TEXT(MIN(J32,J26,J20,J14,J8), "0.0%") & " - " & TEXT(MAX(J32,J26,J20,J14,J8), "0.0%") & ")" -> 11.0% (10.5% - 12.8%) | K44: =TEXT(K38, "0.0") & " (" & TEXT(MIN(K32,K26,K20,K14,K8), "0.0") & " - " & TEXT(MAX(K32,K26,K20,K14,K8), "0.0") & ")" -> 38.8 (38.0 - 40.0) | L44: =TEXT(L38, "0.0%") & " (" & TEXT(MIN(L32,L26,L20,L14,L8), "0.0%") & " - " & TEXT(MAX(L32,L26,L20,L14,L8), "0.0%") & ")" -> 100.0% (100.0% - 100.0%) | M44: =TEXT(M38, "0.0%") & " (" & TEXT(MIN(M32,M26,M20,M14,M8), "0.0%") & " - " & TEXT(MAX(M32,M26,M20,M14,M8), "0.0%") & ")" -> 0.0% (0.0% - 0.0%) | N44: =TEXT(N38, "0.0%") & " (" & TEXT(MIN(N32,N26,N20,N14,N8), "0.0%") & " - " & TEXT(MAX(N32,N26,N20,N14,N8), "0.0%") & ")" -> 3.5% (3.5% - 3.5%) | O44: =TEXT(O38, "0.0%") & " (" & TEXT(MIN(O32,O26,O20,O14,O8), "0.0%") & " - " & TEXT(MAX(O32,O26,O20,O14,O8), "0.0%") & ")" -> 4.0% (0.0% - 20.0%) | P44: =TEXT(P38, "0.0%") & " (" & TEXT(MIN(P32,P26,P20,P14,P8), "0.0%") & " - " & TEXT(MAX(P32,P26,P20,P14,P8), "0.0%") & ")" -> 25.5% (0.0% - 60.0%) | Q44: =TEXT(Q38, "0.0%") & " (" & TEXT(MIN(Q32,Q26,Q20,Q14,Q8), "0.0%") & " - " & TEXT(MAX(Q32,Q26,Q20,Q14,Q8), "0.0%") & ")" -> 4.6% (4.6% - 4.6%) | R44: =TEXT(R38, "$0.0") & " (" & TEXT(MIN(R32,R26,R20,R14,R8), "$0.0") & " - " & TEXT(MAX(R32,R26,R20,R14,R8), "$0.0") & ")" -> $28681.8 ($21500.0 - $38000.0) | S44: =TEXT(S38, "0.0") & " (" & TEXT(MIN(S32,S26,S20,S14,S8), "0.0") & " - " & TEXT(MAX(S32,S26,S20,S14,S8), "0.0") & ")" -> 4.4 (4.0 - 5.0) | T44: =TEXT(T38, "0.0%") & " (" & TEXT(MIN(T32,T26,T20,T14,T8), "0.0%") & " - " & TEXT(MAX(T32,T26,T20,T14,T8), "0.0%") & ")" -> 10.5% (0.0% - 17.5%) | U44: =TEXT(U38, "0.0%") & " (" & TEXT(MIN(U32,U26,U20,U14,U8), "0.0%") & " - " & TEXT(MAX(U32,U26,U20,U14,U8), "0.0%") & ")" -> 1.5% (1.5% - 1.5%) | V44: ="AUD " & TEXT(W38, "0,0") & " (" & TEXT(V38, "0,0") & " - " & TEXT(X38, "0,0") & ")" -> AUD 266,292 (179,078 - 386,515) | Y44: ="AUD " & TEXT(Z38, "0,0") & " (" & TEXT(Y38, "0,0") & " - " & TEXT(AA38, "0,0") & ")" -> AUD 732,329 (548,011 - 923,661) | AB44: ="AUD " & TEXT(AC38, "0,0") & " (" & TEXT(AB38, "0,0") & " - " & TEXT(AD38, "0,0") & ")" -> AUD 363 (263 - 467) | AE44: ="AUD " & TEXT(AF38, "0,0") & " (" & TEXT(AE38, "0,0") & " - " & TEXT(AG38, "0,0") & ")" -> AUD 266,332 (179,105 - 386,573) | AH44: ="AUD " & TEXT(AI38, "0,0") & " (" & TEXT(AH38, "0,0") & " - " & TEXT(AJ38, "0,0") & ")" -> AUD 732,434 (548,087 - 923,795) | AK44: ="AUD " & TEXT(AL38, "0,0") & " (" & TEXT(AK38, "0,0") & " - " & TEXT(AM38, "0,0") & ")" -> AUD 363 (264 - 468) | AN44: AUD 266,292 (179,078 - 386,515) | AQ44: ="AUD " & TEXT(AR38, "0,0") & " (" & TEXT(AQ38, "0,0") & " - " & TEXT(AS38, "0,0") & ")" -> AUD 732,540 (548,164 - 923,930) | AT44: ="AUD " & TEXT(AU38, "0,0") & " (" & TEXT(AT38, "0,0") & " - " & TEXT(AV38, "0,0") & ")" -> AUD 363 (264 - 468) | AW44: AUD 266,292 (179,078 - 386,515) | AZ44: ="AUD " & TEXT(BA38, "0,0") & " (" & TEXT(AZ38, "0,0") & " - " & TEXT(BB38, "0,0") & ")" -> AUD 732,646 (548,240 - 924,065) | BC44: ="AUD " & TEXT(BD38, "0,0") & " (" & TEXT(BC38, "0,0") & " - " & TEXT(BE38, "0,0") & ")" -> AUD 363 (264 - 468) | BF44: AUD 266,292 (179,078 - 386,515) | BI44: ="AUD " & TEXT(BJ38, "0,0") & " (" & TEXT(BI38, "0,0") & " - " & TEXT(BK38, "0,0") & ")" -> AUD 732,751 (548,317 - 924,199) | BL44: ="AUD " & TEXT(BM38, "0,0") & " (" & TEXT(BL38, "0,0") & " - " & TEXT(BN38, "0,0") & ")" -> AUD 364 (264 - 468)
A46: $
A47: VIC | B47: Lab technician | J47: =(J4*$W4) -> 9971.745 | M47: =(M4*$W4) -> 9496.9 | N47: =(N4*$W4) -> 3323.915 | O47: =(O4*$W4) -> 0 | P47: =(P4*$W4) -> 0 | Q47: =(Q4*$W4) -> 4368.574 | R47: =R4 -> 0 | S47: =(S4/52*$W4) -> 7305.3077 | T47: =(T4*$W4) -> 16619.575 | V47: =V4 -> 79624 | W47: =W4 -> 94969 | X47: =X4 -> 110314
A48: VIC | B48: Medical scientist | J48: =(J5*$W5) -> 10697.232 | M48: =(M5*$W5) -> 10187.84 | N48: =(N5*$W5) -> 3565.744 | O48: =(O5*$W5) -> 0 | P48: =(P5*$W5) -> 0 | Q48: =(Q5*$W5) -> 4686.4064 | R48: =R5 -> 0 | S48: =(S5/52*$W5) -> 9796 | T48: =(T5*$W5) -> 17828.72 | V48: =V5 -> 61204 | W48: =W5 -> 101878.4 | X48: =X5 -> 142552.8
A49: VIC | B49: Admin staff | J49: =(J6*$W6) -> 8145.9525 | M49: =(M6*$W6) -> 7758.05 | N49: =(N6*$W6) -> 2715.3175 | O49: =(O6*$W6) -> 0 | P49: =(P6*$W6) -> 0 | Q49: =(Q6*$W6) -> 3568.703 | R49: =R6 -> 0 | S49: =(S6/52*$W6) -> 5967.7308 | T49: =(T6*$W6) -> 13576.587 | V49: =V6 -> 63701 | W49: =W6 -> 77580.5 | X49: =X6 -> 91460
A50: VIC | B50: Bioinformatics staff | J50: =(J7*$W7) -> 10695.405 | M50: =(M7*$W7) -> 10186.1 | N50: =(N7*$W7) -> 3565.135 | O50: =(O7*$W7) -> 0 | P50: =(P7*$W7) -> 0 | Q50: =(Q7*$W7) -> 4685.606 | R50: =R7 -> 0 | S50: =(S7/52*$W7) -> 7835.4615 | T50: =(T7*$W7) -> 17825.675 | V50: =V7 -> 79624 | W50: =W7 -> 101861 | X50: =X7 -> 124098
A51: VIC | B51: Pathologists | J51: =(J8*$W8) -> 31106.03 | M51: =(M8*$W8) -> 0 | N51: =(N8*$W8) -> 10368.677 | O51: =(O8*$W8) -> 0 | P51: =(P8*$W8) -> 0 | Q51: =(Q8*$W8) -> 13627.403 | R51: =R8 -> 29000.16 | S51: =(S8/52*$W8) -> 22788.3 | T51: =(T8*$W8) -> 51843.382 | V51: =V8 -> 249470 | W51: =W8 -> 296247.9 | X51: =X8 -> 343025.8
A53: SA | B53: Lab technician | J53: =(J10*$W10) -> 8155.665 | M53: =(M10*$W10) -> 7767.3 | N53: =(N10*$W10) -> 2718.555 | O53: =(O10*$W10) -> 0 | P53: =(P10*$W10) -> 0 | Q53: =(Q10*$W10) -> 3572.958 | R53: =R10 -> 0 | S53: =(S10/52*$W10) -> 5974.8462 | T53: =(T10*$W10) -> 0 | V53: =V10 -> 54364 | W53: =W10 -> 77673 | X53: =X10 -> 100982
A54: SA | B54: Medical scientist | J54: =(J11*$W11) -> 10944.99 | M54: =(M11*$W11) -> 10423.8 | N54: =(N11*$W11) -> 3648.33 | O54: =(O11*$W11) -> 0 | P54: =(P11*$W11) -> 0 | Q54: =(Q11*$W11) -> 4794.948 | R54: =R11 -> 0 | S54: =(S11/52*$W11) -> 10022.885 | T54: =(T11*$W11) -> 0 | V54: =V11 -> 66386 | W54: =W11 -> 104238 | X54: =X11 -> 142090
A55: SA | B55: Admin staff | J55: =(J12*$W12) -> 6654.27 | M55: =(M12*$W12) -> 6337.4 | N55: =(N12*$W12) -> 2218.09 | O55: =(O12*$W12) -> 0 | P55: =(P12*$W12) -> 0 | Q55: =(Q12*$W12) -> 2915.204 | R55: =R12 -> 0 | S55: =(S12/52*$W12) -> 4874.9231 | T55: =(T12*$W12) -> 0 | V55: =V12 -> 56916 | W55: =W12 -> 63374 | X55: =X12 -> 69832
A56: SA | B56: Bioinformatics staff | J56: =(J13*$W13) -> 9616.6875 | M56: =(M13*$W13) -> 9158.75 | N56: =(N13*$W13) -> 3205.5625 | O56: =(O13*$W13) -> 0 | P56: =(P13*$W13) -> 0 | Q56: =(Q13*$W13) -> 4213.025 | R56: =R13 -> 0 | S56: =(S13/52*$W13) -> 7045.1923 | T56: =(T13*$W13) -> 0 | V56: =V13 -> 66386 | W56: =W13 -> 91587.5 | X56: =X13 -> 116789
A57: SA | B57: Pathologists | J57: =(J14*$W14) -> 26966.153 | M57: =(M14*$W14) -> 0 | N57: =(N14*$W14) -> 8988.7175 | O57: =(O14*$W14) -> 0 | P57: =(P14*$W14) -> 154092.3 | Q57: =(Q14*$W14) -> 11813.743 | R57: =R14 -> 26000 | S57: =(S14/52*$W14) -> 24694.279 | T57: =(T14*$W14) -> 44943.587 | V57: =V14 -> 221622 | W57: =W14 -> 256820.5 | X57: =X14 -> 292019
A59: NSW | B59: Lab technician | J59: =(J16*$W16) -> 8151.9438 | M59: =(M16*$W16) -> 7763.756 | N59: =(N16*$W16) -> 2717.3146 | O59: =(O16*$W16) -> 0 | P59: =(P16*$W16) -> 0 | Q59: =(Q16*$W16) -> 3571.3278 | R59: =R16 -> 0 | S59: =(S16/52*$W16) -> 5972.12 | T59: =(T16*$W16) -> 0 | V59: =V16 -> 60017.88 | W59: =W16 -> 77637.56 | X59: =X16 -> 95257.24
A60: NSW | B60: Medical scientist | J60: =(J17*$W17) -> 10804.466 | M60: =(M17*$W17) -> 10289.968 | N60: =(N17*$W17) -> 3601.4888 | O60: =(O17*$W17) -> 0 | P60: =(P17*$W17) -> 0 | Q60: =(Q17*$W17) -> 4733.3853 | R60: =R17 -> 0 | S60: =(S17/52*$W17) -> 7915.36 | T60: =(T17*$W17) -> 18007.444 | V60: =V17 -> 67224.04 | W60: =W17 -> 102899.68 | X60: =X17 -> 138575.32
... A75: WA | B75: Pathologists | J75: =(J32*$W32) -> 35924.28 | M75: =(M32*$W32) -> 0 | N75: =(N32*$W32) -> 11974.76 | O75: =(O32*$W32) -> 0 | P75: =(P32*$W32) -> 0 | Q75: =(Q32*$W32) -> 15738.256 | R75: =R32 -> 28909 | S75: =(S32/52*$W32) -> 26318.154 | T75: =(T32*$W32) -> 0 | V75: =V32 -> 297757 | W75: =W32 -> 342136 | X75: =X32 -> 386515
A77: ALL | B77: Lab technician | J77: =AVERAGE(J28,J22,J16,J10,J4)*$W4 -> 10399.105 | M77: =AVERAGE(M28,M22,M16,M10,M4)*$W4 -> 9496.9 | N77: =AVERAGE(N28,N22,N16,N10,N4)*$W4 -> 3323.915 | O77: =AVERAGE(O28,O22,O16,O10,O4)*$W4 -> 0 | P77: =AVERAGE(P28,P22,P16,P10,P4)*$W4 -> 0 | Q77: =AVERAGE(Q28,Q22,Q16,Q10,Q4)*$W4 -> 4368.574 | R77: =AVERAGE(R28,R22,R16,R10,R4) -> 365.2 | S77: =AVERAGE(S28,S22,S16,S10,S4)/52*$W4 -> 7305.3077 | T77: =AVERAGE(T28,T22,T16,T10,T4)*$W4 -> 7122.675 | V77: =AVERAGE(V28,V22,V16,V10,V4) -> 60027.376 | W77: =AVERAGE(W28,W22,W16,W10,W4) -> 78368.712 | X77: =AVERAGE(X28,X22,X16,X10,X4) -> 96710.048
A78: ALL | B78: Medical scientist | J78: =AVERAGE(J29,J23,J17,J11,J5)*$W5 -> 11155.685 | M78: =AVERAGE(M29,M23,M17,M11,M5)*$W5 -> 10187.84 | N78: =AVERAGE(N29,N23,N17,N11,N5)*$W5 -> 3565.744 | O78: =AVERAGE(O29,O23,O17,O11,O5)*$W5 -> 0 | P78: =AVERAGE(P29,P23,P17,P11,P5)*$W5 -> 0 | Q78: =AVERAGE(Q29,Q23,Q17,Q11,Q5)*$W5 -> 4686.4064 | R78: =AVERAGE(R29,R23,R17,R11,R5) -> 365.2 | S78: =AVERAGE(S29,S23,S17,S11,S5)/52*$W5 -> 8620.48 | T78: =AVERAGE(T29,T23,T17,T11,T5)*$W5 -> 11206.624 | V78: =AVERAGE(V29,V23,V17,V11,V5) -> 68335.608 | W78: =AVERAGE(W29,W23,W17,W11,W5) -> 104472.12 | X78: =AVERAGE(X29,X23,X17,X11,X5) -> 140608.62
A79: ALL | B79: Admin staff | J79: =AVERAGE(J30,J24,J18,J12,J6)*$W6 -> 8495.0647 | M79: =AVERAGE(M30,M24,M18,M12,M6)*$W6 -> 7758.05 | N79: =AVERAGE(N30,N24,N18,N12,N6)*$W6 -> 2715.3175 | O79: =AVERAGE(O30,O24,O18,O12,O6)*$W6 -> 0 | P79: =AVERAGE(P30,P24,P18,P12,P6)*$W6 -> 0 | Q79: =AVERAGE(Q30,Q24,Q18,Q12,Q6)*$W6 -> 3568.703 | R79: =AVERAGE(R30,R24,R18,R12,R6) -> 365.2 | S79: =AVERAGE(S30,S24,S18,S12,S6)/52*$W6 -> 5967.7308 | T79: =AVERAGE(T30,T24,T18,T12,T6)*$W6 -> 5818.5375 | V79: =AVERAGE(V30,V24,V18,V12,V6) -> 54816.224 | W79: =AVERAGE(W30,W24,W18,W12,W6) -> 65202.816 | X79: =AVERAGE(X30,X24,X18,X12,X6) -> 75589.408
A80: ALL | B80: Bioinformatics staff | J80: =AVERAGE(J31,J25,J19,J13,J7)*$W7 -> 11153.78 | M80: =AVERAGE(M31,M25,M19,M13,M7)*$W7 -> 10186.1 | N80: =AVERAGE(N31,N25,N19,N13,N7)*$W7 -> 3565.135 | O80: =AVERAGE(O31,O25,O19,O13,O7)*$W7 -> 0 | P80: =AVERAGE(P31,P25,P19,P13,P7)*$W7 -> 0 | Q80: =AVERAGE(Q31,Q25,Q19,Q13,Q7)*$W7 -> 4685.606 | R80: =AVERAGE(R31,R25,R19,R13,R7) -> 365.2 | S80: =AVERAGE(S31,S25,S19,S13,S7)/52*$W7 -> 7835.4615 | T80: =AVERAGE(T31,T25,T19,T13,T7)*$W7 -> 11204.71 | V80: =AVERAGE(V31,V25,V19,V13,V7) -> 72209 | W80: =AVERAGE(W31,W25,W19,W13,W7) -> 94993.5 | X80: =AVERAGE(X31,X25,X19,X13,X7) -> 117778
A81: ALL | B81: Pathologists | J81: =AVERAGE(J32,J26,J20,J14,J8)*$W8 -> 32439.145 | M81: =AVERAGE(M32,M26,M20,M14,M8)*$W8 -> 0 | N81: =AVERAGE(N32,N26,N20,N14,N8)*$W8 -> 10368.677 | O81: =AVERAGE(O32,O26,O20,O14,O8)*$W8 -> 11849.916 | P81: =AVERAGE(P32,P26,P20,P14,P8)*$W8 -> 75483.965 | Q81: =AVERAGE(Q32,Q26,Q20,Q14,Q8)*$W8 -> 13627.403 | R81: =AVERAGE(R32,R26,R20,R14,R8) -> 28681.832 | S81: =AVERAGE(S32,S26,S20,S14,S8)/52*$W8 -> 25067.13 | T81: =AVERAGE(T32,T26,T20,T14,T8)*$W8 -> 31106.029 | V81: =AVERAGE(V32,V26,V20,V14,V8) -> 227466.6 | W81: =AVERAGE(W32,W26,W20,W14,W8) -> 266292.28 | X81: =AVERAGE(X32,X26,X20,X14,X8) -> 305117.96
A83: ALL | B83: Lab technician | J83: =TEXT((AVERAGE(J28,J22,J16,J10,J4)*$W4), "$0,0") & " (" & TEXT((MIN(J28,J22,J16,J10,J4)*$W4), "0,0") & " - " & TEXT((MAX(J28,J22,J16,J10,J4)*$W4), "0,0") & ")" -> $10,399 (9,972 - 12,109) | M83: =TEXT((AVERAGE(M28,M22,M16,M10,M4)*$W4), "$0,0") & " (" & TEXT((MIN(M28,M22,M16,M10,M4)*$W4), "0,0") & " - " & TEXT((MAX(M28,M22,M16,M10,M4)*$W4), "0,0") & ")" -> $9,497 (9,497 - 9,497) | N83: =TEXT((AVERAGE(N28,N22,N16,N10,N4)*$W4), "$0,0") & " (" & TEXT((MIN(N28,N22,N16,N10,N4)*$W4), "0,0") & " - " & TEXT((MAX(N28,N22,N16,N10,N4)*$W4), "0,0") & ")" -> $3,324 (3,324 - 3,324) | O83: =TEXT((AVERAGE(O28,O22,O16,O10,O4)*$W4), "$0") & " (" & TEXT((MIN(O28,O22,O16,O10,O4)*$W4), "0") & " - " & TEXT((MAX(O28,O22,O16,O10,O4)*$W4), "0") & ")" -> $0 (0 - 0) | P83: =TEXT((AVERAGE(P28,P22,P16,P10,P4)*$W4), "$0") & " (" & TEXT((MIN(P28,P22,P16,P10,P4)*$W4), "0") & " - " & TEXT((MAX(P28,P22,P16,P10,P4)*$W4), "0") & ")" -> $0 (0 - 0) | Q83: =TEXT((AVERAGE(Q28,Q22,Q16,Q10,Q4)*$W4), "$0,0") & " (" & TEXT((MIN(Q28,Q22,Q16,Q10,Q4)*$W4), "0,0") & " - " & TEXT((MAX(Q28,Q22,Q16,Q10,Q4)*$W4), "0,0") & ")" -> $4,369 (4,369 - 4,369) | R83: =TEXT((AVERAGE(R28,R22,R16,R10,R4)), "$0,0") & " (" & TEXT((MIN(R28,R22,R16,R10,R4)), "0,0") & " - " & TEXT((MAX(R28,R22,R16,R10,R4)), "0,0") & ")" -> $365 (00 - 1,826) | S83: =TEXT((AVERAGE(S28,S22,S16,S10,S4)/52*$W4), "$0,0") & " (" & TEXT((MIN(S28,S22,S16,S10,S4)/52*$W4), "0,0") & " - " & TEXT((MAX(S28,S22,S16,S10,S4)*$W4)/52, "0,0") & ")" -> $7,305 (7,305 - 7,305) | T83: =TEXT((AVERAGE(T28,T22,T16,T10,T4)*$W4), "$0,0") & " (" & TEXT((MIN(T28,T22,T16,T10,T4)*$W4), "0,0") & " - " & TEXT((MAX(T28,T22,T16,T10,T4)*$W4), "0,0") & ")" -> $7,123 (00 - 18,994) | V83: =TEXT((AVERAGE(V28,V22,V16,V10,V4)), "$0,0") & " (" & TEXT((MIN(V28,V22,V16,V10,V4)), "0,0") & " - " & TEXT((MAX(V28,V22,V16,V10,V4)), "0,0") & ")" -> $60,027 (48,552 - 79,624) | W83: =TEXT((AVERAGE(W28,W22,W16,W10,W4)), "$0,0") & " (" & TEXT((MIN(W28,W22,W16,W10,W4)), "0,0") & " - " & TEXT((MAX(W28,W22,W16,W10,W4)), "0,0") & ")" -> $78,369 (70,196 - 94,969) | X83: =TEXT((AVERAGE(X28,X22,X16,X10,X4)), "$0,0") & " (" & TEXT((MIN(X28,X22,X16,X10,X4)), "0,0") & " - " & TEXT((MAX(X28,X22,X16,X10,X4)), "0,0") & ")" -> $96,710 (85,157 - 110,314)
A84: ALL | B84: Medical scientist | J84: =TEXT((AVERAGE(J29,J23,J17,J11,J5)*$W5), "$0,0") & " (" & TEXT((MIN(J29,J23,J17,J11,J5)*$W5), "0,0") & " - " & TEXT((MAX(J29,J23,J17,J11,J5)*$W5), "0,0") & ")" -> $11,156 (10,697 - 12,989) | M84: =TEXT((AVERAGE(M29,M23,M17,M11,M5)*$W5), "$0,0") & " (" & TEXT((MIN(M29,M23,M17,M11,M5)*$W5), "0,0") & " - " & TEXT((MAX(M29,M23,M17,M11,M5)*$W5), "0,0") & ")" -> $10,188 (10,188 - 10,188) | N84: =TEXT((AVERAGE(N29,N23,N17,N11,N5)*$W5), "$0,0") & " (" & TEXT((MIN(N29,N23,N17,N11,N5)*$W5), "0,0") & " - " & TEXT((MAX(N29,N23,N17,N11,N5)*$W5), "0,0") & ")" -> $3,566 (3,566 - 3,566) | O84: =TEXT((AVERAGE(O29,O23,O17,O11,O5)*$W5), "$0") & " (" & TEXT((MIN(O29,O23,O17,O11,O5)*$W5), "0") & " - " & TEXT((MAX(O29,O23,O17,O11,O5)*$W5), "0") & ")" -> $0 (0 - 0) | P84: =TEXT((AVERAGE(P29,P23,P17,P11,P5)*$W5), "$0") & " (" & TEXT((MIN(P29,P23,P17,P11,P5)*$W5), "0") & " - " & TEXT((MAX(P29,P23,P17,P11,P5)*$W5), "0") & ")" -> $0 (0 - 0) | Q84: =TEXT((AVERAGE(Q29,Q23,Q17,Q11,Q5)*$W5), "$0,0") & " (" & TEXT((MIN(Q29,Q23,Q17,Q11,Q5)*$W5), "0,0") & " - " & TEXT((MAX(Q29,Q23,Q17,Q11,Q5)*$W5), "0,0") & ")" -> $4,686 (4,686 - 4,686) | R84: =TEXT((AVERAGE(R29,R23,R17,R11,R5)), "$0,0") & " (" & TEXT((MIN(R29,R23,R17,R11,R5)), "0,0") & " - " & TEXT((MAX(R29,R23,R17,R11,R5)), "0,0") & ")" -> $365 (00 - 1,826) | S84: =TEXT((AVERAGE(S29,S23,S17,S11,S5)/52*$W5), "$0,0") & " (" & TEXT((MIN(S29,S23,S17,S11,S5)/52*$W5), "0,0") & " - " & TEXT((MAX(S29,S23,S17,S11,S5)*$W5)/52, "0,0") & ")" -> $8,620 (7,837 - 9,796) | T84: =TEXT((AVERAGE(T29,T23,T17,T11,T5)*$W5), "$0,0") & " (" & TEXT((MIN(T29,T23,T17,T11,T5)*$W5), "0,0") & " - " & TEXT((MAX(T29,T23,T17,T11,T5)*$W5), "0,0") & ")" -> $11,207 (00 - 20,376) | V84: =TEXT((AVERAGE(V29,V23,V17,V11,V5)), "$0,0") & " (" & TEXT((MIN(V29,V23,V17,V11,V5)), "0,0") & " - " & TEXT((MAX(V29,V23,V17,V11,V5)), "0,0") & ")" -> $68,336 (61,204 - 77,833) | W84: =TEXT((AVERAGE(W29,W23,W17,W11,W5)), "$0,0") & " (" & TEXT((MIN(W29,W23,W17,W11,W5)), "0,0") & " - " & TEXT((MAX(W29,W23,W17,W11,W5)), "0,0") & ")" -> $104,472 (101,878 - 109,041) | X84: =TEXT((AVERAGE(X29,X23,X17,X11,X5)), "$0,0") & " (" & TEXT((MIN(X29,X23,X17,X11,X5)), "0,0") & " - " & TEXT((MAX(X29,X23,X17,X11,X5)), "0,0") & ")" -> $140,609 (138,575 - 142,553)
A85: ALL | B85: Admin staff | J85: =TEXT((AVERAGE(J30,J24,J18,J12,J6)*$W6), "$0,0") & " (" & TEXT((MIN(J30,J24,J18,J12,J6)*$W6), "0,0") & " - " & TEXT((MAX(J30,J24,J18,J12,J6)*$W6), "0,0") & ")" -> $8,495 (8,146 - 9,892) | M85: =TEXT((AVERAGE(M30,M24,M18,M12,M6)*$W6), "$0,0") & " (" & TEXT((MIN(M30,M24,M18,M12,M6)*$W6), "0,0") & " - " & TEXT((MAX(M30,M24,M18,M12,M6)*$W6), "0,0") & ")" -> $7,758 (7,758 - 7,758) | N85: =TEXT((AVERAGE(N30,N24,N18,N12,N6)*$W6), "$0,0") & " (" & TEXT((MIN(N30,N24,N18,N12,N6)*$W6), "0,0") & " - " & TEXT((MAX(N30,N24,N18,N12,N6)*$W6), "0,0") & ")" -> $2,715 (2,715 - 2,715) | O85: =TEXT((AVERAGE(O30,O24,O18,O12,O6)*$W6), "$0") & " (" & TEXT((MIN(O30,O24,O18,O12,O6)*$W6), "0") & " - " & TEXT((MAX(O30,O24,O18,O12,O6)*$W6), "0") & ")" -> $0 (0 - 0) | P85: =TEXT((AVERAGE(P30,P24,P18,P12,P6)*$W6), "$0") & " (" & TEXT((MIN(P30,P24,P18,P12,P6)*$W6), "0") & " - " & TEXT((MAX(P30,P24,P18,P12,P6)*$W6), "0") & ")" -> $0 (0 - 0) | Q85: =TEXT((AVERAGE(Q30,Q24,Q18,Q12,Q6)*$W6), "$0,0") & " (" & TEXT((MIN(Q30,Q24,Q18,Q12,Q6)*$W6), "0,0") & " - " & TEXT((MAX(Q30,Q24,Q18,Q12,Q6)*$W6), "0,0") & ")" -> $3,569 (3,569 - 3,569) | R85: =TEXT((AVERAGE(R30,R24,R18,R12,R6)), "$0,0") & " (" & TEXT((MIN(R30,R24,R18,R12,R6)), "0,0") & " - " & TEXT((MAX(R30,R24,R18,R12,R6)), "0,0") & ")" -> $365 (00 - 1,826) | S85: =TEXT((AVERAGE(S30,S24,S18,S12,S6)/52*$W6), "$0,0") & " (" & TEXT((MIN(S30,S24,S18,S12,S6)/52*$W6), "0,0") & " - " & TEXT((MAX(S30,S24,S18,S12,S6)*$W6)/52, "0,0") & ")" -> $5,968 (5,968 - 5,968) | T85: =TEXT((AVERAGE(T30,T24,T18,T12,T6)*$W6), "$0,0") & " (" & TEXT((MIN(T30,T24,T18,T12,T6)*$W6), "0,0") & " - " & TEXT((MAX(T30,T24,T18,T12,T6)*$W6), "0,0") & ")" -> $5,819 (00 - 15,516) | V85: =TEXT((AVERAGE(V30,V24,V18,V12,V6)), "$0,0") & " (" & TEXT((MIN(V30,V24,V18,V12,V6)), "0,0") & " - " & TEXT((MAX(V30,V24,V18,V12,V6)), "0,0") & ")" -> $54,816 (47,704 - 63,701) | W85: =TEXT((AVERAGE(W30,W24,W18,W12,W6)), "$0,0") & " (" & TEXT((MIN(W30,W24,W18,W12,W6)), "0,0") & " - " & TEXT((MAX(W30,W24,W18,W12,W6)), "0,0") & ")" -> $65,203 (57,943 - 77,581) | X85: =TEXT((AVERAGE(X30,X24,X18,X12,X6)), "$0,0") & " (" & TEXT((MIN(X30,X24,X18,X12,X6)), "0,0") & " - " & TEXT((MAX(X30,X24,X18,X12,X6)), "0,0") & ")" -> $75,589 (67,705 - 91,460)
A86: ALL | B86: Bioinformatics staff | J86: =TEXT((AVERAGE(J31,J25,J19,J13,J7)*$W7), "$0,0") & " (" & TEXT((MIN(J31,J25,J19,J13,J7)*$W7), "0,0") & " - " & TEXT((MAX(J31,J25,J19,J13,J7)*$W7), "0,0") & ")" -> $11,154 (10,695 - 12,987) | M86: =TEXT((AVERAGE(M31,M25,M19,M13,M7)*$W7), "$0,0") & " (" & TEXT((MIN(M31,M25,M19,M13,M7)*$W7), "0,0") & " - " & TEXT((MAX(M31,M25,M19,M13,M7)*$W7), "0,0") & ")" -> $10,186 (10,186 - 10,186) | N86: =TEXT((AVERAGE(N31,N25,N19,N13,N7)*$W7), "$0,0") & " (" & TEXT((MIN(N31,N25,N19,N13,N7)*$W7), "0,0") & " - " & TEXT((MAX(N31,N25,N19,N13,N7)*$W7), "0,0") & ")" -> $3,565 (3,565 - 3,565) | O86: =TEXT((AVERAGE(O31,O25,O19,O13,O7)*$W7), "$0") & " (" & TEXT((MIN(O31,O25,O19,O13,O7)*$W7), "0") & " - " & TEXT((MAX(O31,O25,O19,O13,O7)*$W7), "0") & ")" -> $0 (0 - 0) | P86: =TEXT((AVERAGE(P31,P25,P19,P13,P7)*$W7), "$0") & " (" & TEXT((MIN(P31,P25,P19,P13,P7)*$W7), "0") & " - " & TEXT((MAX(P31,P25,P19,P13,P7)*$W7), "0") & ")" -> $0 (0 - 0) | Q86: =TEXT((AVERAGE(Q31,Q25,Q19,Q13,Q7)*$W7), "$0,0") & " (" & TEXT((MIN(Q31,Q25,Q19,Q13,Q7)*$W7), "0,0") & " - " & TEXT((MAX(Q31,Q25,Q19,Q13,Q7)*$W7), "0,0") & ")" -> $4,686 (4,686 - 4,686) | R86: =TEXT((AVERAGE(R31,R25,R19,R13,R7)), "$0,0") & " (" & TEXT((MIN(R31,R25,R19,R13,R7)), "0,0") & " - " & TEXT((MAX(R31,R25,R19,R13,R7)), "0,0") & ")" -> $365 (00 - 1,826) | S86: =TEXT((AVERAGE(S31,S25,S19,S13,S7)/52*$W7), "$0,0") & " (" & TEXT((MIN(S31,S25,S19,S13,S7)/52*$W7), "0,0") & " - " & TEXT((MAX(S31,S25,S19,S13,S7)*$W7)/52, "0,0") & ")" -> $7,835 (7,835 - 7,835) | T86: =TEXT((AVERAGE(T31,T25,T19,T13,T7)*$W7), "$0,0") & " (" & TEXT((MIN(T31,T25,T19,T13,T7)*$W7), "0,0") & " - " & TEXT((MAX(T31,T25,T19,T13,T7)*$W7), "0,0") & ")" -> $11,205 (00 - 20,372) | V86: =TEXT((AVERAGE(V31,V25,V19,V13,V7)), "$0,0") & " (" & TEXT((MIN(V31,V25,V19,V13,V7)), "0,0") & " - " & TEXT((MAX(V31,V25,V19,V13,V7)), "0,0") & ")" -> $72,209 (66,106 - 79,898) | W86: =TEXT((AVERAGE(W31,W25,W19,W13,W7)), "$0,0") & " (" & TEXT((MIN(W31,W25,W19,W13,W7)), "0,0") & " - " & TEXT((MAX(W31,W25,W19,W13,W7)), "0,0") & ")" -> $94,994 (86,781 - 104,304) | X86: =TEXT((AVERAGE(X31,X25,X19,X13,X7)), "$0,0") & " (" & TEXT((MIN(X31,X25,X19,X13,X7)), "0,0") & " - " & TEXT((MAX(X31,X25,X19,X13,X7)), "0,0") & ")" -> $117,778 (93,664 - 139,576)
A87: ALL | B87: Pathologists | J87: =TEXT((AVERAGE(J32,J26,J20,J14,J8)*$W8), "$0,0") & " (" & TEXT((MIN(J32,J26,J20,J14,J8)*$W8), "0,0") & " - " & TEXT((MAX(J32,J26,J20,J14,J8)*$W8), "0,0") & ")" -> $32,439 (31,106 - 37,772) | M87: =TEXT((AVERAGE(M32,M26,M20,M14,M8)*$W8), "$0,0") & " (" & TEXT((MIN(M32,M26,M20,M14,M8)*$W8), "0,0") & " - " & TEXT((MAX(M32,M26,M20,M14,M8)*$W8), "0,0") & ")" -> $00 (00 - 00) | N87: =TEXT((AVERAGE(N32,N26,N20,N14,N8)*$W8), "$0,0") & " (" & TEXT((MIN(N32,N26,N20,N14,N8)*$W8), "0,0") & " - " & TEXT((MAX(N32,N26,N20,N14,N8)*$W8), "0,0") & ")" -> $10,369 (10,369 - 10,369) | O87: =TEXT((AVERAGE(O32,O26,O20,O14,O8)*$W8), "$0,0") & " (" & TEXT((MIN(O32,O26,O20,O14,O8)*$W8), "0,0") & " - " & TEXT((MAX(O32,O26,O20,O14,O8)*$W8), "0,0") & ")" -> $11,850 (00 - 59,250) | P87: =TEXT((AVERAGE(P32,P26,P20,P14,P8)*$W8), "$0,0") & " (" & TEXT((MIN(P32,P26,P20,P14,P8)*$W8), "0,0") & " - " & TEXT((MAX(P32,P26,P20,P14,P8)*$W8), "0,0") & ")" -> $75,484 (00 - 177,749) | Q87: =TEXT((AVERAGE(Q32,Q26,Q20,Q14,Q8)*$W8), "$0,0") & " (" & TEXT((MIN(Q32,Q26,Q20,Q14,Q8)*$W8), "0,0") & " - " & TEXT((MAX(Q32,Q26,Q20,Q14,Q8)*$W8), "0,0") & ")" -> $13,627 (13,627 - 13,627) | R87: =TEXT((AVERAGE(R32,R26,R20,R14,R8)), "$0,0") & " (" & TEXT((MIN(R32,R26,R20,R14,R8)), "0,0") & " - " & TEXT((MAX(R32,R26,R20,R14,R8)), "0,0") & ")" -> $28,682 (21,500 - 38,000) | S87: =TEXT((AVERAGE(S32,S26,S20,S14,S8)/52*$W8), "$0,0") & " (" & TEXT((MIN(S32,S26,S20,S14,S8)/52*$W8), "0,0") & " - " & TEXT((MAX(S32,S26,S20,S14,S8)*$W8)/52, "0,0") & ")" -> $25,067 (22,788 - 28,485) | T87: =TEXT((AVERAGE(T32,T26,T20,T14,T8)*$W8), "$0,0") & " (" & TEXT((MIN(T32,T26,T20,T14,T8)*$W8), "0,0") & " - " & TEXT((MAX(T32,T26,T20,T14,T8)*$W8), "0,0") & ")" -> $31,106 (00 - 51,843) | V87: =TEXT((AVERAGE(V32,V26,V20,V14,V8)), "$0,0") & " (" & TEXT((MIN(V32,V26,V20,V14,V8)), "0,0") & " - " & TEXT((MAX(V32,V26,V20,V14,V8)), "0,0") & ")" -> $227,467 (179,078 - 297,757) | W87: =TEXT((AVERAGE(W32,W26,W20,W14,W8)), "$0,0") & " (" & TEXT((MIN(W32,W26,W20,W14,W8)), "0,0") & " - " & TEXT((MAX(W32,W26,W20,W14,W8)), "0,0") & ")" -> $266,292 (210,509 - 342,136) | X87: =TEXT((AVERAGE(X32,X26,X20,X14,X8)), "$0,0") & " (" & TEXT((MIN(X32,X26,X20,X14,X8)), "0,0") & " - " & TEXT((MAX(X32,X26,X20,X14,X8)), "0,0") & ")" -> $305,118 (241,940 - 386,515)
A89: %
A90: VIC | B90: Lab technician | J90: =(J4*$W4)/$Z4 -> 0.041154124 | M90: =(M4*$W4)/$Z4 -> 0.039194404 | N90: =(N4*$W4)/$Z4 -> 0.013718041 | O90: =(O4*$W4)/$Z4 -> 0 | P90: =(P4*$W4)/$Z4 -> 0 | Q90: =(Q4*$W4)/$Z4 -> 0.018029426 | R90: =(R4)/$Z4 -> 0 | S90: =(S4/52*$W4)/$Z4 -> 0.030149542 | T90: =(T4*$W4)/$Z4 -> 0.068590207 | V90: =(V4)/$Z4 -> 0.3286141 | W90: =(W4)/$Z4 -> 0.39194404 | X90: =(X4)/$Z4 -> 0.45527399
A91: VIC | B91: Medical scientist | J91: =(J5*$W5)/$Z5 -> 0.040792846 | M91: =(M5*$W5)/$Z5 -> 0.038850329 | N91: =(N5*$W5)/$Z5 -> 0.013597615 | O91: =(O5*$W5)/$Z5 -> 0 | P91: =(P5*$W5)/$Z5 -> 0 | Q91: =(Q5*$W5)/$Z5 -> 0.017871151 | R91: =(R5)/$Z5 -> 0 | S91: =(S5/52*$W5)/$Z5 -> 0.037356086 | T91: =(T5*$W5)/$Z5 -> 0.067988076 | V91: =(V5)/$Z5 -> 0.23339545 | W91: =(W5)/$Z5 -> 0.38850329 | X91: =(X5)/$Z5 -> 0.54361113
A92: VIC | B92: Admin staff | J92: =(J6*$W6)/$Z6 -> 0.041154124 | M92: =(M6*$W6)/$Z6 -> 0.039194404 | N92: =(N6*$W6)/$Z6 -> 0.013718041 | O92: =(O6*$W6)/$Z6 -> 0 | P92: =(P6*$W6)/$Z6 -> 0 | Q92: =(Q6*$W6)/$Z6 -> 0.018029426 | R92: =(R6)/$Z6 -> 0 | S92: =(S6/52*$W6)/$Z6 -> 0.030149542 | T92: =(T6*$W6)/$Z6 -> 0.068590207 | V92: =(V6)/$Z6 -> 0.32182349 | W92: =(W6)/$Z6 -> 0.39194404 | X92: =(X6)/$Z6 -> 0.46206459
A93: VIC | B93: Bioinformatics staff | J93: =(J7*$W7)/$Z7 -> 0.041154124 | M93: =(M7*$W7)/$Z7 -> 0.039194404 | N93: =(N7*$W7)/$Z7 -> 0.013718041 | O93: =(O7*$W7)/$Z7 -> 0 | P93: =(P7*$W7)/$Z7 -> 0 | Q93: =(Q7*$W7)/$Z7 -> 0.018029426 | R93: =(R7)/$Z7 -> 0 | S93: =(S7/52*$W7)/$Z7 -> 0.030149542 | T93: =(T7*$W7)/$Z7 -> 0.068590207 | V93: =(V7)/$Z7 -> 0.3063798 | W93: =(W7)/$Z7 -> 0.39194404 | X93: =(X7)/$Z7 -> 0.47750829
A94: VIC | B94: Pathologists | J94: =(J8*$W8)/$Z8 -> 0.041188162 | M94: =(M8*$W8)/$Z8 -> 0 | N94: =(N8*$W8)/$Z8 -> 0.013729387 | O94: =(O8*$W8)/$Z8 -> 0 | P94: =(P8*$W8)/$Z8 -> 0 | Q94: =(Q8*$W8)/$Z8 -> 0.018044338 | R94: =(R8)/$Z8 -> 0.038399735 | S94: =(S8/52*$W8)/$Z8 -> 0.030174478 | T94: =(T8*$W8)/$Z8 -> 0.068646937 | V94: =(V8)/$Z8 -> 0.33032859 | W94: =(W8)/$Z8 -> 0.39226821 | X94: =(X8)/$Z8 -> 0.45420784
A96: SA | B96: Lab technician | J96: =(J10*$W10)/$Z10 -> 0.044436487 | M96: =(M10*$W10)/$Z10 -> 0.042320464 | N96: =(N10*$W10)/$Z10 -> 0.014812162 | O96: =(O10*$W10)/$Z10 -> 0 | P96: =(P10*$W10)/$Z10 -> 0 | Q96: =(Q10*$W10)/$Z10 -> 0.019467413 | R96: =(R10)/$Z10 -> 0 | S96: =(S10/52*$W10)/$Z10 -> 0.032554203 | T96: =(T10*$W10)/$Z10 -> 0 | V96: =(V10)/$Z10 -> 0.29620456 | W96: =(W10)/$Z10 -> 0.42320464 | X96: =(X10)/$Z10 -> 0.55020471
A97: SA | B97: Medical scientist | J97: =(J11*$W11)/$Z11 -> 0.044077758 | M97: =(M11*$W11)/$Z11 -> 0.041978817 | N97: =(N11*$W11)/$Z11 -> 0.014692586 | O97: =(O11*$W11)/$Z11 -> 0 | P97: =(P11*$W11)/$Z11 -> 0 | Q97: =(Q11*$W11)/$Z11 -> 0.019310256 | R97: =(R11)/$Z11 -> 0 | S97: =(S11/52*$W11)/$Z11 -> 0.040364247 | T97: =(T11*$W11)/$Z11 -> 0 | V97: =(V11)/$Z11 -> 0.26735027 | W97: =(W11)/$Z11 -> 0.41978817 | X97: =(X11)/$Z11 -> 0.57222607
A98: SA | B98: Admin staff | J98: =(J12*$W12)/$Z12 -> 0.044436487 | M98: =(M12*$W12)/$Z12 -> 0.042320464 | N98: =(N12*$W12)/$Z12 -> 0.014812162 | O98: =(O12*$W12)/$Z12 -> 0 | P98: =(P12*$W12)/$Z12 -> 0 | Q98: =(Q12*$W12)/$Z12 -> 0.019467413 | R98: =(R12)/$Z12 -> 0 | S98: =(S12/52*$W12)/$Z12 -> 0.032554203 | T98: =(T12*$W12)/$Z12 -> 0 | V98: =(V12)/$Z12 -> 0.38007882 | W98: =(W12)/$Z12 -> 0.42320464 | X98: =(X12)/$Z12 -> 0.46633045
A99: SA | B99: Bioinformatics staff | J99: =(J13*$W13)/$Z13 -> 0.044436487 | M99: =(M13*$W13)/$Z13 -> 0.042320464 | N99: =(N13*$W13)/$Z13 -> 0.014812162 | O99: =(O13*$W13)/$Z13 -> 0 | P99: =(P13*$W13)/$Z13 -> 0 | Q99: =(Q13*$W13)/$Z13 -> 0.019467413 | R99: =(R13)/$Z13 -> 0 | S99: =(S13/52*$W13)/$Z13 -> 0.032554203 | T99: =(T13*$W13)/$Z13 -> 0 | V99: =(V13)/$Z13 -> 0.30675434 | W99: =(W13)/$Z13 -> 0.42320464 | X99: =(X13)/$Z13 -> 0.53965493
A100: SA | B100: Pathologists | J100: =(J14*$W14)/$Z14 -> 0.033068587 | M100: =(M14*$W14)/$Z14 -> 0 | N100: =(N14*$W14)/$Z14 -> 0.011022862 | O100: =(O14*$W14)/$Z14 -> 0 | P100: =(P14*$W14)/$Z14 -> 0.18896336 | Q100: =(Q14*$W14)/$Z14 -> 0.014487191 | R100: =(R14)/$Z14 -> 0.031883795 | S100: =(S14/52*$W14)/$Z14 -> 0.030282589 | T100: =(T14*$W14)/$Z14 -> 0.055114312 | V100: =(V14)/$Z14 -> 0.27177501 | W100: =(W14)/$Z14 -> 0.31493893 | X100: =(X14)/$Z14 -> 0.35810284
A102: NSW | B102: Lab technician | J102: =(J16*$W16)/$Z16 -> 0.044436487 | M102: =(M16*$W16)/$Z16 -> 0.042320464 | N102: =(N16*$W16)/$Z16 -> 0.014812162 | O102: =(O16*$W16)/$Z16 -> 0 | P102: =(P16*$W16)/$Z16 -> 0 | Q102: =(Q16*$W16)/$Z16 -> 0.019467413 | R102: =(R16)/$Z16 -> 0 | S102: =(S16/52*$W16)/$Z16 -> 0.032554203 | T102: =(T16*$W16)/$Z16 -> 0 | V102: =(V16)/$Z16 -> 0.32715924 | W102: =(W16)/$Z16 -> 0.42320464 | X102: =(X16)/$Z16 -> 0.51925003
A103: NSW | B103: Medical scientist | J103: =(J17*$W17)/$Z17 -> 0.041154124 | M103: =(M17*$W17)/$Z17 -> 0.039194404 | N103: =(N17*$W17)/$Z17 -> 0.013718041 | O103: =(O17*$W17)/$Z17 -> 0 | P103: =(P17*$W17)/$Z17 -> 0 | Q103: =(Q17*$W17)/$Z17 -> 0.018029426 | R103: =(R17)/$Z17 -> 0 | S103: =(S17/52*$W17)/$Z17 -> 0.030149542 | T103: =(T17*$W17)/$Z17 -> 0.068590207 | V103: =(V17)/$Z17 -> 0.25605582 | W103: =(W17)/$Z17 -> 0.39194404 | X103: =(X17)/$Z17 -> 0.52783226
... A118: WA | B118: Pathologists | J118: =(J32*$W32)/$Z32 -> 0.044729983 | M118: =(M32*$W32)/$Z32 -> 0 | N118: =(N32*$W32)/$Z32 -> 0.014909994 | O118: =(O32*$W32)/$Z32 -> 0 | P118: =(P32*$W32)/$Z32 -> 0 | Q118: =(Q32*$W32)/$Z32 -> 0.019595993 | R118: =(R32)/$Z32 -> 0.035995129 | S118: =(S32/52*$W32)/$Z32 -> 0.032769219 | T118: =(T32*$W32)/$Z32 -> 0 | V118: =(V32)/$Z32 -> 0.37074273 | W118: =(W32)/$Z32 -> 0.42599984 | X118: =(X32)/$Z32 -> 0.48125695
A120: ALL | B120: Lab technician | J120: =TEXT((AVERAGE(J28,J22,J16,J10,J4)*$W4/$Z4), "0.0%") & " (" & TEXT((MIN(J28,J22,J16,J10,J4)*$W4/$Z4), "0.0%") & " - " & TEXT((MAX(J28,J22,J16,J10,J4)*$W4/$Z4), "0.0%") & ")" -> 4.3% (4.1% - 5.0%) | M120: =TEXT((AVERAGE(M28,M22,M16,M10,M4)*$W4/$Z4), "0.0%") & " (" & TEXT((MIN(M28,M22,M16,M10,M4)*$W4/$Z4), "0.0%") & " - " & TEXT((MAX(M28,M22,M16,M10,M4)*$W4/$Z4), "0.0%") & ")" -> 3.9% (3.9% - 3.9%) | N120: =TEXT((AVERAGE(N28,N22,N16,N10,N4)*$W4/$Z4), "0.0%") & " (" & TEXT((MIN(N28,N22,N16,N10,N4)*$W4/$Z4), "0.0%") & " - " & TEXT((MAX(N28,N22,N16,N10,N4)*$W4/$Z4), "0.0%") & ")" -> 1.4% (1.4% - 1.4%) | O120: =TEXT((AVERAGE(O28,O22,O16,O10,O4)*$W4/$Z4), "0.0%") & " (" & TEXT((MIN(O28,O22,O16,O10,O4)*$W4/$Z4), "0.0%") & " - " & TEXT((MAX(O28,O22,O16,O10,O4)*$W4/$Z4), "0.0%") & ")" -> 0.0% (0.0% - 0.0%) | P120: =TEXT((AVERAGE(P28,P22,P16,P10,P4)*$W4/$Z4), "0.0%") & " (" & TEXT((MIN(P28,P22,P16,P10,P4)*$W4/$Z4), "0.0%") & " - " & TEXT((MAX(P28,P22,P16,P10,P4)*$W4/$Z4), "0.0%") & ")" -> 0.0% (0.0% - 0.0%) | Q120: =TEXT((AVERAGE(Q28,Q22,Q16,Q10,Q4)*$W4/$Z4), "0.0%") & " (" & TEXT((MIN(Q28,Q22,Q16,Q10,Q4)*$W4/$Z4), "0.0%") & " - " & TEXT((MAX(Q28,Q22,Q16,Q10,Q4)*$W4/$Z4), "0.0%") & ")" -> 1.8% (1.8% - 1.8%) | R120: =TEXT((AVERAGE(R28,R22,R16,R10,R4)/$Z4), "0.0%") & " (" & TEXT((MIN(R28,R22,R16,R10,R4)/$Z4), "0.0%") & " - " & TEXT((MAX(R28,R22,R16,R10,R4)/$Z4), "0.0%") & ")" -> 0.2% (0.0% - 0.8%) | S120: =TEXT((AVERAGE(S28,S22,S16,S10,S4)/52*$W4/$Z4), "0.0%") & " (" & TEXT((MIN(S28,S22,S16,S10,S4)/52*$W4/$Z4), "0.0%") & " - " & TEXT((MAX(S28,S22,S16,S10,S4)/52*$W4/$Z4), "0.0%") & ")" -> 3.0% (3.0% - 3.0%) | T120: =TEXT((AVERAGE(T28,T22,T16,T10,T4)*$W4/$Z4), "0.0%") & " (" & TEXT((MIN(T28,T22,T16,T10,T4)*$W4/$Z4), "0.0%") & " - " & TEXT((MAX(T28,T22,T16,T10,T4)*$W4/$Z4), "0.0%") & ")" -> 2.9% (0.0% - 7.8%) | V120: =TEXT((AVERAGE(V28,V22,V16,V10,V4)/$Z4), "0.0%") & " (" & TEXT((MIN(V28,V22,V16,V10,V4)/$Z4), "0.0%") & " - " & TEXT((MAX(V28,V22,V16,V10,V4)/$Z4), "0.0%") & ")" -> 24.8% (20.0% - 32.9%) | W120: =TEXT((AVERAGE(W28,W22,W16,W10,W4)/$Z4), "0.0%") & " (" & TEXT((MIN(W28,W22,W16,W10,W4)/$Z4), "0.0%") & " - " & TEXT((MAX(W28,W22,W16,W10,W4)/$Z4), "0.0%") & ")" -> 32.3% (29.0% - 39.2%) | X120: =TEXT((AVERAGE(X28,X22,X16,X10,X4)/$Z4), "0.0%") & " (" & TEXT((MIN(X28,X22,X16,X10,X4)/$Z4), "0.0%") & " - " & TEXT((MAX(X28,X22,X16,X10,X4)/$Z4), "0.0%") & ")" -> 39.9% (35.1% - 45.5%)
A121: ALL | B121: Medical scientist | J121: =TEXT((AVERAGE(J29,J23,J17,J11,J5)*$W5/$Z5), "0.0%") & " (" & TEXT((MIN(J29,J23,J17,J11,J5)*$W5/$Z5), "0.0%") & " - " & TEXT((MAX(J29,J23,J17,J11,J5)*$W5/$Z5), "0.0%") & ")" -> 4.3% (4.1% - 5.0%) | M121: =TEXT((AVERAGE(M29,M23,M17,M11,M5)*$W5/$Z5), "0.0%") & " (" & TEXT((MIN(M29,M23,M17,M11,M5)*$W5/$Z5), "0.0%") & " - " & TEXT((MAX(M29,M23,M17,M11,M5)*$W5/$Z5), "0.0%") & ")" -> 3.9% (3.9% - 3.9%) | N121: =TEXT((AVERAGE(N29,N23,N17,N11,N5)*$W5/$Z5), "0.0%") & " (" & TEXT((MIN(N29,N23,N17,N11,N5)*$W5/$Z5), "0.0%") & " - " & TEXT((MAX(N29,N23,N17,N11,N5)*$W5/$Z5), "0.0%") & ")" -> 1.4% (1.4% - 1.4%) | O121: =TEXT((AVERAGE(O29,O23,O17,O11,O5)*$W5/$Z5), "0.0%") & " (" & TEXT((MIN(O29,O23,O17,O11,O5)*$W5/$Z5), "0.0%") & " - " & TEXT((MAX(O29,O23,O17,O11,O5)*$W5/$Z5), "0.0%") & ")" -> 0.0% (0.0% - 0.0%) | P121: =TEXT((AVERAGE(P29,P23,P17,P11,P5)*$W5/$Z5), "0.0%") & " (" & TEXT((MIN(P29,P23,P17,P11,P5)*$W5/$Z5), "0.0%") & " - " & TEXT((MAX(P29,P23,P17,P11,P5)*$W5/$Z5), "0.0%") & ")" -> 0.0% (0.0% - 0.0%) | Q121: =TEXT((AVERAGE(Q29,Q23,Q17,Q11,Q5)*$W5/$Z5), "0.0%") & " (" & TEXT((MIN(Q29,Q23,Q17,Q11,Q5)*$W5/$Z5), "0.0%") & " - " & TEXT((MAX(Q29,Q23,Q17,Q11,Q5)*$W5/$Z5), "0.0%") & ")" -> 1.8% (1.8% - 1.8%) | R121: =TEXT((AVERAGE(R29,R23,R17,R11,R5)/$Z5), "0.0%") & " (" & TEXT((MIN(R29,R23,R17,R11,R5)/$Z5), "0.0%") & " - " & TEXT((MAX(R29,R23,R17,R11,R5)/$Z5), "0.0%") & ")" -> 0.1% (0.0% - 0.7%) | S121: =TEXT((AVERAGE(S29,S23,S17,S11,S5)/52*$W5/$Z5), "0.0%") & " (" & TEXT((MIN(S29,S23,S17,S11,S5)/52*$W5/$Z5), "0.0%") & " - " & TEXT((MAX(S29,S23,S17,S11,S5)/52*$W5/$Z5), "0.0%") & ")" -> 3.3% (3.0% - 3.7%) | T121: =TEXT((AVERAGE(T29,T23,T17,T11,T5)*$W5/$Z5), "0.0%") & " (" & TEXT((MIN(T29,T23,T17,T11,T5)*$W5/$Z5), "0.0%") & " - " & TEXT((MAX(T29,T23,T17,T11,T5)*$W5/$Z5), "0.0%") & ")" -> 4.3% (0.0% - 7.8%) | V121: =TEXT((AVERAGE(V29,V23,V17,V11,V5)/$Z5), "0.0%") & " (" & TEXT((MIN(V29,V23,V17,V11,V5)/$Z5), "0.0%") & " - " & TEXT((MAX(V29,V23,V17,V11,V5)/$Z5), "0.0%") & ")" -> 26.1% (23.3% - 29.7%) | W121: =TEXT((AVERAGE(W29,W23,W17,W11,W5)/$Z5), "0.0%") & " (" & TEXT((MIN(W29,W23,W17,W11,W5)/$Z5), "0.0%") & " - " & TEXT((MAX(W29,W23,W17,W11,W5)/$Z5), "0.0%") & ")" -> 39.8% (38.9% - 41.6%) | X121: =TEXT((AVERAGE(X29,X23,X17,X11,X5)/$Z5), "0.0%") & " (" & TEXT((MIN(X29,X23,X17,X11,X5)/$Z5), "0.0%") & " - " & TEXT((MAX(X29,X23,X17,X11,X5)/$Z5), "0.0%") & ")" -> 53.6% (52.8% - 54.4%)
A122: ALL | B122: Admin staff | J122: =TEXT((AVERAGE(J30,J24,J18,J12,J6)*$W6/$Z6), "0.0%") & " (" & TEXT((MIN(J30,J24,J18,J12,J6)*$W6/$Z6), "0.0%") & " - " & TEXT((MAX(J30,J24,J18,J12,J6)*$W6/$Z6), "0.0%") & ")" -> 4.3% (4.1% - 5.0%) | M122: =TEXT((AVERAGE(M30,M24,M18,M12,M6)*$W6/$Z6), "0.0%") & " (" & TEXT((MIN(M30,M24,M18,M12,M6)*$W6/$Z6), "0.0%") & " - " & TEXT((MAX(M30,M24,M18,M12,M6)*$W6/$Z6), "0.0%") & ")" -> 3.9% (3.9% - 3.9%) | N122: =TEXT((AVERAGE(N30,N24,N18,N12,N6)*$W6/$Z6), "0.0%") & " (" & TEXT((MIN(N30,N24,N18,N12,N6)*$W6/$Z6), "0.0%") & " - " & TEXT((MAX(N30,N24,N18,N12,N6)*$W6/$Z6), "0.0%") & ")" -> 1.4% (1.4% - 1.4%) | O122: =TEXT((AVERAGE(O30,O24,O18,O12,O6)*$W6/$Z6), "0.0%") & " (" & TEXT((MIN(O30,O24,O18,O12,O6)*$W6/$Z6), "0.0%") & " - " & TEXT((MAX(O30,O24,O18,O12,O6)*$W6/$Z6), "0.0%") & ")" -> 0.0% (0.0% - 0.0%) | P122: =TEXT((AVERAGE(P30,P24,P18,P12,P6)*$W6/$Z6), "0.0%") & " (" & TEXT((MIN(P30,P24,P18,P12,P6)*$W6/$Z6), "0.0%") & " - " & TEXT((MAX(P30,P24,P18,P12,P6)*$W6/$Z6), "0.0%") & ")" -> 0.0% (0.0% - 0.0%) | Q122: =TEXT((AVERAGE(Q30,Q24,Q18,Q12,Q6)*$W6/$Z6), "0.0%") & " (" & TEXT((MIN(Q30,Q24,Q18,Q12,Q6)*$W6/$Z6), "0.0%") & " - " & TEXT((MAX(Q30,Q24,Q18,Q12,Q6)*$W6/$Z6), "0.0%") & ")" -> 1.8% (1.8% - 1.8%) | R122: =TEXT((AVERAGE(R30,R24,R18,R12,R6)/$Z6), "0.0%") & " (" & TEXT((MIN(R30,R24,R18,R12,R6)/$Z6), "0.0%") & " - " & TEXT((MAX(R30,R24,R18,R12,R6)/$Z6), "0.0%") & ")" -> 0.2% (0.0% - 0.9%) | S122: =TEXT((AVERAGE(S30,S24,S18,S12,S6)/52*$W6/$Z6), "0.0%") & " (" & TEXT((MIN(S30,S24,S18,S12,S6)/52*$W6/$Z6), "0.0%") & " - " & TEXT((MAX(S30,S24,S18,S12,S6)/52*$W6/$Z6), "0.0%") & ")" -> 3.0% (3.0% - 3.0%) | T122: =TEXT((AVERAGE(T30,T24,T18,T12,T6)*$W6/$Z6), "0.0%") & " (" & TEXT((MIN(T30,T24,T18,T12,T6)*$W6/$Z6), "0.0%") & " - " & TEXT((MAX(T30,T24,T18,T12,T6)*$W6/$Z6), "0.0%") & ")" -> 2.9% (0.0% - 7.8%) | V122: =TEXT((AVERAGE(V30,V24,V18,V12,V6)/$Z6), "0.0%") & " (" & TEXT((MIN(V30,V24,V18,V12,V6)/$Z6), "0.0%") & " - " & TEXT((MAX(V30,V24,V18,V12,V6)/$Z6), "0.0%") & ")" -> 27.7% (24.1% - 32.2%) | W122: =TEXT((AVERAGE(W30,W24,W18,W12,W6)/$Z6), "0.0%") & " (" & TEXT((MIN(W30,W24,W18,W12,W6)/$Z6), "0.0%") & " - " & TEXT((MAX(W30,W24,W18,W12,W6)/$Z6), "0.0%") & ")" -> 32.9% (29.3% - 39.2%) | X122: =TEXT((AVERAGE(X30,X24,X18,X12,X6)/$Z6), "0.0%") & " (" & TEXT((MIN(X30,X24,X18,X12,X6)/$Z6), "0.0%") & " - " & TEXT((MAX(X30,X24,X18,X12,X6)/$Z6), "0.0%") & ")" -> 38.2% (34.2% - 46.2%)
A123: ALL | B123: Bioinformatics staff | J123: =TEXT((AVERAGE(J31,J25,J19,J13,J7)*$W7/$Z7), "0.0%") & " (" & TEXT((MIN(J31,J25,J19,J13,J7)*$W7/$Z7), "0.0%") & " - " & TEXT((MAX(J31,J25,J19,J13,J7)*$W7/$Z7), "0.0%") & ")" -> 4.3% (4.1% - 5.0%) | M123: =TEXT((AVERAGE(M31,M25,M19,M13,M7)*$W7/$Z7), "0.0%") & " (" & TEXT((MIN(M31,M25,M19,M13,M7)*$W7/$Z7), "0.0%") & " - " & TEXT((MAX(M31,M25,M19,M13,M7)*$W7/$Z7), "0.0%") & ")" -> 3.9% (3.9% - 3.9%) | N123: =TEXT((AVERAGE(N31,N25,N19,N13,N7)*$W7/$Z7), "0.0%") & " (" & TEXT((MIN(N31,N25,N19,N13,N7)*$W7/$Z7), "0.0%") & " - " & TEXT((MAX(N31,N25,N19,N13,N7)*$W7/$Z7), "0.0%") & ")" -> 1.4% (1.4% - 1.4%) | O123: =TEXT((AVERAGE(O31,O25,O19,O13,O7)*$W7/$Z7), "0.0%") & " (" & TEXT((MIN(O31,O25,O19,O13,O7)*$W7/$Z7), "0.0%") & " - " & TEXT((MAX(O31,O25,O19,O13,O7)*$W7/$Z7), "0.0%") & ")" -> 0.0% (0.0% - 0.0%) | P123: =TEXT((AVERAGE(P31,P25,P19,P13,P7)*$W7/$Z7), "0.0%") & " (" & TEXT((MIN(P31,P25,P19,P13,P7)*$W7/$Z7), "0.0%") & " - " & TEXT((MAX(P31,P25,P19,P13,P7)*$W7/$Z7), "0.0%") & ")" -> 0.0% (0.0% - 0.0%) | Q123: =TEXT((AVERAGE(Q31,Q25,Q19,Q13,Q7)*$W7/$Z7), "0.0%") & " (" & TEXT((MIN(Q31,Q25,Q19,Q13,Q7)*$W7/$Z7), "0.0%") & " - " & TEXT((MAX(Q31,Q25,Q19,Q13,Q7)*$W7/$Z7), "0.0%") & ")" -> 1.8% (1.8% - 1.8%) | R123: =TEXT((AVERAGE(R31,R25,R19,R13,R7)/$Z7), "0.0%") & " (" & TEXT((MIN(R31,R25,R19,R13,R7)/$Z7), "0.0%") & " - " & TEXT((MAX(R31,R25,R19,R13,R7)/$Z7), "0.0%") & ")" -> 0.1% (0.0% - 0.7%) | S123: =TEXT((AVERAGE(S31,S25,S19,S13,S7)/52*$W7/$Z7), "0.0%") & " (" & TEXT((MIN(S31,S25,S19,S13,S7)/52*$W7/$Z7), "0.0%") & " - " & TEXT((MAX(S31,S25,S19,S13,S7)/52*$W7/$Z7), "0.0%") & ")" -> 3.0% (3.0% - 3.0%) | T123: =TEXT((AVERAGE(T31,T25,T19,T13,T7)*$W7/$Z7), "0.0%") & " (" & TEXT((MIN(T31,T25,T19,T13,T7)*$W7/$Z7), "0.0%") & " - " & TEXT((MAX(T31,T25,T19,T13,T7)*$W7/$Z7), "0.0%") & ")" -> 4.3% (0.0% - 7.8%) | V123: =TEXT((AVERAGE(V31,V25,V19,V13,V7)/$Z7), "0.0%") & " (" & TEXT((MIN(V31,V25,V19,V13,V7)/$Z7), "0.0%") & " - " & TEXT((MAX(V31,V25,V19,V13,V7)/$Z7), "0.0%") & ")" -> 27.8% (25.4% - 30.7%) | W123: =TEXT((AVERAGE(W31,W25,W19,W13,W7)/$Z7), "0.0%") & " (" & TEXT((MIN(W31,W25,W19,W13,W7)/$Z7), "0.0%") & " - " & TEXT((MAX(W31,W25,W19,W13,W7)/$Z7), "0.0%") & ")" -> 36.6% (33.4% - 40.1%) | X123: =TEXT((AVERAGE(X31,X25,X19,X13,X7)/$Z7), "0.0%") & " (" & TEXT((MIN(X31,X25,X19,X13,X7)/$Z7), "0.0%") & " - " & TEXT((MAX(X31,X25,X19,X13,X7)/$Z7), "0.0%") & ")" -> 45.3% (36.0% - 53.7%)
A124: ALL | B124: Pathologists | J124: =TEXT((AVERAGE(J32,J26,J20,J14,J8)*$W8/$Z8), "0.0%") & " (" & TEXT((MIN(J32,J26,J20,J14,J8)*$W8/$Z8), "0.0%") & " - " & TEXT((MAX(J32,J26,J20,J14,J8)*$W8/$Z8), "0.0%") & ")" -> 4.3% (4.1% - 5.0%) | M124: =TEXT((AVERAGE(M32,M26,M20,M14,M8)*$W8/$Z8), "0.0%") & " (" & TEXT((MIN(M32,M26,M20,M14,M8)*$W8/$Z8), "0.0%") & " - " & TEXT((MAX(M32,M26,M20,M14,M8)*$W8/$Z8), "0.0%") & ")" -> 0.0% (0.0% - 0.0%) | N124: =TEXT((AVERAGE(N32,N26,N20,N14,N8)*$W8/$Z8), "0.0%") & " (" & TEXT((MIN(N32,N26,N20,N14,N8)*$W8/$Z8), "0.0%") & " - " & TEXT((MAX(N32,N26,N20,N14,N8)*$W8/$Z8), "0.0%") & ")" -> 1.4% (1.4% - 1.4%) | O124: =TEXT((AVERAGE(O32,O26,O20,O14,O8)*$W8/$Z8), "0.0%") & " (" & TEXT((MIN(O32,O26,O20,O14,O8)*$W8/$Z8), "0.0%") & " - " & TEXT((MAX(O32,O26,O20,O14,O8)*$W8/$Z8), "0.0%") & ")" -> 1.6% (0.0% - 7.8%) | P124: =TEXT((AVERAGE(P32,P26,P20,P14,P8)*$W8/$Z8), "0.0%") & " (" & TEXT((MIN(P32,P26,P20,P14,P8)*$W8/$Z8), "0.0%") & " - " & TEXT((MAX(P32,P26,P20,P14,P8)*$W8/$Z8), "0.0%") & ")" -> 10.0% (0.0% - 23.5%) | Q124: =TEXT((AVERAGE(Q32,Q26,Q20,Q14,Q8)*$W8/$Z8), "0.0%") & " (" & TEXT((MIN(Q32,Q26,Q20,Q14,Q8)*$W8/$Z8), "0.0%") & " - " & TEXT((MAX(Q32,Q26,Q20,Q14,Q8)*$W8/$Z8), "0.0%") & ")" -> 1.8% (1.8% - 1.8%) | R124: =TEXT((AVERAGE(R32,R26,R20,R14,R8)/$Z8), "0.0%") & " (" & TEXT((MIN(R32,R26,R20,R14,R8)/$Z8), "0.0%") & " - " & TEXT((MAX(R32,R26,R20,R14,R8)/$Z8), "0.0%") & ")" -> 3.8% (2.8% - 5.0%) | S124: =TEXT((AVERAGE(S32,S26,S20,S14,S8)/52*$W8/$Z8), "0.0%") & " (" & TEXT((MIN(S32,S26,S20,S14,S8)/52*$W8/$Z8), "0.0%") & " - " & TEXT((MAX(S32,S26,S20,S14,S8)/52*$W8/$Z8), "0.0%") & ")" -> 3.3% (3.0% - 3.8%) | T124: =TEXT((AVERAGE(T32,T26,T20,T14,T8)*$W8/$Z8), "0.0%") & " (" & TEXT((MIN(T32,T26,T20,T14,T8)*$W8/$Z8), "0.0%") & " - " & TEXT((MAX(T32,T26,T20,T14,T8)*$W8/$Z8), "0.0%") & ")" -> 4.1% (0.0% - 6.9%) | V124: =TEXT((AVERAGE(V32,V26,V20,V14,V8)/$Z8), "0.0%") & " (" & TEXT((MIN(V32,V26,V20,V14,V8)/$Z8), "0.0%") & " - " & TEXT((MAX(V32,V26,V20,V14,V8)/$Z8), "0.0%") & ")" -> 30.1% (23.7% - 39.4%) | W124: =TEXT((AVERAGE(W32,W26,W20,W14,W8)/$Z8), "0.0%") & " (" & TEXT((MIN(W32,W26,W20,W14,W8)/$Z8), "0.0%") & " - " & TEXT((MAX(W32,W26,W20,W14,W8)/$Z8), "0.0%") & ")" -> 35.3% (27.9% - 45.3%) | X124: =TEXT((AVERAGE(X32,X26,X20,X14,X8)/$Z8), "0.0%") & " (" & TEXT((MIN(X32,X26,X20,X14,X8)/$Z8), "0.0%") & " - " & TEXT((MAX(X32,X26,X20,X14,X8)/$Z8), "0.0%") & ")" -> 40.4% (32.0% - 51.2%)

Sheet Labour - Prices (WM)
V1: Year 0 | AE1: Year 1 | AN1: Year 2 | AW1: Year 3 | BF1: Year 4
A2: Jurisdiction | B2: Personnel type | C2: Label | D2: Award | E2: Grade(s) | V2: Base Salary | Y2: Base Salary + Costs | AB2: Base Salary + Costs (hourly) | AE2: Base Salary | AH2: Base Salary + Costs | AK2: Base Salary + Costs (hourly) | AN2: Base Salary | AQ2: Base Salary + Costs | AT2: Base Salary + Costs (hourly) | AW2: Base Salary | AZ2: Base Salary + Costs | BC2: Base Salary + Costs (hourly) | BF2: Base Salary | BI2: Base Salary + Costs | BL2: Base Salary + Costs (hourly)
F3: Distribution desc | G3: References | H3: Rate of Pay (weekly, 38h) desc | I3: Year | J3: Superannuation Rate (%) | K3: Hours per week | L3: Average productive time (%) | M3: Average Penalties % | N3: Public Holiday Penalty % | O3: Private Practice Loading % | P3: Attraction and Retention Allowance % | Q3: Sick Leave % | R3: Professional Development Allowance ($) | S3: Annual Leave Entitlement (Weeks) | T3: Annual Leave Loading (%) | U3: Indexation per annum (%) | V3: LL | W3: Mid-point | X3: UL | Y3: LL | Z3: Mid-point | AA3: UL | AB3: LL | AC3: Mid-point | AD3: UL | AE3: LL | AF3: Mid-point | AG3: UL | AH3: LL | AI3: Mid-point | AJ3: UL | AK3: LL | AL3: Mid-point | AM3: UL | AN3: LL | AO3: Mid-point | AP3: UL | AQ3: LL | AR3: Mid-point | AS3: UL | AT3: LL | AU3: Mid-point | AV3: UL | AW3: LL | AX3: Mid-point | AY3: UL | AZ3: LL | BA3: Mid-point | BB3: UL | BC3: LL | BD3: Mid-point | BE3: UL | BF3: LL | BG3: Mid-point | BH3: UL | BI3: LL | BJ3: Mid-point | BK3: UL | BL3: LL | BM3: Mid-point | BN3: UL
A4: VIC | B4: Lab technician | C4: LT | D4: HPA | E4: 5-7 | F4: normal distro | G4: pp247 HS5-HS7 (July 22) | H4: 1785.7-2257.10 | I4: 2022 | J4: 0.105 | K4: 38 | L4: 1 | M4: 0.1 | N4: 0.035 | O4: 0 | P4: 0 | Q4: 0.046 | R4: 0 | S4: 4 | T4: 0.175 | U4: 0.015 | V4: 79624 | W4: =V4+((X4-V4)/2) -> 94969 | X4: 110314 | Y4: =(V4+(V4*$J4)+(V4*$M4)+(V4*$N4)+(V4*$O4)+(V4*$P4)+(V4*$Q4)+($R4)+(V4*((52+$S4)/52))*(1+$T4))*1/$L4 -> 203151.45 | Z4: =(W4+(W4*$J4)+(W4*$M4)+(W4*$N4)+(W4*$O4)+(W4*$P4)+(W4*$Q4)+($R4)+(W4*((52+$S4)/52))*(1+$T4))*1/$L4 -> 242302.45 | AA4: =(X4+(X4*$J4)+(X4*$M4)+(X4*$N4)+(X4*$O4)+(X4*$P4)+(X4*$Q4)+($R4)+(X4*((52+$S4)/52))*(1+$T4))*1/$L4 -> 281453.44 | AB4: =Y4/52/$K4 -> 102.80944 | AC4: =Z4/52/$K4 -> 122.6227 | AD4: =AA4/52/$K4 -> 142.43595 | AE4: =($V4*(1+(($U4/100)*1))) -> 79635.944 | AF4: =($W4*(1+(($U4/100)*1))) -> 94983.245 | AG4: =($X4*(1+(($U4/100)*1))) -> 110330.55 | AH4: =(AE4+(AE4*$J4)+(AE4*$M4)+(AE4*$N4)+(AE4*$O4)+(AE4*$P4)+(AE4*$Q4)+($R4)+(AE4*((52+$S4)/52))*(1+$T4))*1/$L4 -> 203181.92 | AI4: =(AF4+(AF4*$J4)+(AF4*$M4)+(AF4*$N4)+(AF4*$O4)+(AF4*$P4)+(AF4*$Q4)+($R4)+(AF4*((52+$S4)/52))*(1+$T4))*1/$L4 -> 242338.79 | AJ4: =(AG4+(AG4*$J4)+(AG4*$M4)+(AG4*$N4)+(AG4*$O4)+(AG4*$P4)+(AG4*$Q4)+($R4)+(AG4*((52+$S4)/52))*(1+$T4))*1/$L4 -> 281495.66 | AK4: =AH4/52/$K4 -> 102.82486 | AL4: =AI4/52/$K4 -> 122.64109 | AM4: =AJ4/52/$K4 -> 142.45732 | AN4: =($V4*(1+(($U4/100)*2))) -> 79647.887 | AO4: =($W4*(1+(($U4/100)*2))) -> 94997.491 | AP4: =($X4*(1+(($U4/100)*2))) -> 110347.09 | AQ4: =(AN4+(AN4*$J4)+(AN4*$M4)+(AN4*$N4)+(AN4*$O4)+(AN4*$P4)+(AN4*$Q4)+($R4)+(AN4*((52+$S4)/52))*(1+$T4))*1/$L4 -> 203212.39 | AR4: =(AO4+(AO4*$J4)+(AO4*$M4)+(AO4*$N4)+(AO4*$O4)+(AO4*$P4)+(AO4*$Q4)+($R4)+(AO4*((52+$S4)/52))*(1+$T4))*1/$L4 -> 242375.14 | AS4: =(AP4+(AP4*$J4)+(AP4*$M4)+(AP4*$N4)+(AP4*$O4)+(AP4*$P4)+(AP4*$Q4)+($R4)+(AP4*((52+$S4)/52))*(1+$T4))*1/$L4 -> 281537.88 | AT4: =AQ4/52/$K4 -> 102.84028 | AU4: =AR4/52/$K4 -> 122.65948 | AV4: =AS4/52/$K4 -> 142.47868 | AW4: =($V4*(1+(($U4/100)*3))) -> 79659.831 | AX4: =($W4*(1+(($U4/100)*3))) -> 95011.736 | AY4: =($X4*(1+(($U4/100)*3))) -> 110363.64 | AZ4: =(AW4+(AW4*$J4)+(AW4*$M4)+(AW4*$N4)+(AW4*$O4)+(AW4*$P4)+(AW4*$Q4)+($R4)+(AW4*((52+$S4)/52))*(1+$T4))*1/$L4 -> 203242.87 | BA4: =(AX4+(AX4*$J4)+(AX4*$M4)+(AX4*$N4)+(AX4*$O4)+(AX4*$P4)+(AX4*$Q4)+($R4)+(AX4*((52+$S4)/52))*(1+$T4))*1/$L4 -> 242411.48 | BB4: =(AY4+(AY4*$J4)+(AY4*$M4)+(AY4*$N4)+(AY4*$O4)+(AY4*$P4)+(AY4*$Q4)+($R4)+(AY4*((52+$S4)/52))*(1+$T4))*1/$L4 -> 281580.1 | BC4: =AZ4/52/$K4 -> 102.8557 | BD4: =BA4/52/$K4 -> 122.67788 | BE4: =BB4/52/$K4 -> 142.50005 | BF4: =($V4*(1+(($U4/100)*4))) -> 79671.774 | BG4: =($W4*(1+(($U4/100)*4))) -> 95025.981 | BH4: =($X4*(1+(($U4/100)*4))) -> 110380.19 | BI4: =(BF4+(BF4*$J4)+(BF4*$M4)+(BF4*$N4)+(BF4*$O4)+(BF4*$P4)+(BF4*$Q4)+($R4)+(BF4*((52+$S4)/52))*(1+$T4))*1/$L4 -> 203273.34 | BJ4: =(BG4+(BG4*$J4)+(BG4*$M4)+(BG4*$N4)+(BG4*$O4)+(BG4*$P4)+(BG4*$Q4)+($R4)+(BG4*((52+$S4)/52))*(1+$T4))*1/$L4 -> 242447.83 | BK4: =(BH4+(BH4*$J4)+(BH4*$M4)+(BH4*$N4)+(BH4*$O4)+(BH4*$P4)+(BH4*$Q4)+($R4)+(BH4*((52+$S4)/52))*(1+$T4))*1/$L4 -> 281622.31 | BL4: =BI4/52/$K4 -> 102.87112 | BM4: =BJ4/52/$K4 -> 122.69627 | BN4: =BK4/52/$K4 -> 142.52141
A5: VIC | B5: Medical scientist | C5: MS | D5: MSEBA | E5: MS1-4(RX4)-MS4-5(RZ7) | F5: skewed normal | G5: pp111 VPHS 2017-21 RX1-RZ7 | H5: 1131.30-2622.00 | I5: 2023 | J5: 0.105 | K5: 38 | L5: 1 | M5: 0.1 | N5: 0.035 | O5: 0 | P5: 0 | Q5: 0.046 | R5: 0 | S5: 5 | T5: 0.175 | U5: 0.015 | V5: =1177*52 -> 61204 | W5: =V5+((X5-V5)/2) -> 101878.4 | X5: =2741.4*52 -> 142552.8 | Y5: =(V5+(V5*$J5)+(V5*$M5)+(V5*$N5)+(V5*$O5)+(V5*$P5)+(V5*$Q5)+($R5)+(V5*((52+$S5)/52))*(1+$T5))*1/$L5 -> 157537.92 | Z5: =(W5+(W5*$J5)+(W5*$M5)+(W5*$N5)+(W5*$O5)+(W5*$P5)+(W5*$Q5)+($R5)+(W5*((52+$S5)/52))*(1+$T5))*1/$L5 -> 262233.04 | AA5: =(X5+(X5*$J5)+(X5*$M5)+(X5*$N5)+(X5*$O5)+(X5*$P5)+(X5*$Q5)+($R5)+(X5*((52+$S5)/52))*(1+$T5))*1/$L5 -> 366928.17 | AB5: =Y5/52/$K5 -> 79.725668 | AC5: =Z5/52/$K5 -> 132.70903 | AD5: =AA5/52/$K5 -> 185.69239 | AE5: =($V5*(1+(($U5/100)*1))) -> 61213.181 | AF5: =($W5*(1+(($U5/100)*1))) -> 101893.68 | AG5: =($X5*(1+(($U5/100)*1))) -> 142574.18 | AH5: =(AE5+(AE5*$J5)+(AE5*$M5)+(AE5*$N5)+(AE5*$O5)+(AE5*$P5)+(AE5*$Q5)+($R5)+(AE5*((52+$S5)/52))*(1+$T5))*1/$L5 -> 157561.55 | AI5: =(AF5+(AF5*$J5)+(AF5*$M5)+(AF5*$N5)+(AF5*$O5)+(AF5*$P5)+(AF5*$Q5)+($R5)+(AF5*((52+$S5)/52))*(1+$T5))*1/$L5 -> 262272.38 | AJ5: =(AG5+(AG5*$J5)+(AG5*$M5)+(AG5*$N5)+(AG5*$O5)+(AG5*$P5)+(AG5*$Q5)+($R5)+(AG5*((52+$S5)/52))*(1+$T5))*1/$L5 -> 366983.21 | AK5: =AH5/52/$K5 -> 79.737626 | AL5: =AI5/52/$K5 -> 132.72894 | AM5: =AJ5/52/$K5 -> 185.72025 | AN5: =($V5*(1+(($U5/100)*2))) -> 61222.361 | AO5: =($W5*(1+(($U5/100)*2))) -> 101908.96 | AP5: =($X5*(1+(($U5/100)*2))) -> 142595.57 | AQ5: =(AN5+(AN5*$J5)+(AN5*$M5)+(AN5*$N5)+(AN5*$O5)+(AN5*$P5)+(AN5*$Q5)+($R5)+(AN5*((52+$S5)/52))*(1+$T5))*1/$L5 -> 157585.18 | AR5: =(AO5+(AO5*$J5)+(AO5*$M5)+(AO5*$N5)+(AO5*$O5)+(AO5*$P5)+(AO5*$Q5)+($R5)+(AO5*((52+$S5)/52))*(1+$T5))*1/$L5 -> 262311.71 | AS5: =(AP5+(AP5*$J5)+(AP5*$M5)+(AP5*$N5)+(AP5*$O5)+(AP5*$P5)+(AP5*$Q5)+($R5)+(AP5*((52+$S5)/52))*(1+$T5))*1/$L5 -> 367038.24 | AT5: =AQ5/52/$K5 -> 79.749585 | AU5: =AR5/52/$K5 -> 132.74884 | AV5: =AS5/52/$K5 -> 185.7481 | AW5: =($V5*(1+(($U5/100)*3))) -> 61231.542 | AX5: =($W5*(1+(($U5/100)*3))) -> 101924.25 | AY5: =($X5*(1+(($U5/100)*3))) -> 142616.95 | AZ5: =(AW5+(AW5*$J5)+(AW5*$M5)+(AW5*$N5)+(AW5*$O5)+(AW5*$P5)+(AW5*$Q5)+($R5)+(AW5*((52+$S5)/52))*(1+$T5))*1/$L5 -> 157608.81 | BA5: =(AX5+(AX5*$J5)+(AX5*$M5)+(AX5*$N5)+(AX5*$O5)+(AX5*$P5)+(AX5*$Q5)+($R5)+(AX5*((52+$S5)/52))*(1+$T5))*1/$L5 -> 262351.05 | BB5: =(AY5+(AY5*$J5)+(AY5*$M5)+(AY5*$N5)+(AY5*$O5)+(AY5*$P5)+(AY5*$Q5)+($R5)+(AY5*((52+$S5)/52))*(1+$T5))*1/$L5 -> 367093.28 | BC5: =AZ5/52/$K5 -> 79.761544 | BD5: =BA5/52/$K5 -> 132.76875 | BE5: =BB5/52/$K5 -> 185.77595 | BF5: =($V5*(1+(($U5/100)*4))) -> 61240.722 | BG5: =($W5*(1+(($U5/100)*4))) -> 101939.53 | BH5: =($X5*(1+(($U5/100)*4))) -> 142638.33 | BI5: =(BF5+(BF5*$J5)+(BF5*$M5)+(BF5*$N5)+(BF5*$O5)+(BF5*$P5)+(BF5*$Q5)+($R5)+(BF5*((52+$S5)/52))*(1+$T5))*1/$L5 -> 157632.44 | BJ5: =(BG5+(BG5*$J5)+(BG5*$M5)+(BG5*$N5)+(BG5*$O5)+(BG5*$P5)+(BG5*$Q5)+($R5)+(BG5*((52+$S5)/52))*(1+$T5))*1/$L5 -> 262390.38 | BK5: =(BH5+(BH5*$J5)+(BH5*$M5)+(BH5*$N5)+(BH5*$O5)+(BH5*$P5)+(BH5*$Q5)+($R5)+(BH5*((52+$S5)/52))*(1+$T5))*1/$L5 -> 367148.32 | BL5: =BI5/52/$K5 -> 79.773503 | BM5: =BJ5/52/$K5 -> 132.78865 | BN5: =BK5/52/$K5 -> 185.80381
A6: VIC | B6: Admin staff | C6: AS | D6: HPA | E6: 3-5 | G6: pp247 HS5-HS7 (July 22) | H6: 1785.7-2257.10 | I6: 2022 | J6: 0.105 | K6: 38 | L6: 1 | M6: 0.1 | N6: 0.035 | O6: 0 | P6: 0 | Q6: 0.046 | R6: 0 | S6: 4 | T6: 0.175 | U6: 0.015 | V6: 63701 | W6: =V6+((X6-V6)/2) -> 77580.5 | X6: 91460 | Y6: =(V6+(V6*$J6)+(V6*$M6)+(V6*$N6)+(V6*$O6)+(V6*$P6)+(V6*$Q6)+($R6)+(V6*((52+$S6)/52))*(1+$T6))*1/$L6 -> 162525.75 | Z6: =(W6+(W6*$J6)+(W6*$M6)+(W6*$N6)+(W6*$O6)+(W6*$P6)+(W6*$Q6)+($R6)+(W6*((52+$S6)/52))*(1+$T6))*1/$L6 -> 197937.69 | AA6: =(X6+(X6*$J6)+(X6*$M6)+(X6*$N6)+(X6*$O6)+(X6*$P6)+(X6*$Q6)+($R6)+(X6*((52+$S6)/52))*(1+$T6))*1/$L6 -> 233349.64 | AB6: =Y6/52/$K6 -> 82.249874 | AC6: =Z6/52/$K6 -> 100.1709 | AD6: =AA6/52/$K6 -> 118.09192 | AE6: =($V6*(1+(($U6/100)*1))) -> 63710.555 | AF6: =($W6*(1+(($U6/100)*1))) -> 77592.137 | AG6: =($X6*(1+(($U6/100)*1))) -> 91473.719 | AH6: =(AE6+(AE6*$J6)+(AE6*$M6)+(AE6*$N6)+(AE6*$O6)+(AE6*$P6)+(AE6*$Q6)+($R6)+(AE6*((52+$S6)/52))*(1+$T6))*1/$L6 -> 162550.13 | AI6: =(AF6+(AF6*$J6)+(AF6*$M6)+(AF6*$N6)+(AF6*$O6)+(AF6*$P6)+(AF6*$Q6)+($R6)+(AF6*((52+$S6)/52))*(1+$T6))*1/$L6 -> 197967.38 | AJ6: =(AG6+(AG6*$J6)+(AG6*$M6)+(AG6*$N6)+(AG6*$O6)+(AG6*$P6)+(AG6*$Q6)+($R6)+(AG6*((52+$S6)/52))*(1+$T6))*1/$L6 -> 233384.64 | AK6: =AH6/52/$K6 -> 82.262212 | AL6: =AI6/52/$K6 -> 100.18592 | AM6: =AJ6/52/$K6 -> 118.10964 | AN6: =($V6*(1+(($U6/100)*2))) -> 63720.11 | AO6: =($W6*(1+(($U6/100)*2))) -> 77603.774 | AP6: =($X6*(1+(($U6/100)*2))) -> 91487.438 | AQ6: =(AN6+(AN6*$J6)+(AN6*$M6)+(AN6*$N6)+(AN6*$O6)+(AN6*$P6)+(AN6*$Q6)+($R6)+(AN6*((52+$S6)/52))*(1+$T6))*1/$L6 -> 162574.51 | AR6: =(AO6+(AO6*$J6)+(AO6*$M6)+(AO6*$N6)+(AO6*$O6)+(AO6*$P6)+(AO6*$Q6)+($R6)+(AO6*((52+$S6)/52))*(1+$T6))*1/$L6 -> 197997.08 | AS6: =(AP6+(AP6*$J6)+(AP6*$M6)+(AP6*$N6)+(AP6*$O6)+(AP6*$P6)+(AP6*$Q6)+($R6)+(AP6*((52+$S6)/52))*(1+$T6))*1/$L6 -> 233419.64 | AT6: =AQ6/52/$K6 -> 82.274549 | AU6: =AR6/52/$K6 -> 100.20095 | AV6: =AS6/52/$K6 -> 118.12735 | AW6: =($V6*(1+(($U6/100)*3))) -> 63729.665 | AX6: =($W6*(1+(($U6/100)*3))) -> 77615.411 | AY6: =($X6*(1+(($U6/100)*3))) -> 91501.157 | AZ6: =(AW6+(AW6*$J6)+(AW6*$M6)+(AW6*$N6)+(AW6*$O6)+(AW6*$P6)+(AW6*$Q6)+($R6)+(AW6*((52+$S6)/52))*(1+$T6))*1/$L6 -> 162598.89 | BA6: =(AX6+(AX6*$J6)+(AX6*$M6)+(AX6*$N6)+(AX6*$O6)+(AX6*$P6)+(AX6*$Q6)+($R6)+(AX6*((52+$S6)/52))*(1+$T6))*1/$L6 -> 198026.77 | BB6: =(AY6+(AY6*$J6)+(AY6*$M6)+(AY6*$N6)+(AY6*$O6)+(AY6*$P6)+(AY6*$Q6)+($R6)+(AY6*((52+$S6)/52))*(1+$T6))*1/$L6 -> 233454.64 | BC6: =AZ6/52/$K6 -> 82.286887 | BD6: =BA6/52/$K6 -> 100.21597 | BE6: =BB6/52/$K6 -> 118.14506 | BF6: =($V6*(1+(($U6/100)*4))) -> 63739.221 | BG6: =($W6*(1+(($U6/100)*4))) -> 77627.048 | BH6: =($X6*(1+(($U6/100)*4))) -> 91514.876 | BI6: =(BF6+(BF6*$J6)+(BF6*$M6)+(BF6*$N6)+(BF6*$O6)+(BF6*$P6)+(BF6*$Q6)+($R6)+(BF6*((52+$S6)/52))*(1+$T6))*1/$L6 -> 162623.27 | BJ6: =(BG6+(BG6*$J6)+(BG6*$M6)+(BG6*$N6)+(BG6*$O6)+(BG6*$P6)+(BG6*$Q6)+($R6)+(BG6*((52+$S6)/52))*(1+$T6))*1/$L6 -> 198056.46 | BK6: =(BH6+(BH6*$J6)+(BH6*$M6)+(BH6*$N6)+(BH6*$O6)+(BH6*$P6)+(BH6*$Q6)+($R6)+(BH6*((52+$S6)/52))*(1+$T6))*1/$L6 -> 233489.65 | BL6: =BI6/52/$K6 -> 82.299224 | BM6: =BJ6/52/$K6 -> 100.231 | BN6: =BK6/52/$K6 -> 118.16278
A7: VIC | B7: Bioinformatics staff | C7: BI | D7: MCRI Professional and Administrative Salaries | E7: 5-8 | G7: pp247 HS5-HS7 (July 22) | H7: 1785.7-2525.90 | I7: 2022 | J7: 0.105 | K7: 38 | L7: 1 | M7: 0.1 | N7: 0.035 | O7: 0 | P7: 0 | Q7: 0.046 | R7: 0 | S7: 4 | T7: 0.175 | U7: 0.015 | V7: 79624 | W7: =V7+((X7-V7)/2) -> 101861 | X7: 124098 | Y7: =(V7+(V7*$J7)+(V7*$M7)+(V7*$N7)+(V7*$O7)+(V7*$P7)+(V7*$Q7)+($R7)+(V7*((52+$S7)/52))*(1+$T7))*1/$L7 -> 203151.45 | Z7: =(W7+(W7*$J7)+(W7*$M7)+(W7*$N7)+(W7*$O7)+(W7*$P7)+(W7*$Q7)+($R7)+(W7*((52+$S7)/52))*(1+$T7))*1/$L7 -> 259886.59 | AA7: =(X7+(X7*$J7)+(X7*$M7)+(X7*$N7)+(X7*$O7)+(X7*$P7)+(X7*$Q7)+($R7)+(X7*((52+$S7)/52))*(1+$T7))*1/$L7 -> 316621.73 | AB7: =Y7/52/$K7 -> 102.80944 | AC7: =Z7/52/$K7 -> 131.52155 | AD7: =AA7/52/$K7 -> 160.23367 | AE7: =($V7*(1+(($U7/100)*1))) -> 79635.944 | AF7: =($W7*(1+(($U7/100)*1))) -> 101876.28 | AG7: =($X7*(1+(($U7/100)*1))) -> 124116.61 | AH7: =(AE7+(AE7*$J7)+(AE7*$M7)+(AE7*$N7)+(AE7*$O7)+(AE7*$P7)+(AE7*$Q7)+($R7)+(AE7*((52+$S7)/52))*(1+$T7))*1/$L7 -> 203181.92 | AI7: =(AF7+(AF7*$J7)+(AF7*$M7)+(AF7*$N7)+(AF7*$O7)+(AF7*$P7)+(AF7*$Q7)+($R7)+(AF7*((52+$S7)/52))*(1+$T7))*1/$L7 -> 259925.57 | AJ7: =(AG7+(AG7*$J7)+(AG7*$M7)+(AG7*$N7)+(AG7*$O7)+(AG7*$P7)+(AG7*$Q7)+($R7)+(AG7*((52+$S7)/52))*(1+$T7))*1/$L7 -> 316669.22 | AK7: =AH7/52/$K7 -> 102.82486 | AL7: =AI7/52/$K7 -> 131.54128 | AM7: =AJ7/52/$K7 -> 160.2577 | AN7: =($V7*(1+(($U7/100)*2))) -> 79647.887 | AO7: =($W7*(1+(($U7/100)*2))) -> 101891.56 | AP7: =($X7*(1+(($U7/100)*2))) -> 124135.23 | AQ7: =(AN7+(AN7*$J7)+(AN7*$M7)+(AN7*$N7)+(AN7*$O7)+(AN7*$P7)+(AN7*$Q7)+($R7)+(AN7*((52+$S7)/52))*(1+$T7))*1/$L7 -> 203212.39 | AR7: =(AO7+(AO7*$J7)+(AO7*$M7)+(AO7*$N7)+(AO7*$O7)+(AO7*$P7)+(AO7*$Q7)+($R7)+(AO7*((52+$S7)/52))*(1+$T7))*1/$L7 -> 259964.55 | AS7: =(AP7+(AP7*$J7)+(AP7*$M7)+(AP7*$N7)+(AP7*$O7)+(AP7*$P7)+(AP7*$Q7)+($R7)+(AP7*((52+$S7)/52))*(1+$T7))*1/$L7 -> 316716.71 | AT7: =AQ7/52/$K7 -> 102.84028 | AU7: =AR7/52/$K7 -> 131.56101 | AV7: =AS7/52/$K7 -> 160.28174 | AW7: =($V7*(1+(($U7/100)*3))) -> 79659.831 | AX7: =($W7*(1+(($U7/100)*3))) -> 101906.84 | AY7: =($X7*(1+(($U7/100)*3))) -> 124153.84 | AZ7: =(AW7+(AW7*$J7)+(AW7*$M7)+(AW7*$N7)+(AW7*$O7)+(AW7*$P7)+(AW7*$Q7)+($R7)+(AW7*((52+$S7)/52))*(1+$T7))*1/$L7 -> 203242.87 | BA7: =(AX7+(AX7*$J7)+(AX7*$M7)+(AX7*$N7)+(AX7*$O7)+(AX7*$P7)+(AX7*$Q7)+($R7)+(AX7*((52+$S7)/52))*(1+$T7))*1/$L7 -> 260003.54 | BB7: =(AY7+(AY7*$J7)+(AY7*$M7)+(AY7*$N7)+(AY7*$O7)+(AY7*$P7)+(AY7*$Q7)+($R7)+(AY7*((52+$S7)/52))*(1+$T7))*1/$L7 -> 316764.21 | BC7: =AZ7/52/$K7 -> 102.8557 | BD7: =BA7/52/$K7 -> 131.58074 | BE7: =BB7/52/$K7 -> 160.30577 | BF7: =($V7*(1+(($U7/100)*4))) -> 79671.774 | BG7: =($W7*(1+(($U7/100)*4))) -> 101922.12 | BH7: =($X7*(1+(($U7/100)*4))) -> 124172.46 | BI7: =(BF7+(BF7*$J7)+(BF7*$M7)+(BF7*$N7)+(BF7*$O7)+(BF7*$P7)+(BF7*$Q7)+($R7)+(BF7*((52+$S7)/52))*(1+$T7))*1/$L7 -> 203273.34 | BJ7: =(BG7+(BG7*$J7)+(BG7*$M7)+(BG7*$N7)+(BG7*$O7)+(BG7*$P7)+(BG7*$Q7)+($R7)+(BG7*((52+$S7)/52))*(1+$T7))*1/$L7 -> 260042.52 | BK7: =(BH7+(BH7*$J7)+(BH7*$M7)+(BH7*$N7)+(BH7*$O7)+(BH7*$P7)+(BH7*$Q7)+($R7)+(BH7*((52+$S7)/52))*(1+$T7))*1/$L7 -> 316811.7 | BL7: =BI7/52/$K7 -> 102.87112 | BM7: =BJ7/52/$K7 -> 131.60047 | BN7: =BK7/52/$K7 -> 160.32981
A8: VIC | B8: Pathologists | C8: MP | D8: MEDICAL SPECIALISTS (VICTORIAN PUBLIC HEALTH SECTOR) (AMA VICTORIA/ASMOF) (SINGLE INTEREST EMPLOYERS) ENTERPRISE AGREEMENT 2022 – 2026 | E8: Assume year 9, full time | F8: rightward skewed | G8: - | H8: 6420.1-7383.20 | I8: 2022 | J8: 0.105 | K8: 38 | L8: 1 | M8: 0 | N8: 0.035 | O8: 0 | P8: 0 | Q8: 0.046 | R8: 29000.16 | S8: 4 | T8: 0.175 | U8: 0.015 | V8: =4797.5*52 -> 249470 | W8: =V8+((X8-V8)/2) -> 296247.9 | X8: =6596.65*52 -> 343025.8 | Y8: =(V8+(V8*$J8)+(V8*$M8)+(V8*$N8)+(V8*$O8)+(V8*$P8)+(V8*$Q8)+($R8)+(V8*((52+$S8)/52))*(1+$T8))*1/$L8 -> 640547.08 | Z8: =(W8+(W8*$J8)+(W8*$M8)+(W8*$N8)+(W8*$O8)+(W8*$P8)+(W8*$Q8)+($R8)+(W8*((52+$S8)/52))*(1+$T8))*1/$L8 -> 755217.7 | AA8: =(X8+(X8*$J8)+(X8*$M8)+(X8*$N8)+(X8*$O8)+(X8*$P8)+(X8*$Q8)+($R8)+(X8*((52+$S8)/52))*(1+$T8))*1/$L8 -> 869888.33 | AB8: =Y8/52/$K8 -> 324.1635 | AC8: =Z8/52/$K8 -> 382.19519 | AD8: =AA8/52/$K8 -> 440.22689 | AE8: =($V8*(1+(($U8/100)*1))) -> 249507.42 | AF8: =($W8*(1+(($U8/100)*1))) -> 296292.34 | AG8: =($X8*(1+(($U8/100)*1))) -> 343077.25 | AH8: =(AE8+(AE8*$J8)+(AE8*$M8)+(AE8*$N8)+(AE8*$O8)+(AE8*$P8)+(AE8*$Q8)+($R8)+(AE8*((52+$S8)/52))*(1+$T8))*1/$L8 -> 640638.81 | AI8: =(AF8+(AF8*$J8)+(AF8*$M8)+(AF8*$N8)+(AF8*$O8)+(AF8*$P8)+(AF8*$Q8)+($R8)+(AF8*((52+$S8)/52))*(1+$T8))*1/$L8 -> 755326.64 | AJ8: =(AG8+(AG8*$J8)+(AG8*$M8)+(AG8*$N8)+(AG8*$O8)+(AG8*$P8)+(AG8*$Q8)+($R8)+(AG8*((52+$S8)/52))*(1+$T8))*1/$L8 -> 870014.46 | AK8: =AH8/52/$K8 -> 324.20993 | AL8: =AI8/52/$K8 -> 382.25032 | AM8: =AJ8/52/$K8 -> 440.29072 | AN8: =($V8*(1+(($U8/100)*2))) -> 249544.84 | AO8: =($W8*(1+(($U8/100)*2))) -> 296336.77 | AP8: =($X8*(1+(($U8/100)*2))) -> 343128.71 | AQ8: =(AN8+(AN8*$J8)+(AN8*$M8)+(AN8*$N8)+(AN8*$O8)+(AN8*$P8)+(AN8*$Q8)+($R8)+(AN8*((52+$S8)/52))*(1+$T8))*1/$L8 -> 640730.54 | AR8: =(AO8+(AO8*$J8)+(AO8*$M8)+(AO8*$N8)+(AO8*$O8)+(AO8*$P8)+(AO8*$Q8)+($R8)+(AO8*((52+$S8)/52))*(1+$T8))*1/$L8 -> 755435.57 | AS8: =(AP8+(AP8*$J8)+(AP8*$M8)+(AP8*$N8)+(AP8*$O8)+(AP8*$P8)+(AP8*$Q8)+($R8)+(AP8*((52+$S8)/52))*(1+$T8))*1/$L8 -> 870140.6 | AT8: =AQ8/52/$K8 -> 324.25635 | AU8: =AR8/52/$K8 -> 382.30545 | AV8: =AS8/52/$K8 -> 440.35455 | AW8: =($V8*(1+(($U8/100)*3))) -> 249582.26 | AX8: =($W8*(1+(($U8/100)*3))) -> 296381.21 | AY8: =($X8*(1+(($U8/100)*3))) -> 343180.16 | AZ8: =(AW8+(AW8*$J8)+(AW8*$M8)+(AW8*$N8)+(AW8*$O8)+(AW8*$P8)+(AW8*$Q8)+($R8)+(AW8*((52+$S8)/52))*(1+$T8))*1/$L8 -> 640822.28 | BA8: =(AX8+(AX8*$J8)+(AX8*$M8)+(AX8*$N8)+(AX8*$O8)+(AX8*$P8)+(AX8*$Q8)+($R8)+(AX8*((52+$S8)/52))*(1+$T8))*1/$L8 -> 755544.5 | BB8: =(AY8+(AY8*$J8)+(AY8*$M8)+(AY8*$N8)+(AY8*$O8)+(AY8*$P8)+(AY8*$Q8)+($R8)+(AY8*((52+$S8)/52))*(1+$T8))*1/$L8 -> 870266.73 | BC8: =AZ8/52/$K8 -> 324.30277 | BD8: =BA8/52/$K8 -> 382.36058 | BE8: =BB8/52/$K8 -> 440.41838 | BF8: =($V8*(1+(($U8/100)*4))) -> 249619.68 | BG8: =($W8*(1+(($U8/100)*4))) -> 296425.65 | BH8: =($X8*(1+(($U8/100)*4))) -> 343231.62 | BI8: =(BF8+(BF8*$J8)+(BF8*$M8)+(BF8*$N8)+(BF8*$O8)+(BF8*$P8)+(BF8*$Q8)+($R8)+(BF8*((52+$S8)/52))*(1+$T8))*1/$L8 -> 640914.01 | BJ8: =(BG8+(BG8*$J8)+(BG8*$M8)+(BG8*$N8)+(BG8*$O8)+(BG8*$P8)+(BG8*$Q8)+($R8)+(BG8*((52+$S8)/52))*(1+$T8))*1/$L8 -> 755653.43 | BK8: =(BH8+(BH8*$J8)+(BH8*$M8)+(BH8*$N8)+(BH8*$O8)+(BH8*$P8)+(BH8*$Q8)+($R8)+(BH8*((52+$S8)/52))*(1+$T8))*1/$L8 -> 870392.86 | BL8: =BI8/52/$K8 -> 324.34919 | BM8: =BJ8/52/$K8 -> 382.41571 | BN8: =BK8/52/$K8 -> 440.48222
A10: SA | B10: Lab technician | C10: LT | D10: S.A. PUBLIC SECTOR SALARIED EMPLOYEES INTERIM AWARD | E10: TG0-1 - TGO-3 | G10: SA Health Costing Table | I10: 2022 | J10: 0.105 | K10: 37.5 | L10: 1 | M10: 0.1 | N10: 0.035 | O10: 0 | P10: 0 | Q10: 0.046 | R10: 0 | S10: 4 | T10: 0 | U10: 0.015 | V10: 54364 | W10: =V10+((X10-V10)/2) -> 77673 | X10: 100982 | Y10: =(V10+(V10*$J10)+(V10*$M10)+(V10*$N10)+(V10*$O10)+(V10*$P10)+(V10*$Q10)+($R10)+(V10*((52+$S10)/52))*(1+$T10))*1/$L10 -> 128457.95 | Z10: =(W10+(W10*$J10)+(W10*$M10)+(W10*$N10)+(W10*$O10)+(W10*$P10)+(W10*$Q10)+($R10)+(W10*((52+$S10)/52))*(1+$T10))*1/$L10 -> 183535.32 | AA10: =(X10+(X10*$J10)+(X10*$M10)+(X10*$N10)+(X10*$O10)+(X10*$P10)+(X10*$Q10)+($R10)+(X10*((52+$S10)/52))*(1+$T10))*1/$L10 -> 238612.7 | AB10: =Y10/52/$K10 -> 65.875872 | AC10: =Z10/52/$K10 -> 94.120679 | AD10: =AA10/52/$K10 -> 122.36549 | AE10: =($V10*(1+(($U10/100)*1))) -> 54372.155 | AF10: =($W10*(1+(($U10/100)*1))) -> 77684.651 | AG10: =($X10*(1+(($U10/100)*1))) -> 100997.15 | AH10: =(AE10+(AE10*$J10)+(AE10*$M10)+(AE10*$N10)+(AE10*$O10)+(AE10*$P10)+(AE10*$Q10)+($R10)+(AE10*((52+$S10)/52))*(1+$T10))*1/$L10 -> 128477.22 | AI10: =(AF10+(AF10*$J10)+(AF10*$M10)+(AF10*$N10)+(AF10*$O10)+(AF10*$P10)+(AF10*$Q10)+($R10)+(AF10*((52+$S10)/52))*(1+$T10))*1/$L10 -> 183562.85 | AJ10: =(AG10+(AG10*$J10)+(AG10*$M10)+(AG10*$N10)+(AG10*$O10)+(AG10*$P10)+(AG10*$Q10)+($R10)+(AG10*((52+$S10)/52))*(1+$T10))*1/$L10 -> 238648.49 | AK10: =AH10/52/$K10 -> 65.885753 | AL10: =AI10/52/$K10 -> 94.134797 | AM10: =AJ10/52/$K10 -> 122.38384 | AN10: =($V10*(1+(($U10/100)*2))) -> 54380.309 | AO10: =($W10*(1+(($U10/100)*2))) -> 77696.302 | AP10: =($X10*(1+(($U10/100)*2))) -> 101012.29 | AQ10: =(AN10+(AN10*$J10)+(AN10*$M10)+(AN10*$N10)+(AN10*$O10)+(AN10*$P10)+(AN10*$Q10)+($R10)+(AN10*((52+$S10)/52))*(1+$T10))*1/$L10 -> 128496.49 | AR10: =(AO10+(AO10*$J10)+(AO10*$M10)+(AO10*$N10)+(AO10*$O10)+(AO10*$P10)+(AO10*$Q10)+($R10)+(AO10*((52+$S10)/52))*(1+$T10))*1/$L10 -> 183590.38 | AS10: =(AP10+(AP10*$J10)+(AP10*$M10)+(AP10*$N10)+(AP10*$O10)+(AP10*$P10)+(AP10*$Q10)+($R10)+(AP10*((52+$S10)/52))*(1+$T10))*1/$L10 -> 238684.28 | AT10: =AQ10/52/$K10 -> 65.895635 | AU10: =AR10/52/$K10 -> 94.148915 | AV10: =AS10/52/$K10 -> 122.4022 | AW10: =($V10*(1+(($U10/100)*3))) -> 54388.464 | AX10: =($W10*(1+(($U10/100)*3))) -> 77707.953 | AY10: =($X10*(1+(($U10/100)*3))) -> 101027.44 | AZ10: =(AW10+(AW10*$J10)+(AW10*$M10)+(AW10*$N10)+(AW10*$O10)+(AW10*$P10)+(AW10*$Q10)+($R10)+(AW10*((52+$S10)/52))*(1+$T10))*1/$L10 -> 128515.76 | BA10: =(AX10+(AX10*$J10)+(AX10*$M10)+(AX10*$N10)+(AX10*$O10)+(AX10*$P10)+(AX10*$Q10)+($R10)+(AX10*((52+$S10)/52))*(1+$T10))*1/$L10 -> 183617.92 | BB10: =(AY10+(AY10*$J10)+(AY10*$M10)+(AY10*$N10)+(AY10*$O10)+(AY10*$P10)+(AY10*$Q10)+($R10)+(AY10*((52+$S10)/52))*(1+$T10))*1/$L10 -> 238720.07 | BC10: =AZ10/52/$K10 -> 65.905516 | BD10: =BA10/52/$K10 -> 94.163033 | BE10: =BB10/52/$K10 -> 122.42055 | BF10: =($V10*(1+(($U10/100)*4))) -> 54396.618 | BG10: =($W10*(1+(($U10/100)*4))) -> 77719.604 | BH10: =($X10*(1+(($U10/100)*4))) -> 101042.59 | BI10: =(BF10+(BF10*$J10)+(BF10*$M10)+(BF10*$N10)+(BF10*$O10)+(BF10*$P10)+(BF10*$Q10)+($R10)+(BF10*((52+$S10)/52))*(1+$T10))*1/$L10 -> 128535.02 | BJ10: =(BG10+(BG10*$J10)+(BG10*$M10)+(BG10*$N10)+(BG10*$O10)+(BG10*$P10)+(BG10*$Q10)+($R10)+(BG10*((52+$S10)/52))*(1+$T10))*1/$L10 -> 183645.45 | BK10: =(BH10+(BH10*$J10)+(BH10*$M10)+(BH10*$N10)+(BH10*$O10)+(BH10*$P10)+(BH10*$Q10)+($R10)+(BH10*((52+$S10)/52))*(1+$T10))*1/$L10 -> 238755.87 | BL10: =BI10/52/$K10 -> 65.915397 | BM10: =BJ10/52/$K10 -> 94.177151 | BN10: =BK10/52/$K10 -> 122.43891
A11: SA | B11: Medical scientist | C11: MS | D11: MEDICAL SCIENTISTS (SOUTH AUSTRALIAN PUBLIC SECTOR) AWARD | E11: MS1 - MS4 | F11: - | G11: pp38 (Schedule 4, pg 1) | H11: 1145.45-2310.89 | I11: 2022 | J11: 0.105 | K11: 37.5 | L11: 1 | M11: 0.1 | N11: 0.035 | O11: 0 | P11: 0 | Q11: 0.046 | R11: 0 | S11: 5 | T11: 0 | U11: 0.015 | V11: 66386 | W11: =V11+((X11-V11)/2) -> 104238 | X11: 142090 | Y11: =(V11+(V11*$J11)+(V11*$M11)+(V11*$N11)+(V11*$O11)+(V11*$P11)+(V11*$Q11)+($R11)+(V11*((52+$S11)/52))*(1+$T11))*1/$L11 -> 158141.67 | Z11: =(W11+(W11*$J11)+(W11*$M11)+(W11*$N11)+(W11*$O11)+(W11*$P11)+(W11*$Q11)+($R11)+(W11*((52+$S11)/52))*(1+$T11))*1/$L11 -> 248310.95 | AA11: =(X11+(X11*$J11)+(X11*$M11)+(X11*$N11)+(X11*$O11)+(X11*$P11)+(X11*$Q11)+($R11)+(X11*((52+$S11)/52))*(1+$T11))*1/$L11 -> 338480.24 | AB11: =Y11/52/$K11 -> 81.09829 | AC11: =Z11/52/$K11 -> 127.33895 | AD11: =AA11/52/$K11 -> 173.57961 | AE11: =($V11*(1+(($U11/100)*1))) -> 66395.958 | AF11: =($W11*(1+(($U11/100)*1))) -> 104253.64 | AG11: =($X11*(1+(($U11/100)*1))) -> 142111.31 | AH11: =(AE11+(AE11*$J11)+(AE11*$M11)+(AE11*$N11)+(AE11*$O11)+(AE11*$P11)+(AE11*$Q11)+($R11)+(AE11*((52+$S11)/52))*(1+$T11))*1/$L11 -> 158165.39 | AI11: =(AF11+(AF11*$J11)+(AF11*$M11)+(AF11*$N11)+(AF11*$O11)+(AF11*$P11)+(AF11*$Q11)+($R11)+(AF11*((52+$S11)/52))*(1+$T11))*1/$L11 -> 248348.2 | AJ11: =(AG11+(AG11*$J11)+(AG11*$M11)+(AG11*$N11)+(AG11*$O11)+(AG11*$P11)+(AG11*$Q11)+($R11)+(AG11*((52+$S11)/52))*(1+$T11))*1/$L11 -> 338531.01 | AK11: =AH11/52/$K11 -> 81.110455 | AL11: =AI11/52/$K11 -> 127.35805 | AM11: =AJ11/52/$K11 -> 173.60565 | AN11: =($V11*(1+(($U11/100)*2))) -> 66405.916 | AO11: =($W11*(1+(($U11/100)*2))) -> 104269.27 | AP11: =($X11*(1+(($U11/100)*2))) -> 142132.63 | AQ11: =(AN11+(AN11*$J11)+(AN11*$M11)+(AN11*$N11)+(AN11*$O11)+(AN11*$P11)+(AN11*$Q11)+($R11)+(AN11*((52+$S11)/52))*(1+$T11))*1/$L11 -> 158189.11 | AR11: =(AO11+(AO11*$J11)+(AO11*$M11)+(AO11*$N11)+(AO11*$O11)+(AO11*$P11)+(AO11*$Q11)+($R11)+(AO11*((52+$S11)/52))*(1+$T11))*1/$L11 -> 248385.45 | AS11: =(AP11+(AP11*$J11)+(AP11*$M11)+(AP11*$N11)+(AP11*$O11)+(AP11*$P11)+(AP11*$Q11)+($R11)+(AP11*((52+$S11)/52))*(1+$T11))*1/$L11 -> 338581.78 | AT11: =AQ11/52/$K11 -> 81.122619 | AU11: =AR11/52/$K11 -> 127.37715 | AV11: =AS11/52/$K11 -> 173.63168 | AW11: =($V11*(1+(($U11/100)*3))) -> 66415.874 | AX11: =($W11*(1+(($U11/100)*3))) -> 104284.91 | AY11: =($X11*(1+(($U11/100)*3))) -> 142153.94 | AZ11: =(AW11+(AW11*$J11)+(AW11*$M11)+(AW11*$N11)+(AW11*$O11)+(AW11*$P11)+(AW11*$Q11)+($R11)+(AW11*((52+$S11)/52))*(1+$T11))*1/$L11 -> 158212.83 | BA11: =(AX11+(AX11*$J11)+(AX11*$M11)+(AX11*$N11)+(AX11*$O11)+(AX11*$P11)+(AX11*$Q11)+($R11)+(AX11*((52+$S11)/52))*(1+$T11))*1/$L11 -> 248422.69 | BB11: =(AY11+(AY11*$J11)+(AY11*$M11)+(AY11*$N11)+(AY11*$O11)+(AY11*$P11)+(AY11*$Q11)+($R11)+(AY11*((52+$S11)/52))*(1+$T11))*1/$L11 -> 338632.56 | BC11: =AZ11/52/$K11 -> 81.134784 | BD11: =BA11/52/$K11 -> 127.39625 | BE11: =BB11/52/$K11 -> 173.65772 | BF11: =($V11*(1+(($U11/100)*4))) -> 66425.832 | BG11: =($W11*(1+(($U11/100)*4))) -> 104300.54 | BH11: =($X11*(1+(($U11/100)*4))) -> 142175.25 | BI11: =(BF11+(BF11*$J11)+(BF11*$M11)+(BF11*$N11)+(BF11*$O11)+(BF11*$P11)+(BF11*$Q11)+($R11)+(BF11*((52+$S11)/52))*(1+$T11))*1/$L11 -> 158236.55 | BJ11: =(BG11+(BG11*$J11)+(BG11*$M11)+(BG11*$N11)+(BG11*$O11)+(BG11*$P11)+(BG11*$Q11)+($R11)+(BG11*((52+$S11)/52))*(1+$T11))*1/$L11 -> 248459.94 | BK11: =(BH11+(BH11*$J11)+(BH11*$M11)+(BH11*$N11)+(BH11*$O11)+(BH11*$P11)+(BH11*$Q11)+($R11)+(BH11*((52+$S11)/52))*(1+$T11))*1/$L11 -> 338683.33 | BL11: =BI11/52/$K11 -> 81.146949 | BM11: =BJ11/52/$K11 -> 127.41535 | BN11: =BK11/52/$K11 -> 173.68376
A12: SA | B12: Admin staff | C12: AS | D12: S.A. PUBLIC SECTOR SALARIED EMPLOYEES INTERIM AWARD | E12: ASO2-1 - ASO3-3 | I12: 2022 | J12: 0.105 | K12: 37.5 | L12: 1 | M12: 0.1 | N12: 0.035 | O12: 0 | P12: 0 | Q12: 0.046 | R12: 0 | S12: 4 | T12: 0 | U12: 0.015 | V12: 56916 | W12: =V12+((X12-V12)/2) -> 63374 | X12: 69832 | Y12: =(V12+(V12*$J12)+(V12*$M12)+(V12*$N12)+(V12*$O12)+(V12*$P12)+(V12*$Q12)+($R12)+(V12*((52+$S12)/52))*(1+$T12))*1/$L12 -> 134488.13 | Z12: =(W12+(W12*$J12)+(W12*$M12)+(W12*$N12)+(W12*$O12)+(W12*$P12)+(W12*$Q12)+($R12)+(W12*((52+$S12)/52))*(1+$T12))*1/$L12 -> 149747.89 | AA12: =(X12+(X12*$J12)+(X12*$M12)+(X12*$N12)+(X12*$O12)+(X12*$P12)+(X12*$Q12)+($R12)+(X12*((52+$S12)/52))*(1+$T12))*1/$L12 -> 165007.64 | AB12: =Y12/52/$K12 -> 68.968272 | AC12: =Z12/52/$K12 -> 76.793788 | AD12: =AA12/52/$K12 -> 84.619305 | AE12: =($V12*(1+(($U12/100)*1))) -> 56924.537 | AF12: =($W12*(1+(($U12/100)*1))) -> 63383.506 | AG12: =($X12*(1+(($U12/100)*1))) -> 69842.475 | AH12: =(AE12+(AE12*$J12)+(AE12*$M12)+(AE12*$N12)+(AE12*$O12)+(AE12*$P12)+(AE12*$Q12)+($R12)+(AE12*((52+$S12)/52))*(1+$T12))*1/$L12 -> 134508.3 | AI12: =(AF12+(AF12*$J12)+(AF12*$M12)+(AF12*$N12)+(AF12*$O12)+(AF12*$P12)+(AF12*$Q12)+($R12)+(AF12*((52+$S12)/52))*(1+$T12))*1/$L12 -> 149770.35 | AJ12: =(AG12+(AG12*$J12)+(AG12*$M12)+(AG12*$N12)+(AG12*$O12)+(AG12*$P12)+(AG12*$Q12)+($R12)+(AG12*((52+$S12)/52))*(1+$T12))*1/$L12 -> 165032.4 | AK12: =AH12/52/$K12 -> 68.978617 | AL12: =AI12/52/$K12 -> 76.805307 | AM12: =AJ12/52/$K12 -> 84.631998 | AN12: =($V12*(1+(($U12/100)*2))) -> 56933.075 | AO12: =($W12*(1+(($U12/100)*2))) -> 63393.012 | AP12: =($X12*(1+(($U12/100)*2))) -> 69852.95 | AQ12: =(AN12+(AN12*$J12)+(AN12*$M12)+(AN12*$N12)+(AN12*$O12)+(AN12*$P12)+(AN12*$Q12)+($R12)+(AN12*((52+$S12)/52))*(1+$T12))*1/$L12 -> 134528.48 | AR12: =(AO12+(AO12*$J12)+(AO12*$M12)+(AO12*$N12)+(AO12*$O12)+(AO12*$P12)+(AO12*$Q12)+($R12)+(AO12*((52+$S12)/52))*(1+$T12))*1/$L12 -> 149792.81 | AS12: =(AP12+(AP12*$J12)+(AP12*$M12)+(AP12*$N12)+(AP12*$O12)+(AP12*$P12)+(AP12*$Q12)+($R12)+(AP12*((52+$S12)/52))*(1+$T12))*1/$L12 -> 165057.15 | AT12: =AQ12/52/$K12 -> 68.988962 | AU12: =AR12/52/$K12 -> 76.816826 | AV12: =AS12/52/$K12 -> 84.644691 | AW12: =($V12*(1+(($U12/100)*3))) -> 56941.612 | AX12: =($W12*(1+(($U12/100)*3))) -> 63402.518 | AY12: =($X12*(1+(($U12/100)*3))) -> 69863.424 | AZ12: =(AW12+(AW12*$J12)+(AW12*$M12)+(AW12*$N12)+(AW12*$O12)+(AW12*$P12)+(AW12*$Q12)+($R12)+(AW12*((52+$S12)/52))*(1+$T12))*1/$L12 -> 134548.65 | BA12: =(AX12+(AX12*$J12)+(AX12*$M12)+(AX12*$N12)+(AX12*$O12)+(AX12*$P12)+(AX12*$Q12)+($R12)+(AX12*((52+$S12)/52))*(1+$T12))*1/$L12 -> 149815.27 | BB12: =(AY12+(AY12*$J12)+(AY12*$M12)+(AY12*$N12)+(AY12*$O12)+(AY12*$P12)+(AY12*$Q12)+($R12)+(AY12*((52+$S12)/52))*(1+$T12))*1/$L12 -> 165081.9 | BC12: =AZ12/52/$K12 -> 68.999307 | BD12: =BA12/52/$K12 -> 76.828345 | BE12: =BB12/52/$K12 -> 84.657383 | BF12: =($V12*(1+(($U12/100)*4))) -> 56950.15 | BG12: =($W12*(1+(($U12/100)*4))) -> 63412.024 | BH12: =($X12*(1+(($U12/100)*4))) -> 69873.899 | BI12: =(BF12+(BF12*$J12)+(BF12*$M12)+(BF12*$N12)+(BF12*$O12)+(BF12*$P12)+(BF12*$Q12)+($R12)+(BF12*((52+$S12)/52))*(1+$T12))*1/$L12 -> 134568.82 | BJ12: =(BG12+(BG12*$J12)+(BG12*$M12)+(BG12*$N12)+(BG12*$O12)+(BG12*$P12)+(BG12*$Q12)+($R12)+(BG12*((52+$S12)/52))*(1+$T12))*1/$L12 -> 149837.74 | BK12: =(BH12+(BH12*$J12)+(BH12*$M12)+(BH12*$N12)+(BH12*$O12)+(BH12*$P12)+(BH12*$Q12)+($R12)+(BH12*((52+$S12)/52))*(1+$T12))*1/$L12 -> 165106.65 | BL12: =BI12/52/$K12 -> 69.009653 | BM12: =BJ12/52/$K12 -> 76.839865 | BN12: =BK12/52/$K12 -> 84.670076
A13: SA | B13: Bioinformatics staff | C13: BI | D13: S.A. PUBLIC SECTOR SALARIED EMPLOYEES INTERIM AWARD | E13: PO-1 - PO-4 | I13: 2022 | J13: 0.105 | K13: 37.5 | L13: 1 | M13: 0.1 | N13: 0.035 | O13: 0 | P13: 0 | Q13: 0.046 | R13: 0 | S13: 4 | T13: 0 | U13: 0.015 | V13: 66386 | W13: =V13+((X13-V13)/2) -> 91587.5 | X13: 116789 | Y13: =(V13+(V13*$J13)+(V13*$M13)+(V13*$N13)+(V13*$O13)+(V13*$P13)+(V13*$Q13)+($R13)+(V13*((52+$S13)/52))*(1+$T13))*1/$L13 -> 156865.01 | Z13: =(W13+(W13*$J13)+(W13*$M13)+(W13*$N13)+(W13*$O13)+(W13*$P13)+(W13*$Q13)+($R13)+(W13*((52+$S13)/52))*(1+$T13))*1/$L13 -> 216414.22 | AA13: =(X13+(X13*$J13)+(X13*$M13)+(X13*$N13)+(X13*$O13)+(X13*$P13)+(X13*$Q13)+($R13)+(X13*((52+$S13)/52))*(1+$T13))*1/$L13 -> 275963.42 | AB13: =Y13/52/$K13 -> 80.443596 | AC13: =Z13/52/$K13 -> 110.98165 | AD13: =AA13/52/$K13 -> 141.5197 | AE13: =($V13*(1+(($U13/100)*1))) -> 66395.958 | AF13: =($W13*(1+(($U13/100)*1))) -> 91601.238 | AG13: =($X13*(1+(($U13/100)*1))) -> 116806.52 | AH13: =(AE13+(AE13*$J13)+(AE13*$M13)+(AE13*$N13)+(AE13*$O13)+(AE13*$P13)+(AE13*$Q13)+($R13)+(AE13*((52+$S13)/52))*(1+$T13))*1/$L13 -> 156888.54 | AI13: =(AF13+(AF13*$J13)+(AF13*$M13)+(AF13*$N13)+(AF13*$O13)+(AF13*$P13)+(AF13*$Q13)+($R13)+(AF13*((52+$S13)/52))*(1+$T13))*1/$L13 -> 216446.68 | AJ13: =(AG13+(AG13*$J13)+(AG13*$M13)+(AG13*$N13)+(AG13*$O13)+(AG13*$P13)+(AG13*$Q13)+($R13)+(AG13*((52+$S13)/52))*(1+$T13))*1/$L13 -> 276004.82 | AK13: =AH13/52/$K13 -> 80.455662 | AL13: =AI13/52/$K13 -> 110.9983 | AM13: =AJ13/52/$K13 -> 141.54093 | AN13: =($V13*(1+(($U13/100)*2))) -> 66405.916 | AO13: =($W13*(1+(($U13/100)*2))) -> 91614.976 | AP13: =($X13*(1+(($U13/100)*2))) -> 116824.04 | AQ13: =(AN13+(AN13*$J13)+(AN13*$M13)+(AN13*$N13)+(AN13*$O13)+(AN13*$P13)+(AN13*$Q13)+($R13)+(AN13*((52+$S13)/52))*(1+$T13))*1/$L13 -> 156912.07 | AR13: =(AO13+(AO13*$J13)+(AO13*$M13)+(AO13*$N13)+(AO13*$O13)+(AO13*$P13)+(AO13*$Q13)+($R13)+(AO13*((52+$S13)/52))*(1+$T13))*1/$L13 -> 216479.14 | AS13: =(AP13+(AP13*$J13)+(AP13*$M13)+(AP13*$N13)+(AP13*$O13)+(AP13*$P13)+(AP13*$Q13)+($R13)+(AP13*((52+$S13)/52))*(1+$T13))*1/$L13 -> 276046.21 | AT13: =AQ13/52/$K13 -> 80.467729 | AU13: =AR13/52/$K13 -> 111.01494 | AV13: =AS13/52/$K13 -> 141.56216 | AW13: =($V13*(1+(($U13/100)*3))) -> 66415.874 | AX13: =($W13*(1+(($U13/100)*3))) -> 91628.714 | AY13: =($X13*(1+(($U13/100)*3))) -> 116841.56 | AZ13: =(AW13+(AW13*$J13)+(AW13*$M13)+(AW13*$N13)+(AW13*$O13)+(AW13*$P13)+(AW13*$Q13)+($R13)+(AW13*((52+$S13)/52))*(1+$T13))*1/$L13 -> 156935.6 | BA13: =(AX13+(AX13*$J13)+(AX13*$M13)+(AX13*$N13)+(AX13*$O13)+(AX13*$P13)+(AX13*$Q13)+($R13)+(AX13*((52+$S13)/52))*(1+$T13))*1/$L13 -> 216511.6 | BB13: =(AY13+(AY13*$J13)+(AY13*$M13)+(AY13*$N13)+(AY13*$O13)+(AY13*$P13)+(AY13*$Q13)+($R13)+(AY13*((52+$S13)/52))*(1+$T13))*1/$L13 -> 276087.61 | BC13: =AZ13/52/$K13 -> 80.479795 | BD13: =BA13/52/$K13 -> 111.03159 | BE13: =BB13/52/$K13 -> 141.58339 | BF13: =($V13*(1+(($U13/100)*4))) -> 66425.832 | BG13: =($W13*(1+(($U13/100)*4))) -> 91642.452 | BH13: =($X13*(1+(($U13/100)*4))) -> 116859.07 | BI13: =(BF13+(BF13*$J13)+(BF13*$M13)+(BF13*$N13)+(BF13*$O13)+(BF13*$P13)+(BF13*$Q13)+($R13)+(BF13*((52+$S13)/52))*(1+$T13))*1/$L13 -> 156959.13 | BJ13: =(BG13+(BG13*$J13)+(BG13*$M13)+(BG13*$N13)+(BG13*$O13)+(BG13*$P13)+(BG13*$Q13)+($R13)+(BG13*((52+$S13)/52))*(1+$T13))*1/$L13 -> 216544.07 | BK13: =(BH13+(BH13*$J13)+(BH13*$M13)+(BH13*$N13)+(BH13*$O13)+(BH13*$P13)+(BH13*$Q13)+($R13)+(BH13*((52+$S13)/52))*(1+$T13))*1/$L13 -> 276129 | BL13: =BI13/52/$K13 -> 80.491862 | BM13: =BJ13/52/$K13 -> 111.04824 | BN13: =BK13/52/$K13 -> 141.60462
A14: SA | B14: Pathologists | C14: MP | D14: SA Health Salaried Medical Officers Enterprise Agreement 2022 | E14: MD0201 - MD029G | I14: 2022 | J14: 0.105 | K14: 38 | L14: 1 | M14: 0 | N14: 0.035 | O14: 0 | P14: 0.6 | Q14: 0.046 | R14: 26000 | S14: 5 | T14: 0.175 | U14: 0.015 | V14: 221622 | W14: =V14+((X14-V14)/2) -> 256820.5 | X14: 292019 | Y14: =(V14+(V14*$J14)+(V14*$M14)+(V14*$N14)+(V14*$O14)+(V14*$P14)+(V14*$Q14)+($R14)+(V14*((52+$S14)/52))*(1+$T14))*1/$L14 -> 707261.77 | Z14: =(W14+(W14*$J14)+(W14*$M14)+(W14*$N14)+(W14*$O14)+(W14*$P14)+(W14*$Q14)+($R14)+(W14*((52+$S14)/52))*(1+$T14))*1/$L14 -> 815461.28 | AA14: =(X14+(X14*$J14)+(X14*$M14)+(X14*$N14)+(X14*$O14)+(X14*$P14)+(X14*$Q14)+($R14)+(X14*((52+$S14)/52))*(1+$T14))*1/$L14 -> 923660.79 | AB14: =Y14/52/$K14 -> 357.92599 | AC14: =Z14/52/$K14 -> 412.68283 | AD14: =AA14/52/$K14 -> 467.43967 | AE14: =($V14*(1+(($U14/100)*1))) -> 221655.24 | AF14: =($W14*(1+(($U14/100)*1))) -> 256859.02 | AG14: =($X14*(1+(($U14/100)*1))) -> 292062.8 | AH14: =(AE14+(AE14*$J14)+(AE14*$M14)+(AE14*$N14)+(AE14*$O14)+(AE14*$P14)+(AE14*$Q14)+($R14)+(AE14*((52+$S14)/52))*(1+$T14))*1/$L14 -> 707363.96 | AI14: =(AF14+(AF14*$J14)+(AF14*$M14)+(AF14*$N14)+(AF14*$O14)+(AF14*$P14)+(AF14*$Q14)+($R14)+(AF14*((52+$S14)/52))*(1+$T14))*1/$L14 -> 815579.7 | AJ14: =(AG14+(AG14*$J14)+(AG14*$M14)+(AG14*$N14)+(AG14*$O14)+(AG14*$P14)+(AG14*$Q14)+($R14)+(AG14*((52+$S14)/52))*(1+$T14))*1/$L14 -> 923795.44 | AK14: =AH14/52/$K14 -> 357.97771 | AL14: =AI14/52/$K14 -> 412.74276 | AM14: =AJ14/52/$K14 -> 467.50781 | AN14: =($V14*(1+(($U14/100)*2))) -> 221688.49 | AO14: =($W14*(1+(($U14/100)*2))) -> 256897.55 | AP14: =($X14*(1+(($U14/100)*2))) -> 292106.61 | AQ14: =(AN14+(AN14*$J14)+(AN14*$M14)+(AN14*$N14)+(AN14*$O14)+(AN14*$P14)+(AN14*$Q14)+($R14)+(AN14*((52+$S14)/52))*(1+$T14))*1/$L14 -> 707466.14 | AR14: =(AO14+(AO14*$J14)+(AO14*$M14)+(AO14*$N14)+(AO14*$O14)+(AO14*$P14)+(AO14*$Q14)+($R14)+(AO14*((52+$S14)/52))*(1+$T14))*1/$L14 -> 815698.12 | AS14: =(AP14+(AP14*$J14)+(AP14*$M14)+(AP14*$N14)+(AP14*$O14)+(AP14*$P14)+(AP14*$Q14)+($R14)+(AP14*((52+$S14)/52))*(1+$T14))*1/$L14 -> 923930.09 | AT14: =AQ14/52/$K14 -> 358.02943 | AU14: =AR14/52/$K14 -> 412.80269 | AV14: =AS14/52/$K14 -> 467.57596 | AW14: =($V14*(1+(($U14/100)*3))) -> 221721.73 | AX14: =($W14*(1+(($U14/100)*3))) -> 256936.07 | AY14: =($X14*(1+(($U14/100)*3))) -> 292150.41 | AZ14: =(AW14+(AW14*$J14)+(AW14*$M14)+(AW14*$N14)+(AW14*$O14)+(AW14*$P14)+(AW14*$Q14)+($R14)+(AW14*((52+$S14)/52))*(1+$T14))*1/$L14 -> 707568.33 | BA14: =(AX14+(AX14*$J14)+(AX14*$M14)+(AX14*$N14)+(AX14*$O14)+(AX14*$P14)+(AX14*$Q14)+($R14)+(AX14*((52+$S14)/52))*(1+$T14))*1/$L14 -> 815816.54 | BB14: =(AY14+(AY14*$J14)+(AY14*$M14)+(AY14*$N14)+(AY14*$O14)+(AY14*$P14)+(AY14*$Q14)+($R14)+(AY14*((52+$S14)/52))*(1+$T14))*1/$L14 -> 924064.74 | BC14: =AZ14/52/$K14 -> 358.08114 | BD14: =BA14/52/$K14 -> 412.86262 | BE14: =BB14/52/$K14 -> 467.6441 | BF14: =($V14*(1+(($U14/100)*4))) -> 221754.97 | BG14: =($W14*(1+(($U14/100)*4))) -> 256974.59 | BH14: =($X14*(1+(($U14/100)*4))) -> 292194.21 | BI14: =(BF14+(BF14*$J14)+(BF14*$M14)+(BF14*$N14)+(BF14*$O14)+(BF14*$P14)+(BF14*$Q14)+($R14)+(BF14*((52+$S14)/52))*(1+$T14))*1/$L14 -> 707670.52 | BJ14: =(BG14+(BG14*$J14)+(BG14*$M14)+(BG14*$N14)+(BG14*$O14)+(BG14*$P14)+(BG14*$Q14)+($R14)+(BG14*((52+$S14)/52))*(1+$T14))*1/$L14 -> 815934.95 | BK14: =(BH14+(BH14*$J14)+(BH14*$M14)+(BH14*$N14)+(BH14*$O14)+(BH14*$P14)+(BH14*$Q14)+($R14)+(BH14*((52+$S14)/52))*(1+$T14))*1/$L14 -> 924199.39 | BL14: =BI14/52/$K14 -> 358.13286 | BM14: =BJ14/52/$K14 -> 412.92255 | BN14: =BK14/52/$K14 -> 467.71224
A16: NSW | B16: Lab technician | C16: LT | D16: Health Employees (State) Award | E16: Tech Assistant G1-3 | I16: 2022 | J16: 0.105 | K16: 40 | L16: 1 | M16: 0.1 | N16: 0.035 | O16: 0 | P16: 0 | Q16: 0.046 | R16: 0 | S16: 4 | T16: 0 | U16: 0.015 | V16: =1154.19*52 -> 60017.88 | W16: =V16+((X16-V16)/2) -> 77637.56 | X16: =1831.87*52 -> 95257.24 | Y16: =(V16+(V16*$J16)+(V16*$M16)+(V16*$N16)+(V16*$O16)+(V16*$P16)+(V16*$Q16)+($R16)+(V16*((52+$S16)/52))*(1+$T16))*1/$L16 -> 141817.63 | Z16: =(W16+(W16*$J16)+(W16*$M16)+(W16*$N16)+(W16*$O16)+(W16*$P16)+(W16*$Q16)+($R16)+(W16*((52+$S16)/52))*(1+$T16))*1/$L16 -> 183451.58 | AA16: =(X16+(X16*$J16)+(X16*$M16)+(X16*$N16)+(X16*$O16)+(X16*$P16)+(X16*$Q16)+($R16)+(X16*((52+$S16)/52))*(1+$T16))*1/$L16 -> 225085.53 | AB16: =Y16/52/$K16 -> 68.181555 | AC16: =Z16/52/$K16 -> 88.197876 | AD16: =AA16/52/$K16 -> 108.2142 | AE16: =($V16*(1+(($U16/100)*1))) -> 60026.883 | AF16: =($W16*(1+(($U16/100)*1))) -> 77649.206 | AG16: =($X16*(1+(($U16/100)*1))) -> 95271.529 | AH16: =(AE16+(AE16*$J16)+(AE16*$M16)+(AE16*$N16)+(AE16*$O16)+(AE16*$P16)+(AE16*$Q16)+($R16)+(AE16*((52+$S16)/52))*(1+$T16))*1/$L16 -> 141838.91 | AI16: =(AF16+(AF16*$J16)+(AF16*$M16)+(AF16*$N16)+(AF16*$O16)+(AF16*$P16)+(AF16*$Q16)+($R16)+(AF16*((52+$S16)/52))*(1+$T16))*1/$L16 -> 183479.1 | AJ16: =(AG16+(AG16*$J16)+(AG16*$M16)+(AG16*$N16)+(AG16*$O16)+(AG16*$P16)+(AG16*$Q16)+($R16)+(AG16*((52+$S16)/52))*(1+$T16))*1/$L16 -> 225119.29 | AK16: =AH16/52/$K16 -> 68.191782 | AL16: =AI16/52/$K16 -> 88.211106 | AM16: =AJ16/52/$K16 -> 108.23043 | AN16: =($V16*(1+(($U16/100)*2))) -> 60035.885 | AO16: =($W16*(1+(($U16/100)*2))) -> 77660.851 | AP16: =($X16*(1+(($U16/100)*2))) -> 95285.817 | AQ16: =(AN16+(AN16*$J16)+(AN16*$M16)+(AN16*$N16)+(AN16*$O16)+(AN16*$P16)+(AN16*$Q16)+($R16)+(AN16*((52+$S16)/52))*(1+$T16))*1/$L16 -> 141860.18 | AR16: =(AO16+(AO16*$J16)+(AO16*$M16)+(AO16*$N16)+(AO16*$O16)+(AO16*$P16)+(AO16*$Q16)+($R16)+(AO16*((52+$S16)/52))*(1+$T16))*1/$L16 -> 183506.62 | AS16: =(AP16+(AP16*$J16)+(AP16*$M16)+(AP16*$N16)+(AP16*$O16)+(AP16*$P16)+(AP16*$Q16)+($R16)+(AP16*((52+$S16)/52))*(1+$T16))*1/$L16 -> 225153.06 | AT16: =AQ16/52/$K16 -> 68.202009 | AU16: =AR16/52/$K16 -> 88.224335 | AV16: =AS16/52/$K16 -> 108.24666 | AW16: =($V16*(1+(($U16/100)*3))) -> 60044.888 | AX16: =($W16*(1+(($U16/100)*3))) -> 77672.497 | AY16: =($X16*(1+(($U16/100)*3))) -> 95300.106 | AZ16: =(AW16+(AW16*$J16)+(AW16*$M16)+(AW16*$N16)+(AW16*$O16)+(AW16*$P16)+(AW16*$Q16)+($R16)+(AW16*((52+$S16)/52))*(1+$T16))*1/$L16 -> 141881.45 | BA16: =(AX16+(AX16*$J16)+(AX16*$M16)+(AX16*$N16)+(AX16*$O16)+(AX16*$P16)+(AX16*$Q16)+($R16)+(AX16*((52+$S16)/52))*(1+$T16))*1/$L16 -> 183534.14 | BB16: =(AY16+(AY16*$J16)+(AY16*$M16)+(AY16*$N16)+(AY16*$O16)+(AY16*$P16)+(AY16*$Q16)+($R16)+(AY16*((52+$S16)/52))*(1+$T16))*1/$L16 -> 225186.82 | BC16: =AZ16/52/$K16 -> 68.212236 | BD16: =BA16/52/$K16 -> 88.237565 | BE16: =BB16/52/$K16 -> 108.26289 | BF16: =($V16*(1+(($U16/100)*4))) -> 60053.891 | BG16: =($W16*(1+(($U16/100)*4))) -> 77684.143 | BH16: =($X16*(1+(($U16/100)*4))) -> 95314.394 | BI16: =(BF16+(BF16*$J16)+(BF16*$M16)+(BF16*$N16)+(BF16*$O16)+(BF16*$P16)+(BF16*$Q16)+($R16)+(BF16*((52+$S16)/52))*(1+$T16))*1/$L16 -> 141902.72 | BJ16: =(BG16+(BG16*$J16)+(BG16*$M16)+(BG16*$N16)+(BG16*$O16)+(BG16*$P16)+(BG16*$Q16)+($R16)+(BG16*((52+$S16)/52))*(1+$T16))*1/$L16 -> 183561.65 | BK16: =(BH16+(BH16*$J16)+(BH16*$M16)+(BH16*$N16)+(BH16*$O16)+(BH16*$P16)+(BH16*$Q16)+($R16)+(BH16*((52+$S16)/52))*(1+$T16))*1/$L16 -> 225220.58 | BL16: =BI16/52/$K16 -> 68.222464 | BM16: =BJ16/52/$K16 -> 88.250795 | BN16: =BK16/52/$K16 -> 108.27913
